package com.amap.api.location;

import android.app.PendingIntent;
import android.content.Context;
import android.os.Bundle;
import com.amap.api.location.core.AMapLocException;
import com.aps.j;
import com.aps.k;

public class c
  implements Runnable
{
  k a = null;
  volatile boolean b = false;
  boolean c = true;
  private volatile boolean d = false;
  private Context e;
  private long f = 2000L;
  private a.a g;
  private a h;
  private boolean i = false;
  
  c(Context paramContext, a.a parama, a parama1)
  {
    this.h = parama1;
    b(false);
    this.e = paramContext;
    this.a = new com.aps.a();
    this.g = parama;
  }
  
  private AMapLocation a(com.aps.c paramc)
  {
    AMapLocation localAMapLocation = new AMapLocation("");
    localAMapLocation.setProvider("lbs");
    localAMapLocation.setLatitude(paramc.f());
    localAMapLocation.setLongitude(paramc.e());
    localAMapLocation.setAccuracy(paramc.g());
    localAMapLocation.setTime(paramc.h());
    localAMapLocation.setPoiId(paramc.b());
    localAMapLocation.setFloor(paramc.c());
    localAMapLocation.setCountry(paramc.n());
    localAMapLocation.setRoad(paramc.q());
    localAMapLocation.setPoiName(paramc.s());
    localAMapLocation.setAMapException(paramc.a());
    Object localObject = new Bundle();
    ((Bundle)localObject).putString("citycode", paramc.k());
    ((Bundle)localObject).putString("desc", paramc.l());
    ((Bundle)localObject).putString("adcode", paramc.m());
    localAMapLocation.setExtras((Bundle)localObject);
    localObject = paramc.k();
    String str1 = paramc.l();
    String str2 = paramc.m();
    localAMapLocation.setCityCode((String)localObject);
    localAMapLocation.setAdCode(str2);
    if (str2 == null) {
      localAMapLocation.b(str1);
    }
    for (;;)
    {
      localAMapLocation.setCity(paramc.p());
      localAMapLocation.setDistrict(paramc.d());
      localAMapLocation.a(paramc.r());
      localAMapLocation.setProvince(paramc.o());
      return localAMapLocation;
      if (str2.trim().length() <= 0) {
        break;
      }
      localAMapLocation.b(str1.replace(" ", ""));
    }
  }
  
  /* Error */
  private void d()
  {
    // Byte code:
    //   0: aload_0
    //   1: getfield 47	com/amap/api/location/c:e	Landroid/content/Context;
    //   4: invokestatic 212	com/amap/api/location/core/c:a	(Landroid/content/Context;)Lcom/amap/api/location/core/c;
    //   7: pop
    //   8: aload_0
    //   9: getfield 28	com/amap/api/location/c:a	Lcom/aps/k;
    //   12: ifnonnull +118 -> 130
    //   15: aload_0
    //   16: getfield 28	com/amap/api/location/c:a	Lcom/aps/k;
    //   19: ifnonnull +135 -> 154
    //   22: new 214	org/json/JSONObject
    //   25: dup
    //   26: invokespecial 215	org/json/JSONObject:<init>	()V
    //   29: astore_1
    //   30: aload_1
    //   31: ldc -39
    //   33: aload_0
    //   34: getfield 47	com/amap/api/location/c:e	Landroid/content/Context;
    //   37: invokestatic 220	com/amap/api/location/core/c:b	(Landroid/content/Context;)Ljava/lang/String;
    //   40: invokevirtual 224	org/json/JSONObject:put	(Ljava/lang/String;Ljava/lang/Object;)Lorg/json/JSONObject;
    //   43: pop
    //   44: aload_1
    //   45: ldc -30
    //   47: aload_0
    //   48: getfield 47	com/amap/api/location/c:e	Landroid/content/Context;
    //   51: invokestatic 212	com/amap/api/location/core/c:a	(Landroid/content/Context;)Lcom/amap/api/location/core/c;
    //   54: ldc -28
    //   56: invokevirtual 231	com/amap/api/location/core/c:a	(Ljava/lang/String;)Ljava/lang/String;
    //   59: invokevirtual 224	org/json/JSONObject:put	(Ljava/lang/String;Ljava/lang/Object;)Lorg/json/JSONObject;
    //   62: pop
    //   63: new 214	org/json/JSONObject
    //   66: dup
    //   67: invokespecial 215	org/json/JSONObject:<init>	()V
    //   70: astore_2
    //   71: aload_0
    //   72: getfield 47	com/amap/api/location/c:e	Landroid/content/Context;
    //   75: invokestatic 212	com/amap/api/location/core/c:a	(Landroid/content/Context;)Lcom/amap/api/location/core/c;
    //   78: invokevirtual 232	com/amap/api/location/core/c:c	()Ljava/lang/String;
    //   81: astore_3
    //   82: aload_2
    //   83: ldc -22
    //   85: aload_3
    //   86: ldc -20
    //   88: invokevirtual 240	java/lang/String:getBytes	(Ljava/lang/String;)[B
    //   91: invokestatic 245	com/aps/b:a	([B)Ljava/lang/String;
    //   94: invokevirtual 224	org/json/JSONObject:put	(Ljava/lang/String;Ljava/lang/Object;)Lorg/json/JSONObject;
    //   97: pop
    //   98: aload_1
    //   99: ldc -9
    //   101: aload_2
    //   102: invokevirtual 224	org/json/JSONObject:put	(Ljava/lang/String;Ljava/lang/Object;)Lorg/json/JSONObject;
    //   105: pop
    //   106: aload_1
    //   107: ldc -7
    //   109: ldc -5
    //   111: invokevirtual 224	org/json/JSONObject:put	(Ljava/lang/String;Ljava/lang/Object;)Lorg/json/JSONObject;
    //   114: pop
    //   115: aload_0
    //   116: getfield 28	com/amap/api/location/c:a	Lcom/aps/k;
    //   119: astore_2
    //   120: aload_2
    //   121: ifnonnull +107 -> 228
    //   124: aload_0
    //   125: iconst_1
    //   126: putfield 38	com/amap/api/location/c:i	Z
    //   129: return
    //   130: aload_0
    //   131: getfield 28	com/amap/api/location/c:a	Lcom/aps/k;
    //   134: aload_0
    //   135: getfield 47	com/amap/api/location/c:e	Landroid/content/Context;
    //   138: invokeinterface 256 2 0
    //   143: goto -128 -> 15
    //   146: astore_1
    //   147: aload_1
    //   148: invokevirtual 259	org/json/JSONException:printStackTrace	()V
    //   151: goto -27 -> 124
    //   154: aload_0
    //   155: getfield 28	com/amap/api/location/c:a	Lcom/aps/k;
    //   158: new 261	java/lang/StringBuilder
    //   161: dup
    //   162: invokespecial 262	java/lang/StringBuilder:<init>	()V
    //   165: ldc_w 264
    //   168: invokevirtual 268	java/lang/StringBuilder:append	(Ljava/lang/String;)Ljava/lang/StringBuilder;
    //   171: aload_0
    //   172: getfield 47	com/amap/api/location/c:e	Landroid/content/Context;
    //   175: invokestatic 220	com/amap/api/location/core/c:b	(Landroid/content/Context;)Ljava/lang/String;
    //   178: invokevirtual 268	java/lang/StringBuilder:append	(Ljava/lang/String;)Ljava/lang/StringBuilder;
    //   181: ldc_w 270
    //   184: invokevirtual 268	java/lang/StringBuilder:append	(Ljava/lang/String;)Ljava/lang/StringBuilder;
    //   187: invokestatic 271	com/amap/api/location/core/c:b	()Ljava/lang/String;
    //   190: invokevirtual 268	java/lang/StringBuilder:append	(Ljava/lang/String;)Ljava/lang/StringBuilder;
    //   193: invokevirtual 274	java/lang/StringBuilder:toString	()Ljava/lang/String;
    //   196: invokeinterface 275 2 0
    //   201: goto -179 -> 22
    //   204: astore_1
    //   205: aload_1
    //   206: invokevirtual 276	java/lang/Throwable:printStackTrace	()V
    //   209: goto -85 -> 124
    //   212: astore_2
    //   213: aload_2
    //   214: invokevirtual 276	java/lang/Throwable:printStackTrace	()V
    //   217: goto -154 -> 63
    //   220: astore_3
    //   221: aload_3
    //   222: invokevirtual 277	java/io/UnsupportedEncodingException:printStackTrace	()V
    //   225: goto -127 -> 98
    //   228: aload_0
    //   229: getfield 28	com/amap/api/location/c:a	Lcom/aps/k;
    //   232: aload_1
    //   233: invokeinterface 280 2 0
    //   238: goto -114 -> 124
    // Local variable table:
    //   start	length	slot	name	signature
    //   0	241	0	this	c
    //   29	78	1	localJSONObject	org.json.JSONObject
    //   146	2	1	localJSONException	org.json.JSONException
    //   204	29	1	localThrowable1	Throwable
    //   70	51	2	localObject	Object
    //   212	2	2	localThrowable2	Throwable
    //   81	5	3	str	String
    //   220	2	3	localUnsupportedEncodingException	java.io.UnsupportedEncodingException
    // Exception table:
    //   from	to	target	type
    //   0	15	146	org/json/JSONException
    //   15	22	146	org/json/JSONException
    //   22	44	146	org/json/JSONException
    //   44	63	146	org/json/JSONException
    //   63	82	146	org/json/JSONException
    //   82	98	146	org/json/JSONException
    //   98	120	146	org/json/JSONException
    //   130	143	146	org/json/JSONException
    //   154	201	146	org/json/JSONException
    //   213	217	146	org/json/JSONException
    //   221	225	146	org/json/JSONException
    //   228	238	146	org/json/JSONException
    //   0	15	204	java/lang/Throwable
    //   15	22	204	java/lang/Throwable
    //   22	44	204	java/lang/Throwable
    //   63	82	204	java/lang/Throwable
    //   82	98	204	java/lang/Throwable
    //   98	120	204	java/lang/Throwable
    //   130	143	204	java/lang/Throwable
    //   154	201	204	java/lang/Throwable
    //   213	217	204	java/lang/Throwable
    //   221	225	204	java/lang/Throwable
    //   228	238	204	java/lang/Throwable
    //   44	63	212	java/lang/Throwable
    //   82	98	220	java/io/UnsupportedEncodingException
  }
  
  private com.aps.c e()
    throws Exception
  {
    com.aps.c localc = f();
    if (localc != null) {
      return localc;
    }
    localc = new com.aps.c();
    localc.a(new AMapLocException("未知的错误"));
    this.c = false;
    return localc;
  }
  
  private com.aps.c f()
  {
    Object localObject2 = null;
    com.aps.c localc = null;
    Object localObject1 = localObject2;
    try
    {
      if (this.a == null) {}
      while (localc != null)
      {
        localObject1 = localc;
        this.c = true;
        return localc;
        localObject1 = localObject2;
        localc = this.a.a();
      }
      localObject1 = localc;
      this.c = false;
      return localc;
    }
    catch (AMapLocException localAMapLocException)
    {
      localObject1 = new com.aps.c();
      ((com.aps.c)localObject1).a(localAMapLocException);
      this.c = false;
      return (com.aps.c)localObject1;
    }
    catch (Throwable localThrowable)
    {
      this.c = false;
      localThrowable.printStackTrace();
    }
    return (com.aps.c)localObject1;
  }
  
  private boolean g()
  {
    if (System.currentTimeMillis() - this.h.d <= this.f * 5L) {}
    for (int j = 1; j == 0; j = 0)
    {
      this.h.c = false;
      return true;
    }
    return false;
  }
  
  void a(long paramLong)
  {
    if (paramLong <= this.f) {}
    for (int j = 1;; j = 0)
    {
      if (j == 0) {
        this.f = paramLong;
      }
      return;
    }
  }
  
  void a(PendingIntent paramPendingIntent)
  {
    this.a.a(paramPendingIntent);
  }
  
  void a(j paramj, PendingIntent paramPendingIntent)
  {
    this.a.a(paramj, paramPendingIntent);
  }
  
  void a(boolean paramBoolean)
  {
    try
    {
      this.b = paramBoolean;
      return;
    }
    finally
    {
      localObject = finally;
      throw ((Throwable)localObject);
    }
  }
  
  public boolean a()
  {
    try
    {
      boolean bool = this.b;
      return bool;
    }
    finally
    {
      localObject = finally;
      throw ((Throwable)localObject);
    }
  }
  
  void b()
  {
    for (;;)
    {
      try
      {
        a(true);
        if (this.d)
        {
          if (this.h == null) {
            this.i = false;
          }
        }
        else
        {
          c();
          continue;
        }
        this.h.b();
      }
      finally {}
    }
  }
  
  void b(PendingIntent paramPendingIntent)
  {
    this.a.b(paramPendingIntent);
  }
  
  void b(j paramj, PendingIntent paramPendingIntent)
  {
    this.a.b(paramj, paramPendingIntent);
  }
  
  void b(boolean paramBoolean)
  {
    try
    {
      this.d = paramBoolean;
      return;
    }
    finally
    {
      localObject = finally;
      throw ((Throwable)localObject);
    }
  }
  
  /* Error */
  void c()
  {
    // Byte code:
    //   0: aload_0
    //   1: monitorenter
    //   2: aload_0
    //   3: getfield 28	com/amap/api/location/c:a	Lcom/aps/k;
    //   6: ifnonnull +11 -> 17
    //   9: aload_0
    //   10: aconst_null
    //   11: putfield 28	com/amap/api/location/c:a	Lcom/aps/k;
    //   14: aload_0
    //   15: monitorexit
    //   16: return
    //   17: aload_0
    //   18: getfield 28	com/amap/api/location/c:a	Lcom/aps/k;
    //   21: invokeinterface 326 1 0
    //   26: goto -17 -> 9
    //   29: astore_1
    //   30: aload_0
    //   31: monitorexit
    //   32: aload_1
    //   33: athrow
    // Local variable table:
    //   start	length	slot	name	signature
    //   0	34	0	this	c
    //   29	4	1	localObject	Object
    // Exception table:
    //   from	to	target	type
    //   2	9	29	finally
    //   9	14	29	finally
    //   17	26	29	finally
  }
  
  /* Error */
  public void run()
  {
    // Byte code:
    //   0: invokestatic 332	android/os/Looper:prepare	()V
    //   3: aload_0
    //   4: invokevirtual 334	com/amap/api/location/c:a	()Z
    //   7: ifne +29 -> 36
    //   10: aload_0
    //   11: getfield 38	com/amap/api/location/c:i	Z
    //   14: ifeq +27 -> 41
    //   17: aload_0
    //   18: getfield 30	com/amap/api/location/c:d	Z
    //   21: istore_2
    //   22: iload_2
    //   23: ifne +40 -> 63
    //   26: aload_0
    //   27: invokevirtual 334	com/amap/api/location/c:a	()Z
    //   30: istore_2
    //   31: iload_2
    //   32: ifne +203 -> 235
    //   35: return
    //   36: aload_0
    //   37: invokevirtual 319	com/amap/api/location/c:c	()V
    //   40: return
    //   41: aload_0
    //   42: getfield 30	com/amap/api/location/c:d	Z
    //   45: ifeq -28 -> 17
    //   48: aload_0
    //   49: invokespecial 336	com/amap/api/location/c:d	()V
    //   52: goto -35 -> 17
    //   55: astore_3
    //   56: aload_3
    //   57: invokevirtual 276	java/lang/Throwable:printStackTrace	()V
    //   60: goto -34 -> 26
    //   63: invokestatic 342	java/lang/Thread:currentThread	()Ljava/lang/Thread;
    //   66: invokevirtual 345	java/lang/Thread:isInterrupted	()Z
    //   69: ifne -43 -> 26
    //   72: aload_0
    //   73: invokevirtual 334	com/amap/api/location/c:a	()Z
    //   76: istore_2
    //   77: iload_2
    //   78: ifne -52 -> 26
    //   81: aload_0
    //   82: getfield 42	com/amap/api/location/c:h	Lcom/amap/api/location/a;
    //   85: getfield 309	com/amap/api/location/a:c	Z
    //   88: ifne +53 -> 141
    //   91: aload_0
    //   92: getfield 42	com/amap/api/location/c:h	Lcom/amap/api/location/a;
    //   95: getfield 347	com/amap/api/location/a:e	Z
    //   98: ifeq +52 -> 150
    //   101: aload_0
    //   102: invokespecial 349	com/amap/api/location/c:e	()Lcom/aps/c;
    //   105: astore_3
    //   106: aload_3
    //   107: ifnonnull +80 -> 187
    //   110: aconst_null
    //   111: astore_3
    //   112: aload_3
    //   113: ifnonnull +201 -> 314
    //   116: invokestatic 353	com/amap/api/location/core/a:a	()I
    //   119: istore_1
    //   120: iload_1
    //   121: iconst_m1
    //   122: if_icmpeq +257 -> 379
    //   125: aload_0
    //   126: getfield 40	com/amap/api/location/c:c	Z
    //   129: ifne +261 -> 390
    //   132: ldc2_w 354
    //   135: invokestatic 358	java/lang/Thread:sleep	(J)V
    //   138: goto -121 -> 17
    //   141: aload_0
    //   142: invokespecial 360	com/amap/api/location/c:g	()Z
    //   145: istore_2
    //   146: iload_2
    //   147: ifne -56 -> 91
    //   150: aload_0
    //   151: iconst_1
    //   152: putfield 40	com/amap/api/location/c:c	Z
    //   155: aload_0
    //   156: getfield 34	com/amap/api/location/c:f	J
    //   159: invokestatic 358	java/lang/Thread:sleep	(J)V
    //   162: invokestatic 353	com/amap/api/location/core/a:a	()I
    //   165: istore_1
    //   166: iload_1
    //   167: iconst_m1
    //   168: if_icmpeq +125 -> 293
    //   171: aload_0
    //   172: getfield 40	com/amap/api/location/c:c	Z
    //   175: ifne +129 -> 304
    //   178: ldc2_w 354
    //   181: invokestatic 358	java/lang/Thread:sleep	(J)V
    //   184: goto -167 -> 17
    //   187: aload_0
    //   188: aload_3
    //   189: invokespecial 362	com/amap/api/location/c:a	(Lcom/aps/c;)Lcom/amap/api/location/AMapLocation;
    //   192: astore_3
    //   193: goto -81 -> 112
    //   196: astore_3
    //   197: aload_3
    //   198: invokevirtual 276	java/lang/Throwable:printStackTrace	()V
    //   201: invokestatic 353	com/amap/api/location/core/a:a	()I
    //   204: istore_1
    //   205: iload_1
    //   206: iconst_m1
    //   207: if_icmpeq +193 -> 400
    //   210: aload_0
    //   211: getfield 40	com/amap/api/location/c:c	Z
    //   214: ifne +197 -> 411
    //   217: ldc2_w 354
    //   220: invokestatic 358	java/lang/Thread:sleep	(J)V
    //   223: goto -206 -> 17
    //   226: aload_0
    //   227: getfield 34	com/amap/api/location/c:f	J
    //   230: invokestatic 358	java/lang/Thread:sleep	(J)V
    //   233: aload_3
    //   234: athrow
    //   235: aload_0
    //   236: invokevirtual 319	com/amap/api/location/c:c	()V
    //   239: return
    //   240: astore_3
    //   241: aload_3
    //   242: invokevirtual 276	java/lang/Throwable:printStackTrace	()V
    //   245: return
    //   246: astore_3
    //   247: invokestatic 353	com/amap/api/location/core/a:a	()I
    //   250: istore_1
    //   251: iload_1
    //   252: iconst_m1
    //   253: if_icmpeq +19 -> 272
    //   256: aload_0
    //   257: getfield 40	com/amap/api/location/c:c	Z
    //   260: ifne +23 -> 283
    //   263: ldc2_w 354
    //   266: invokestatic 358	java/lang/Thread:sleep	(J)V
    //   269: goto -243 -> 26
    //   272: aload_0
    //   273: getfield 47	com/amap/api/location/c:e	Landroid/content/Context;
    //   276: invokestatic 365	com/amap/api/location/core/a:a	(Landroid/content/Context;)Z
    //   279: pop
    //   280: goto -24 -> 256
    //   283: aload_0
    //   284: getfield 34	com/amap/api/location/c:f	J
    //   287: invokestatic 358	java/lang/Thread:sleep	(J)V
    //   290: goto -264 -> 26
    //   293: aload_0
    //   294: getfield 47	com/amap/api/location/c:e	Landroid/content/Context;
    //   297: invokestatic 365	com/amap/api/location/core/a:a	(Landroid/content/Context;)Z
    //   300: pop
    //   301: goto -130 -> 171
    //   304: aload_0
    //   305: getfield 34	com/amap/api/location/c:f	J
    //   308: invokestatic 358	java/lang/Thread:sleep	(J)V
    //   311: goto -294 -> 17
    //   314: aload_0
    //   315: getfield 42	com/amap/api/location/c:h	Lcom/amap/api/location/a;
    //   318: getfield 347	com/amap/api/location/a:e	Z
    //   321: ifeq -205 -> 116
    //   324: aload_0
    //   325: getfield 42	com/amap/api/location/c:h	Lcom/amap/api/location/a;
    //   328: getfield 309	com/amap/api/location/a:c	Z
    //   331: ifne +38 -> 369
    //   334: new 367	android/os/Message
    //   337: dup
    //   338: invokespecial 368	android/os/Message:<init>	()V
    //   341: astore 4
    //   343: aload 4
    //   345: aload_3
    //   346: putfield 372	android/os/Message:obj	Ljava/lang/Object;
    //   349: aload 4
    //   351: bipush 100
    //   353: putfield 376	android/os/Message:what	I
    //   356: aload_0
    //   357: getfield 52	com/amap/api/location/c:g	Lcom/amap/api/location/a$a;
    //   360: aload 4
    //   362: invokevirtual 382	com/amap/api/location/a$a:sendMessage	(Landroid/os/Message;)Z
    //   365: pop
    //   366: goto -250 -> 116
    //   369: aload_0
    //   370: invokespecial 360	com/amap/api/location/c:g	()Z
    //   373: ifne -39 -> 334
    //   376: goto -260 -> 116
    //   379: aload_0
    //   380: getfield 47	com/amap/api/location/c:e	Landroid/content/Context;
    //   383: invokestatic 365	com/amap/api/location/core/a:a	(Landroid/content/Context;)Z
    //   386: pop
    //   387: goto -262 -> 125
    //   390: aload_0
    //   391: getfield 34	com/amap/api/location/c:f	J
    //   394: invokestatic 358	java/lang/Thread:sleep	(J)V
    //   397: goto -380 -> 17
    //   400: aload_0
    //   401: getfield 47	com/amap/api/location/c:e	Landroid/content/Context;
    //   404: invokestatic 365	com/amap/api/location/core/a:a	(Landroid/content/Context;)Z
    //   407: pop
    //   408: goto -198 -> 210
    //   411: aload_0
    //   412: getfield 34	com/amap/api/location/c:f	J
    //   415: invokestatic 358	java/lang/Thread:sleep	(J)V
    //   418: goto -401 -> 17
    //   421: astore_3
    //   422: invokestatic 353	com/amap/api/location/core/a:a	()I
    //   425: istore_1
    //   426: iload_1
    //   427: iconst_m1
    //   428: if_icmpeq +19 -> 447
    //   431: aload_0
    //   432: getfield 40	com/amap/api/location/c:c	Z
    //   435: ifne -209 -> 226
    //   438: ldc2_w 354
    //   441: invokestatic 358	java/lang/Thread:sleep	(J)V
    //   444: goto -211 -> 233
    //   447: aload_0
    //   448: getfield 47	com/amap/api/location/c:e	Landroid/content/Context;
    //   451: invokestatic 365	com/amap/api/location/core/a:a	(Landroid/content/Context;)Z
    //   454: pop
    //   455: goto -24 -> 431
    // Local variable table:
    //   start	length	slot	name	signature
    //   0	458	0	this	c
    //   119	310	1	j	int
    //   21	126	2	bool	boolean
    //   55	2	3	localThrowable1	Throwable
    //   105	88	3	localObject1	Object
    //   196	38	3	localThrowable2	Throwable
    //   240	2	3	localThrowable3	Throwable
    //   246	100	3	localThrowable4	Throwable
    //   421	1	3	localObject2	Object
    //   341	20	4	localMessage	android.os.Message
    // Exception table:
    //   from	to	target	type
    //   0	17	55	java/lang/Throwable
    //   17	22	55	java/lang/Throwable
    //   36	40	55	java/lang/Throwable
    //   41	52	55	java/lang/Throwable
    //   63	77	55	java/lang/Throwable
    //   116	120	55	java/lang/Throwable
    //   125	138	55	java/lang/Throwable
    //   162	166	55	java/lang/Throwable
    //   171	184	55	java/lang/Throwable
    //   201	205	55	java/lang/Throwable
    //   210	223	55	java/lang/Throwable
    //   226	233	55	java/lang/Throwable
    //   233	235	55	java/lang/Throwable
    //   247	251	55	java/lang/Throwable
    //   256	269	55	java/lang/Throwable
    //   272	280	55	java/lang/Throwable
    //   283	290	55	java/lang/Throwable
    //   293	301	55	java/lang/Throwable
    //   304	311	55	java/lang/Throwable
    //   314	334	55	java/lang/Throwable
    //   334	366	55	java/lang/Throwable
    //   369	376	55	java/lang/Throwable
    //   379	387	55	java/lang/Throwable
    //   390	397	55	java/lang/Throwable
    //   400	408	55	java/lang/Throwable
    //   411	418	55	java/lang/Throwable
    //   422	426	55	java/lang/Throwable
    //   431	444	55	java/lang/Throwable
    //   447	455	55	java/lang/Throwable
    //   81	91	196	java/lang/Throwable
    //   91	106	196	java/lang/Throwable
    //   141	146	196	java/lang/Throwable
    //   187	193	196	java/lang/Throwable
    //   26	31	240	java/lang/Throwable
    //   235	239	240	java/lang/Throwable
    //   150	162	246	java/lang/Throwable
    //   81	91	421	finally
    //   91	106	421	finally
    //   141	146	421	finally
    //   150	162	421	finally
    //   187	193	421	finally
    //   197	201	421	finally
  }
}


/* Location:              /Users/joshua/Desktop/system_framework/classes-dex2jar.jar!/com/amap/api/location/c.class
 * Java compiler version: 6 (50.0)
 * JD-Core Version:       0.7.1
 */