package android.media.session;

import android.app.PendingIntent;
import android.content.pm.ParceledListSlice;
import android.media.MediaMetadata;
import android.media.Rating;
import android.net.Uri;
import android.os.Binder;
import android.os.Bundle;
import android.os.IBinder;
import android.os.IInterface;
import android.os.Parcel;
import android.os.Parcelable.Creator;
import android.os.RemoteException;
import android.os.ResultReceiver;
import android.text.TextUtils;
import android.view.KeyEvent;

public abstract interface ISessionController
  extends IInterface
{
  public abstract void adjustVolume(int paramInt1, int paramInt2, String paramString)
    throws RemoteException;
  
  public abstract void fastForward()
    throws RemoteException;
  
  public abstract Bundle getExtras()
    throws RemoteException;
  
  public abstract long getFlags()
    throws RemoteException;
  
  public abstract PendingIntent getLaunchPendingIntent()
    throws RemoteException;
  
  public abstract MediaMetadata getMetadata()
    throws RemoteException;
  
  public abstract String getPackageName()
    throws RemoteException;
  
  public abstract PlaybackState getPlaybackState()
    throws RemoteException;
  
  public abstract ParceledListSlice getQueue()
    throws RemoteException;
  
  public abstract CharSequence getQueueTitle()
    throws RemoteException;
  
  public abstract int getRatingType()
    throws RemoteException;
  
  public abstract void getRemoteControlClientNowPlayingEntries()
    throws RemoteException;
  
  public abstract String getTag()
    throws RemoteException;
  
  public abstract ParcelableVolumeInfo getVolumeAttributes()
    throws RemoteException;
  
  public abstract boolean isTransportControlEnabled()
    throws RemoteException;
  
  public abstract void next()
    throws RemoteException;
  
  public abstract void pause()
    throws RemoteException;
  
  public abstract void play()
    throws RemoteException;
  
  public abstract void playFromMediaId(String paramString, Bundle paramBundle)
    throws RemoteException;
  
  public abstract void playFromSearch(String paramString, Bundle paramBundle)
    throws RemoteException;
  
  public abstract void playFromUri(Uri paramUri, Bundle paramBundle)
    throws RemoteException;
  
  public abstract void prepare()
    throws RemoteException;
  
  public abstract void prepareFromMediaId(String paramString, Bundle paramBundle)
    throws RemoteException;
  
  public abstract void prepareFromSearch(String paramString, Bundle paramBundle)
    throws RemoteException;
  
  public abstract void prepareFromUri(Uri paramUri, Bundle paramBundle)
    throws RemoteException;
  
  public abstract void previous()
    throws RemoteException;
  
  public abstract void rate(Rating paramRating)
    throws RemoteException;
  
  public abstract void registerCallbackListener(ISessionControllerCallback paramISessionControllerCallback)
    throws RemoteException;
  
  public abstract void rewind()
    throws RemoteException;
  
  public abstract void seekTo(long paramLong)
    throws RemoteException;
  
  public abstract void sendCommand(String paramString, Bundle paramBundle, ResultReceiver paramResultReceiver)
    throws RemoteException;
  
  public abstract void sendCustomAction(String paramString, Bundle paramBundle)
    throws RemoteException;
  
  public abstract boolean sendMediaButton(KeyEvent paramKeyEvent)
    throws RemoteException;
  
  public abstract void setRemoteControlClientBrowsedPlayer()
    throws RemoteException;
  
  public abstract void setRemoteControlClientPlayItem(long paramLong, int paramInt)
    throws RemoteException;
  
  public abstract void setVolumeTo(int paramInt1, int paramInt2, String paramString)
    throws RemoteException;
  
  public abstract void skipToQueueItem(long paramLong)
    throws RemoteException;
  
  public abstract void stop()
    throws RemoteException;
  
  public abstract void unregisterCallbackListener(ISessionControllerCallback paramISessionControllerCallback)
    throws RemoteException;
  
  public static abstract class Stub
    extends Binder
    implements ISessionController
  {
    private static final String DESCRIPTOR = "android.media.session.ISessionController";
    static final int TRANSACTION_adjustVolume = 11;
    static final int TRANSACTION_fastForward = 26;
    static final int TRANSACTION_getExtras = 38;
    static final int TRANSACTION_getFlags = 9;
    static final int TRANSACTION_getLaunchPendingIntent = 8;
    static final int TRANSACTION_getMetadata = 34;
    static final int TRANSACTION_getPackageName = 6;
    static final int TRANSACTION_getPlaybackState = 35;
    static final int TRANSACTION_getQueue = 36;
    static final int TRANSACTION_getQueueTitle = 37;
    static final int TRANSACTION_getRatingType = 39;
    static final int TRANSACTION_getRemoteControlClientNowPlayingEntries = 31;
    static final int TRANSACTION_getTag = 7;
    static final int TRANSACTION_getVolumeAttributes = 10;
    static final int TRANSACTION_isTransportControlEnabled = 5;
    static final int TRANSACTION_next = 24;
    static final int TRANSACTION_pause = 22;
    static final int TRANSACTION_play = 17;
    static final int TRANSACTION_playFromMediaId = 18;
    static final int TRANSACTION_playFromSearch = 19;
    static final int TRANSACTION_playFromUri = 20;
    static final int TRANSACTION_prepare = 13;
    static final int TRANSACTION_prepareFromMediaId = 14;
    static final int TRANSACTION_prepareFromSearch = 15;
    static final int TRANSACTION_prepareFromUri = 16;
    static final int TRANSACTION_previous = 25;
    static final int TRANSACTION_rate = 32;
    static final int TRANSACTION_registerCallbackListener = 3;
    static final int TRANSACTION_rewind = 27;
    static final int TRANSACTION_seekTo = 28;
    static final int TRANSACTION_sendCommand = 1;
    static final int TRANSACTION_sendCustomAction = 33;
    static final int TRANSACTION_sendMediaButton = 2;
    static final int TRANSACTION_setRemoteControlClientBrowsedPlayer = 29;
    static final int TRANSACTION_setRemoteControlClientPlayItem = 30;
    static final int TRANSACTION_setVolumeTo = 12;
    static final int TRANSACTION_skipToQueueItem = 21;
    static final int TRANSACTION_stop = 23;
    static final int TRANSACTION_unregisterCallbackListener = 4;
    
    public Stub()
    {
      attachInterface(this, "android.media.session.ISessionController");
    }
    
    public static ISessionController asInterface(IBinder paramIBinder)
    {
      if (paramIBinder == null) {
        return null;
      }
      IInterface localIInterface = paramIBinder.queryLocalInterface("android.media.session.ISessionController");
      if ((localIInterface != null) && ((localIInterface instanceof ISessionController))) {
        return (ISessionController)localIInterface;
      }
      return new Proxy(paramIBinder);
    }
    
    public IBinder asBinder()
    {
      return this;
    }
    
    public boolean onTransact(int paramInt1, Parcel paramParcel1, Parcel paramParcel2, int paramInt2)
      throws RemoteException
    {
      Object localObject;
      label424:
      boolean bool;
      switch (paramInt1)
      {
      default: 
        return super.onTransact(paramInt1, paramParcel1, paramParcel2, paramInt2);
      case 1598968902: 
        paramParcel2.writeString("android.media.session.ISessionController");
        return true;
      case 1: 
        paramParcel1.enforceInterface("android.media.session.ISessionController");
        String str = paramParcel1.readString();
        if (paramParcel1.readInt() != 0)
        {
          localObject = (Bundle)Bundle.CREATOR.createFromParcel(paramParcel1);
          if (paramParcel1.readInt() == 0) {
            break label424;
          }
        }
        for (paramParcel1 = (ResultReceiver)ResultReceiver.CREATOR.createFromParcel(paramParcel1);; paramParcel1 = null)
        {
          sendCommand(str, (Bundle)localObject, paramParcel1);
          paramParcel2.writeNoException();
          return true;
          localObject = null;
          break;
        }
      case 2: 
        paramParcel1.enforceInterface("android.media.session.ISessionController");
        if (paramParcel1.readInt() != 0)
        {
          paramParcel1 = (KeyEvent)KeyEvent.CREATOR.createFromParcel(paramParcel1);
          bool = sendMediaButton(paramParcel1);
          paramParcel2.writeNoException();
          if (!bool) {
            break label485;
          }
        }
        for (paramInt1 = 1;; paramInt1 = 0)
        {
          paramParcel2.writeInt(paramInt1);
          return true;
          paramParcel1 = null;
          break;
        }
      case 3: 
        paramParcel1.enforceInterface("android.media.session.ISessionController");
        registerCallbackListener(ISessionControllerCallback.Stub.asInterface(paramParcel1.readStrongBinder()));
        paramParcel2.writeNoException();
        return true;
      case 4: 
        paramParcel1.enforceInterface("android.media.session.ISessionController");
        unregisterCallbackListener(ISessionControllerCallback.Stub.asInterface(paramParcel1.readStrongBinder()));
        paramParcel2.writeNoException();
        return true;
      case 5: 
        paramParcel1.enforceInterface("android.media.session.ISessionController");
        bool = isTransportControlEnabled();
        paramParcel2.writeNoException();
        if (bool) {}
        for (paramInt1 = 1;; paramInt1 = 0)
        {
          paramParcel2.writeInt(paramInt1);
          return true;
        }
      case 6: 
        paramParcel1.enforceInterface("android.media.session.ISessionController");
        paramParcel1 = getPackageName();
        paramParcel2.writeNoException();
        paramParcel2.writeString(paramParcel1);
        return true;
      case 7: 
        paramParcel1.enforceInterface("android.media.session.ISessionController");
        paramParcel1 = getTag();
        paramParcel2.writeNoException();
        paramParcel2.writeString(paramParcel1);
        return true;
      case 8: 
        paramParcel1.enforceInterface("android.media.session.ISessionController");
        paramParcel1 = getLaunchPendingIntent();
        paramParcel2.writeNoException();
        if (paramParcel1 != null)
        {
          paramParcel2.writeInt(1);
          paramParcel1.writeToParcel(paramParcel2, 1);
        }
        for (;;)
        {
          return true;
          paramParcel2.writeInt(0);
        }
      case 9: 
        paramParcel1.enforceInterface("android.media.session.ISessionController");
        long l = getFlags();
        paramParcel2.writeNoException();
        paramParcel2.writeLong(l);
        return true;
      case 10: 
        paramParcel1.enforceInterface("android.media.session.ISessionController");
        paramParcel1 = getVolumeAttributes();
        paramParcel2.writeNoException();
        if (paramParcel1 != null)
        {
          paramParcel2.writeInt(1);
          paramParcel1.writeToParcel(paramParcel2, 1);
        }
        for (;;)
        {
          return true;
          paramParcel2.writeInt(0);
        }
      case 11: 
        paramParcel1.enforceInterface("android.media.session.ISessionController");
        adjustVolume(paramParcel1.readInt(), paramParcel1.readInt(), paramParcel1.readString());
        paramParcel2.writeNoException();
        return true;
      case 12: 
        paramParcel1.enforceInterface("android.media.session.ISessionController");
        setVolumeTo(paramParcel1.readInt(), paramParcel1.readInt(), paramParcel1.readString());
        paramParcel2.writeNoException();
        return true;
      case 13: 
        paramParcel1.enforceInterface("android.media.session.ISessionController");
        prepare();
        paramParcel2.writeNoException();
        return true;
      case 14: 
        paramParcel1.enforceInterface("android.media.session.ISessionController");
        localObject = paramParcel1.readString();
        if (paramParcel1.readInt() != 0) {}
        for (paramParcel1 = (Bundle)Bundle.CREATOR.createFromParcel(paramParcel1);; paramParcel1 = null)
        {
          prepareFromMediaId((String)localObject, paramParcel1);
          paramParcel2.writeNoException();
          return true;
        }
      case 15: 
        paramParcel1.enforceInterface("android.media.session.ISessionController");
        localObject = paramParcel1.readString();
        if (paramParcel1.readInt() != 0) {}
        for (paramParcel1 = (Bundle)Bundle.CREATOR.createFromParcel(paramParcel1);; paramParcel1 = null)
        {
          prepareFromSearch((String)localObject, paramParcel1);
          paramParcel2.writeNoException();
          return true;
        }
      case 16: 
        paramParcel1.enforceInterface("android.media.session.ISessionController");
        if (paramParcel1.readInt() != 0)
        {
          localObject = (Uri)Uri.CREATOR.createFromParcel(paramParcel1);
          if (paramParcel1.readInt() == 0) {
            break label957;
          }
        }
        for (paramParcel1 = (Bundle)Bundle.CREATOR.createFromParcel(paramParcel1);; paramParcel1 = null)
        {
          prepareFromUri((Uri)localObject, paramParcel1);
          paramParcel2.writeNoException();
          return true;
          localObject = null;
          break;
        }
      case 17: 
        paramParcel1.enforceInterface("android.media.session.ISessionController");
        play();
        paramParcel2.writeNoException();
        return true;
      case 18: 
        paramParcel1.enforceInterface("android.media.session.ISessionController");
        localObject = paramParcel1.readString();
        if (paramParcel1.readInt() != 0) {}
        for (paramParcel1 = (Bundle)Bundle.CREATOR.createFromParcel(paramParcel1);; paramParcel1 = null)
        {
          playFromMediaId((String)localObject, paramParcel1);
          paramParcel2.writeNoException();
          return true;
        }
      case 19: 
        paramParcel1.enforceInterface("android.media.session.ISessionController");
        localObject = paramParcel1.readString();
        if (paramParcel1.readInt() != 0) {}
        for (paramParcel1 = (Bundle)Bundle.CREATOR.createFromParcel(paramParcel1);; paramParcel1 = null)
        {
          playFromSearch((String)localObject, paramParcel1);
          paramParcel2.writeNoException();
          return true;
        }
      case 20: 
        paramParcel1.enforceInterface("android.media.session.ISessionController");
        if (paramParcel1.readInt() != 0)
        {
          localObject = (Uri)Uri.CREATOR.createFromParcel(paramParcel1);
          if (paramParcel1.readInt() == 0) {
            break label1144;
          }
        }
        for (paramParcel1 = (Bundle)Bundle.CREATOR.createFromParcel(paramParcel1);; paramParcel1 = null)
        {
          playFromUri((Uri)localObject, paramParcel1);
          paramParcel2.writeNoException();
          return true;
          localObject = null;
          break;
        }
      case 21: 
        paramParcel1.enforceInterface("android.media.session.ISessionController");
        skipToQueueItem(paramParcel1.readLong());
        paramParcel2.writeNoException();
        return true;
      case 22: 
        paramParcel1.enforceInterface("android.media.session.ISessionController");
        pause();
        paramParcel2.writeNoException();
        return true;
      case 23: 
        paramParcel1.enforceInterface("android.media.session.ISessionController");
        stop();
        paramParcel2.writeNoException();
        return true;
      case 24: 
        paramParcel1.enforceInterface("android.media.session.ISessionController");
        next();
        paramParcel2.writeNoException();
        return true;
      case 25: 
        paramParcel1.enforceInterface("android.media.session.ISessionController");
        previous();
        paramParcel2.writeNoException();
        return true;
      case 26: 
        paramParcel1.enforceInterface("android.media.session.ISessionController");
        fastForward();
        paramParcel2.writeNoException();
        return true;
      case 27: 
        paramParcel1.enforceInterface("android.media.session.ISessionController");
        rewind();
        paramParcel2.writeNoException();
        return true;
      case 28: 
        paramParcel1.enforceInterface("android.media.session.ISessionController");
        seekTo(paramParcel1.readLong());
        paramParcel2.writeNoException();
        return true;
      case 29: 
        paramParcel1.enforceInterface("android.media.session.ISessionController");
        setRemoteControlClientBrowsedPlayer();
        paramParcel2.writeNoException();
        return true;
      case 30: 
        paramParcel1.enforceInterface("android.media.session.ISessionController");
        setRemoteControlClientPlayItem(paramParcel1.readLong(), paramParcel1.readInt());
        paramParcel2.writeNoException();
        return true;
      case 31: 
        paramParcel1.enforceInterface("android.media.session.ISessionController");
        getRemoteControlClientNowPlayingEntries();
        paramParcel2.writeNoException();
        return true;
      case 32: 
        paramParcel1.enforceInterface("android.media.session.ISessionController");
        if (paramParcel1.readInt() != 0) {}
        for (paramParcel1 = (Rating)Rating.CREATOR.createFromParcel(paramParcel1);; paramParcel1 = null)
        {
          rate(paramParcel1);
          paramParcel2.writeNoException();
          return true;
        }
      case 33: 
        paramParcel1.enforceInterface("android.media.session.ISessionController");
        localObject = paramParcel1.readString();
        if (paramParcel1.readInt() != 0) {}
        for (paramParcel1 = (Bundle)Bundle.CREATOR.createFromParcel(paramParcel1);; paramParcel1 = null)
        {
          sendCustomAction((String)localObject, paramParcel1);
          paramParcel2.writeNoException();
          return true;
        }
      case 34: 
        paramParcel1.enforceInterface("android.media.session.ISessionController");
        paramParcel1 = getMetadata();
        paramParcel2.writeNoException();
        if (paramParcel1 != null)
        {
          paramParcel2.writeInt(1);
          paramParcel1.writeToParcel(paramParcel2, 1);
        }
        for (;;)
        {
          return true;
          paramParcel2.writeInt(0);
        }
      case 35: 
        paramParcel1.enforceInterface("android.media.session.ISessionController");
        paramParcel1 = getPlaybackState();
        paramParcel2.writeNoException();
        if (paramParcel1 != null)
        {
          paramParcel2.writeInt(1);
          paramParcel1.writeToParcel(paramParcel2, 1);
        }
        for (;;)
        {
          return true;
          paramParcel2.writeInt(0);
        }
      case 36: 
        paramParcel1.enforceInterface("android.media.session.ISessionController");
        paramParcel1 = getQueue();
        paramParcel2.writeNoException();
        if (paramParcel1 != null)
        {
          paramParcel2.writeInt(1);
          paramParcel1.writeToParcel(paramParcel2, 1);
        }
        for (;;)
        {
          return true;
          paramParcel2.writeInt(0);
        }
      case 37: 
        paramParcel1.enforceInterface("android.media.session.ISessionController");
        paramParcel1 = getQueueTitle();
        paramParcel2.writeNoException();
        if (paramParcel1 != null)
        {
          paramParcel2.writeInt(1);
          TextUtils.writeToParcel(paramParcel1, paramParcel2, 1);
        }
        for (;;)
        {
          return true;
          paramParcel2.writeInt(0);
        }
      case 38: 
        label485:
        label957:
        label1144:
        paramParcel1.enforceInterface("android.media.session.ISessionController");
        paramParcel1 = getExtras();
        paramParcel2.writeNoException();
        if (paramParcel1 != null)
        {
          paramParcel2.writeInt(1);
          paramParcel1.writeToParcel(paramParcel2, 1);
        }
        for (;;)
        {
          return true;
          paramParcel2.writeInt(0);
        }
      }
      paramParcel1.enforceInterface("android.media.session.ISessionController");
      paramInt1 = getRatingType();
      paramParcel2.writeNoException();
      paramParcel2.writeInt(paramInt1);
      return true;
    }
    
    private static class Proxy
      implements ISessionController
    {
      private IBinder mRemote;
      
      Proxy(IBinder paramIBinder)
      {
        this.mRemote = paramIBinder;
      }
      
      public void adjustVolume(int paramInt1, int paramInt2, String paramString)
        throws RemoteException
      {
        Parcel localParcel1 = Parcel.obtain();
        Parcel localParcel2 = Parcel.obtain();
        try
        {
          localParcel1.writeInterfaceToken("android.media.session.ISessionController");
          localParcel1.writeInt(paramInt1);
          localParcel1.writeInt(paramInt2);
          localParcel1.writeString(paramString);
          this.mRemote.transact(11, localParcel1, localParcel2, 0);
          localParcel2.readException();
          return;
        }
        finally
        {
          localParcel2.recycle();
          localParcel1.recycle();
        }
      }
      
      public IBinder asBinder()
      {
        return this.mRemote;
      }
      
      public void fastForward()
        throws RemoteException
      {
        Parcel localParcel1 = Parcel.obtain();
        Parcel localParcel2 = Parcel.obtain();
        try
        {
          localParcel1.writeInterfaceToken("android.media.session.ISessionController");
          this.mRemote.transact(26, localParcel1, localParcel2, 0);
          localParcel2.readException();
          return;
        }
        finally
        {
          localParcel2.recycle();
          localParcel1.recycle();
        }
      }
      
      /* Error */
      public Bundle getExtras()
        throws RemoteException
      {
        // Byte code:
        //   0: invokestatic 30	android/os/Parcel:obtain	()Landroid/os/Parcel;
        //   3: astore_2
        //   4: invokestatic 30	android/os/Parcel:obtain	()Landroid/os/Parcel;
        //   7: astore_3
        //   8: aload_2
        //   9: ldc 32
        //   11: invokevirtual 36	android/os/Parcel:writeInterfaceToken	(Ljava/lang/String;)V
        //   14: aload_0
        //   15: getfield 19	android/media/session/ISessionController$Stub$Proxy:mRemote	Landroid/os/IBinder;
        //   18: bipush 38
        //   20: aload_2
        //   21: aload_3
        //   22: iconst_0
        //   23: invokeinterface 49 5 0
        //   28: pop
        //   29: aload_3
        //   30: invokevirtual 52	android/os/Parcel:readException	()V
        //   33: aload_3
        //   34: invokevirtual 65	android/os/Parcel:readInt	()I
        //   37: ifeq +26 -> 63
        //   40: getstatic 71	android/os/Bundle:CREATOR	Landroid/os/Parcelable$Creator;
        //   43: aload_3
        //   44: invokeinterface 77 2 0
        //   49: checkcast 67	android/os/Bundle
        //   52: astore_1
        //   53: aload_3
        //   54: invokevirtual 55	android/os/Parcel:recycle	()V
        //   57: aload_2
        //   58: invokevirtual 55	android/os/Parcel:recycle	()V
        //   61: aload_1
        //   62: areturn
        //   63: aconst_null
        //   64: astore_1
        //   65: goto -12 -> 53
        //   68: astore_1
        //   69: aload_3
        //   70: invokevirtual 55	android/os/Parcel:recycle	()V
        //   73: aload_2
        //   74: invokevirtual 55	android/os/Parcel:recycle	()V
        //   77: aload_1
        //   78: athrow
        // Local variable table:
        //   start	length	slot	name	signature
        //   0	79	0	this	Proxy
        //   52	13	1	localBundle	Bundle
        //   68	10	1	localObject	Object
        //   3	71	2	localParcel1	Parcel
        //   7	63	3	localParcel2	Parcel
        // Exception table:
        //   from	to	target	type
        //   8	53	68	finally
      }
      
      public long getFlags()
        throws RemoteException
      {
        Parcel localParcel1 = Parcel.obtain();
        Parcel localParcel2 = Parcel.obtain();
        try
        {
          localParcel1.writeInterfaceToken("android.media.session.ISessionController");
          this.mRemote.transact(9, localParcel1, localParcel2, 0);
          localParcel2.readException();
          long l = localParcel2.readLong();
          return l;
        }
        finally
        {
          localParcel2.recycle();
          localParcel1.recycle();
        }
      }
      
      public String getInterfaceDescriptor()
      {
        return "android.media.session.ISessionController";
      }
      
      /* Error */
      public PendingIntent getLaunchPendingIntent()
        throws RemoteException
      {
        // Byte code:
        //   0: invokestatic 30	android/os/Parcel:obtain	()Landroid/os/Parcel;
        //   3: astore_2
        //   4: invokestatic 30	android/os/Parcel:obtain	()Landroid/os/Parcel;
        //   7: astore_3
        //   8: aload_2
        //   9: ldc 32
        //   11: invokevirtual 36	android/os/Parcel:writeInterfaceToken	(Ljava/lang/String;)V
        //   14: aload_0
        //   15: getfield 19	android/media/session/ISessionController$Stub$Proxy:mRemote	Landroid/os/IBinder;
        //   18: bipush 8
        //   20: aload_2
        //   21: aload_3
        //   22: iconst_0
        //   23: invokeinterface 49 5 0
        //   28: pop
        //   29: aload_3
        //   30: invokevirtual 52	android/os/Parcel:readException	()V
        //   33: aload_3
        //   34: invokevirtual 65	android/os/Parcel:readInt	()I
        //   37: ifeq +26 -> 63
        //   40: getstatic 89	android/app/PendingIntent:CREATOR	Landroid/os/Parcelable$Creator;
        //   43: aload_3
        //   44: invokeinterface 77 2 0
        //   49: checkcast 88	android/app/PendingIntent
        //   52: astore_1
        //   53: aload_3
        //   54: invokevirtual 55	android/os/Parcel:recycle	()V
        //   57: aload_2
        //   58: invokevirtual 55	android/os/Parcel:recycle	()V
        //   61: aload_1
        //   62: areturn
        //   63: aconst_null
        //   64: astore_1
        //   65: goto -12 -> 53
        //   68: astore_1
        //   69: aload_3
        //   70: invokevirtual 55	android/os/Parcel:recycle	()V
        //   73: aload_2
        //   74: invokevirtual 55	android/os/Parcel:recycle	()V
        //   77: aload_1
        //   78: athrow
        // Local variable table:
        //   start	length	slot	name	signature
        //   0	79	0	this	Proxy
        //   52	13	1	localPendingIntent	PendingIntent
        //   68	10	1	localObject	Object
        //   3	71	2	localParcel1	Parcel
        //   7	63	3	localParcel2	Parcel
        // Exception table:
        //   from	to	target	type
        //   8	53	68	finally
      }
      
      /* Error */
      public MediaMetadata getMetadata()
        throws RemoteException
      {
        // Byte code:
        //   0: invokestatic 30	android/os/Parcel:obtain	()Landroid/os/Parcel;
        //   3: astore_2
        //   4: invokestatic 30	android/os/Parcel:obtain	()Landroid/os/Parcel;
        //   7: astore_3
        //   8: aload_2
        //   9: ldc 32
        //   11: invokevirtual 36	android/os/Parcel:writeInterfaceToken	(Ljava/lang/String;)V
        //   14: aload_0
        //   15: getfield 19	android/media/session/ISessionController$Stub$Proxy:mRemote	Landroid/os/IBinder;
        //   18: bipush 34
        //   20: aload_2
        //   21: aload_3
        //   22: iconst_0
        //   23: invokeinterface 49 5 0
        //   28: pop
        //   29: aload_3
        //   30: invokevirtual 52	android/os/Parcel:readException	()V
        //   33: aload_3
        //   34: invokevirtual 65	android/os/Parcel:readInt	()I
        //   37: ifeq +26 -> 63
        //   40: getstatic 94	android/media/MediaMetadata:CREATOR	Landroid/os/Parcelable$Creator;
        //   43: aload_3
        //   44: invokeinterface 77 2 0
        //   49: checkcast 93	android/media/MediaMetadata
        //   52: astore_1
        //   53: aload_3
        //   54: invokevirtual 55	android/os/Parcel:recycle	()V
        //   57: aload_2
        //   58: invokevirtual 55	android/os/Parcel:recycle	()V
        //   61: aload_1
        //   62: areturn
        //   63: aconst_null
        //   64: astore_1
        //   65: goto -12 -> 53
        //   68: astore_1
        //   69: aload_3
        //   70: invokevirtual 55	android/os/Parcel:recycle	()V
        //   73: aload_2
        //   74: invokevirtual 55	android/os/Parcel:recycle	()V
        //   77: aload_1
        //   78: athrow
        // Local variable table:
        //   start	length	slot	name	signature
        //   0	79	0	this	Proxy
        //   52	13	1	localMediaMetadata	MediaMetadata
        //   68	10	1	localObject	Object
        //   3	71	2	localParcel1	Parcel
        //   7	63	3	localParcel2	Parcel
        // Exception table:
        //   from	to	target	type
        //   8	53	68	finally
      }
      
      public String getPackageName()
        throws RemoteException
      {
        Parcel localParcel1 = Parcel.obtain();
        Parcel localParcel2 = Parcel.obtain();
        try
        {
          localParcel1.writeInterfaceToken("android.media.session.ISessionController");
          this.mRemote.transact(6, localParcel1, localParcel2, 0);
          localParcel2.readException();
          String str = localParcel2.readString();
          return str;
        }
        finally
        {
          localParcel2.recycle();
          localParcel1.recycle();
        }
      }
      
      /* Error */
      public PlaybackState getPlaybackState()
        throws RemoteException
      {
        // Byte code:
        //   0: invokestatic 30	android/os/Parcel:obtain	()Landroid/os/Parcel;
        //   3: astore_2
        //   4: invokestatic 30	android/os/Parcel:obtain	()Landroid/os/Parcel;
        //   7: astore_3
        //   8: aload_2
        //   9: ldc 32
        //   11: invokevirtual 36	android/os/Parcel:writeInterfaceToken	(Ljava/lang/String;)V
        //   14: aload_0
        //   15: getfield 19	android/media/session/ISessionController$Stub$Proxy:mRemote	Landroid/os/IBinder;
        //   18: bipush 35
        //   20: aload_2
        //   21: aload_3
        //   22: iconst_0
        //   23: invokeinterface 49 5 0
        //   28: pop
        //   29: aload_3
        //   30: invokevirtual 52	android/os/Parcel:readException	()V
        //   33: aload_3
        //   34: invokevirtual 65	android/os/Parcel:readInt	()I
        //   37: ifeq +26 -> 63
        //   40: getstatic 103	android/media/session/PlaybackState:CREATOR	Landroid/os/Parcelable$Creator;
        //   43: aload_3
        //   44: invokeinterface 77 2 0
        //   49: checkcast 102	android/media/session/PlaybackState
        //   52: astore_1
        //   53: aload_3
        //   54: invokevirtual 55	android/os/Parcel:recycle	()V
        //   57: aload_2
        //   58: invokevirtual 55	android/os/Parcel:recycle	()V
        //   61: aload_1
        //   62: areturn
        //   63: aconst_null
        //   64: astore_1
        //   65: goto -12 -> 53
        //   68: astore_1
        //   69: aload_3
        //   70: invokevirtual 55	android/os/Parcel:recycle	()V
        //   73: aload_2
        //   74: invokevirtual 55	android/os/Parcel:recycle	()V
        //   77: aload_1
        //   78: athrow
        // Local variable table:
        //   start	length	slot	name	signature
        //   0	79	0	this	Proxy
        //   52	13	1	localPlaybackState	PlaybackState
        //   68	10	1	localObject	Object
        //   3	71	2	localParcel1	Parcel
        //   7	63	3	localParcel2	Parcel
        // Exception table:
        //   from	to	target	type
        //   8	53	68	finally
      }
      
      /* Error */
      public ParceledListSlice getQueue()
        throws RemoteException
      {
        // Byte code:
        //   0: invokestatic 30	android/os/Parcel:obtain	()Landroid/os/Parcel;
        //   3: astore_2
        //   4: invokestatic 30	android/os/Parcel:obtain	()Landroid/os/Parcel;
        //   7: astore_3
        //   8: aload_2
        //   9: ldc 32
        //   11: invokevirtual 36	android/os/Parcel:writeInterfaceToken	(Ljava/lang/String;)V
        //   14: aload_0
        //   15: getfield 19	android/media/session/ISessionController$Stub$Proxy:mRemote	Landroid/os/IBinder;
        //   18: bipush 36
        //   20: aload_2
        //   21: aload_3
        //   22: iconst_0
        //   23: invokeinterface 49 5 0
        //   28: pop
        //   29: aload_3
        //   30: invokevirtual 52	android/os/Parcel:readException	()V
        //   33: aload_3
        //   34: invokevirtual 65	android/os/Parcel:readInt	()I
        //   37: ifeq +26 -> 63
        //   40: getstatic 110	android/content/pm/ParceledListSlice:CREATOR	Landroid/os/Parcelable$ClassLoaderCreator;
        //   43: aload_3
        //   44: invokeinterface 113 2 0
        //   49: checkcast 107	android/content/pm/ParceledListSlice
        //   52: astore_1
        //   53: aload_3
        //   54: invokevirtual 55	android/os/Parcel:recycle	()V
        //   57: aload_2
        //   58: invokevirtual 55	android/os/Parcel:recycle	()V
        //   61: aload_1
        //   62: areturn
        //   63: aconst_null
        //   64: astore_1
        //   65: goto -12 -> 53
        //   68: astore_1
        //   69: aload_3
        //   70: invokevirtual 55	android/os/Parcel:recycle	()V
        //   73: aload_2
        //   74: invokevirtual 55	android/os/Parcel:recycle	()V
        //   77: aload_1
        //   78: athrow
        // Local variable table:
        //   start	length	slot	name	signature
        //   0	79	0	this	Proxy
        //   52	13	1	localParceledListSlice	ParceledListSlice
        //   68	10	1	localObject	Object
        //   3	71	2	localParcel1	Parcel
        //   7	63	3	localParcel2	Parcel
        // Exception table:
        //   from	to	target	type
        //   8	53	68	finally
      }
      
      /* Error */
      public CharSequence getQueueTitle()
        throws RemoteException
      {
        // Byte code:
        //   0: invokestatic 30	android/os/Parcel:obtain	()Landroid/os/Parcel;
        //   3: astore_2
        //   4: invokestatic 30	android/os/Parcel:obtain	()Landroid/os/Parcel;
        //   7: astore_3
        //   8: aload_2
        //   9: ldc 32
        //   11: invokevirtual 36	android/os/Parcel:writeInterfaceToken	(Ljava/lang/String;)V
        //   14: aload_0
        //   15: getfield 19	android/media/session/ISessionController$Stub$Proxy:mRemote	Landroid/os/IBinder;
        //   18: bipush 37
        //   20: aload_2
        //   21: aload_3
        //   22: iconst_0
        //   23: invokeinterface 49 5 0
        //   28: pop
        //   29: aload_3
        //   30: invokevirtual 52	android/os/Parcel:readException	()V
        //   33: aload_3
        //   34: invokevirtual 65	android/os/Parcel:readInt	()I
        //   37: ifeq +26 -> 63
        //   40: getstatic 120	android/text/TextUtils:CHAR_SEQUENCE_CREATOR	Landroid/os/Parcelable$Creator;
        //   43: aload_3
        //   44: invokeinterface 77 2 0
        //   49: checkcast 122	java/lang/CharSequence
        //   52: astore_1
        //   53: aload_3
        //   54: invokevirtual 55	android/os/Parcel:recycle	()V
        //   57: aload_2
        //   58: invokevirtual 55	android/os/Parcel:recycle	()V
        //   61: aload_1
        //   62: areturn
        //   63: aconst_null
        //   64: astore_1
        //   65: goto -12 -> 53
        //   68: astore_1
        //   69: aload_3
        //   70: invokevirtual 55	android/os/Parcel:recycle	()V
        //   73: aload_2
        //   74: invokevirtual 55	android/os/Parcel:recycle	()V
        //   77: aload_1
        //   78: athrow
        // Local variable table:
        //   start	length	slot	name	signature
        //   0	79	0	this	Proxy
        //   52	13	1	localCharSequence	CharSequence
        //   68	10	1	localObject	Object
        //   3	71	2	localParcel1	Parcel
        //   7	63	3	localParcel2	Parcel
        // Exception table:
        //   from	to	target	type
        //   8	53	68	finally
      }
      
      public int getRatingType()
        throws RemoteException
      {
        Parcel localParcel1 = Parcel.obtain();
        Parcel localParcel2 = Parcel.obtain();
        try
        {
          localParcel1.writeInterfaceToken("android.media.session.ISessionController");
          this.mRemote.transact(39, localParcel1, localParcel2, 0);
          localParcel2.readException();
          int i = localParcel2.readInt();
          return i;
        }
        finally
        {
          localParcel2.recycle();
          localParcel1.recycle();
        }
      }
      
      public void getRemoteControlClientNowPlayingEntries()
        throws RemoteException
      {
        Parcel localParcel1 = Parcel.obtain();
        Parcel localParcel2 = Parcel.obtain();
        try
        {
          localParcel1.writeInterfaceToken("android.media.session.ISessionController");
          this.mRemote.transact(31, localParcel1, localParcel2, 0);
          localParcel2.readException();
          return;
        }
        finally
        {
          localParcel2.recycle();
          localParcel1.recycle();
        }
      }
      
      public String getTag()
        throws RemoteException
      {
        Parcel localParcel1 = Parcel.obtain();
        Parcel localParcel2 = Parcel.obtain();
        try
        {
          localParcel1.writeInterfaceToken("android.media.session.ISessionController");
          this.mRemote.transact(7, localParcel1, localParcel2, 0);
          localParcel2.readException();
          String str = localParcel2.readString();
          return str;
        }
        finally
        {
          localParcel2.recycle();
          localParcel1.recycle();
        }
      }
      
      /* Error */
      public ParcelableVolumeInfo getVolumeAttributes()
        throws RemoteException
      {
        // Byte code:
        //   0: invokestatic 30	android/os/Parcel:obtain	()Landroid/os/Parcel;
        //   3: astore_2
        //   4: invokestatic 30	android/os/Parcel:obtain	()Landroid/os/Parcel;
        //   7: astore_3
        //   8: aload_2
        //   9: ldc 32
        //   11: invokevirtual 36	android/os/Parcel:writeInterfaceToken	(Ljava/lang/String;)V
        //   14: aload_0
        //   15: getfield 19	android/media/session/ISessionController$Stub$Proxy:mRemote	Landroid/os/IBinder;
        //   18: bipush 10
        //   20: aload_2
        //   21: aload_3
        //   22: iconst_0
        //   23: invokeinterface 49 5 0
        //   28: pop
        //   29: aload_3
        //   30: invokevirtual 52	android/os/Parcel:readException	()V
        //   33: aload_3
        //   34: invokevirtual 65	android/os/Parcel:readInt	()I
        //   37: ifeq +26 -> 63
        //   40: getstatic 130	android/media/session/ParcelableVolumeInfo:CREATOR	Landroid/os/Parcelable$Creator;
        //   43: aload_3
        //   44: invokeinterface 77 2 0
        //   49: checkcast 129	android/media/session/ParcelableVolumeInfo
        //   52: astore_1
        //   53: aload_3
        //   54: invokevirtual 55	android/os/Parcel:recycle	()V
        //   57: aload_2
        //   58: invokevirtual 55	android/os/Parcel:recycle	()V
        //   61: aload_1
        //   62: areturn
        //   63: aconst_null
        //   64: astore_1
        //   65: goto -12 -> 53
        //   68: astore_1
        //   69: aload_3
        //   70: invokevirtual 55	android/os/Parcel:recycle	()V
        //   73: aload_2
        //   74: invokevirtual 55	android/os/Parcel:recycle	()V
        //   77: aload_1
        //   78: athrow
        // Local variable table:
        //   start	length	slot	name	signature
        //   0	79	0	this	Proxy
        //   52	13	1	localParcelableVolumeInfo	ParcelableVolumeInfo
        //   68	10	1	localObject	Object
        //   3	71	2	localParcel1	Parcel
        //   7	63	3	localParcel2	Parcel
        // Exception table:
        //   from	to	target	type
        //   8	53	68	finally
      }
      
      /* Error */
      public boolean isTransportControlEnabled()
        throws RemoteException
      {
        // Byte code:
        //   0: invokestatic 30	android/os/Parcel:obtain	()Landroid/os/Parcel;
        //   3: astore_3
        //   4: invokestatic 30	android/os/Parcel:obtain	()Landroid/os/Parcel;
        //   7: astore 4
        //   9: aload_3
        //   10: ldc 32
        //   12: invokevirtual 36	android/os/Parcel:writeInterfaceToken	(Ljava/lang/String;)V
        //   15: aload_0
        //   16: getfield 19	android/media/session/ISessionController$Stub$Proxy:mRemote	Landroid/os/IBinder;
        //   19: iconst_5
        //   20: aload_3
        //   21: aload 4
        //   23: iconst_0
        //   24: invokeinterface 49 5 0
        //   29: pop
        //   30: aload 4
        //   32: invokevirtual 52	android/os/Parcel:readException	()V
        //   35: aload 4
        //   37: invokevirtual 65	android/os/Parcel:readInt	()I
        //   40: istore_1
        //   41: iload_1
        //   42: ifeq +16 -> 58
        //   45: iconst_1
        //   46: istore_2
        //   47: aload 4
        //   49: invokevirtual 55	android/os/Parcel:recycle	()V
        //   52: aload_3
        //   53: invokevirtual 55	android/os/Parcel:recycle	()V
        //   56: iload_2
        //   57: ireturn
        //   58: iconst_0
        //   59: istore_2
        //   60: goto -13 -> 47
        //   63: astore 5
        //   65: aload 4
        //   67: invokevirtual 55	android/os/Parcel:recycle	()V
        //   70: aload_3
        //   71: invokevirtual 55	android/os/Parcel:recycle	()V
        //   74: aload 5
        //   76: athrow
        // Local variable table:
        //   start	length	slot	name	signature
        //   0	77	0	this	Proxy
        //   40	2	1	i	int
        //   46	14	2	bool	boolean
        //   3	68	3	localParcel1	Parcel
        //   7	59	4	localParcel2	Parcel
        //   63	12	5	localObject	Object
        // Exception table:
        //   from	to	target	type
        //   9	41	63	finally
      }
      
      public void next()
        throws RemoteException
      {
        Parcel localParcel1 = Parcel.obtain();
        Parcel localParcel2 = Parcel.obtain();
        try
        {
          localParcel1.writeInterfaceToken("android.media.session.ISessionController");
          this.mRemote.transact(24, localParcel1, localParcel2, 0);
          localParcel2.readException();
          return;
        }
        finally
        {
          localParcel2.recycle();
          localParcel1.recycle();
        }
      }
      
      public void pause()
        throws RemoteException
      {
        Parcel localParcel1 = Parcel.obtain();
        Parcel localParcel2 = Parcel.obtain();
        try
        {
          localParcel1.writeInterfaceToken("android.media.session.ISessionController");
          this.mRemote.transact(22, localParcel1, localParcel2, 0);
          localParcel2.readException();
          return;
        }
        finally
        {
          localParcel2.recycle();
          localParcel1.recycle();
        }
      }
      
      public void play()
        throws RemoteException
      {
        Parcel localParcel1 = Parcel.obtain();
        Parcel localParcel2 = Parcel.obtain();
        try
        {
          localParcel1.writeInterfaceToken("android.media.session.ISessionController");
          this.mRemote.transact(17, localParcel1, localParcel2, 0);
          localParcel2.readException();
          return;
        }
        finally
        {
          localParcel2.recycle();
          localParcel1.recycle();
        }
      }
      
      /* Error */
      public void playFromMediaId(String paramString, Bundle paramBundle)
        throws RemoteException
      {
        // Byte code:
        //   0: invokestatic 30	android/os/Parcel:obtain	()Landroid/os/Parcel;
        //   3: astore_3
        //   4: invokestatic 30	android/os/Parcel:obtain	()Landroid/os/Parcel;
        //   7: astore 4
        //   9: aload_3
        //   10: ldc 32
        //   12: invokevirtual 36	android/os/Parcel:writeInterfaceToken	(Ljava/lang/String;)V
        //   15: aload_3
        //   16: aload_1
        //   17: invokevirtual 43	android/os/Parcel:writeString	(Ljava/lang/String;)V
        //   20: aload_2
        //   21: ifnull +45 -> 66
        //   24: aload_3
        //   25: iconst_1
        //   26: invokevirtual 40	android/os/Parcel:writeInt	(I)V
        //   29: aload_2
        //   30: aload_3
        //   31: iconst_0
        //   32: invokevirtual 141	android/os/Bundle:writeToParcel	(Landroid/os/Parcel;I)V
        //   35: aload_0
        //   36: getfield 19	android/media/session/ISessionController$Stub$Proxy:mRemote	Landroid/os/IBinder;
        //   39: bipush 18
        //   41: aload_3
        //   42: aload 4
        //   44: iconst_0
        //   45: invokeinterface 49 5 0
        //   50: pop
        //   51: aload 4
        //   53: invokevirtual 52	android/os/Parcel:readException	()V
        //   56: aload 4
        //   58: invokevirtual 55	android/os/Parcel:recycle	()V
        //   61: aload_3
        //   62: invokevirtual 55	android/os/Parcel:recycle	()V
        //   65: return
        //   66: aload_3
        //   67: iconst_0
        //   68: invokevirtual 40	android/os/Parcel:writeInt	(I)V
        //   71: goto -36 -> 35
        //   74: astore_1
        //   75: aload 4
        //   77: invokevirtual 55	android/os/Parcel:recycle	()V
        //   80: aload_3
        //   81: invokevirtual 55	android/os/Parcel:recycle	()V
        //   84: aload_1
        //   85: athrow
        // Local variable table:
        //   start	length	slot	name	signature
        //   0	86	0	this	Proxy
        //   0	86	1	paramString	String
        //   0	86	2	paramBundle	Bundle
        //   3	78	3	localParcel1	Parcel
        //   7	69	4	localParcel2	Parcel
        // Exception table:
        //   from	to	target	type
        //   9	20	74	finally
        //   24	35	74	finally
        //   35	56	74	finally
        //   66	71	74	finally
      }
      
      /* Error */
      public void playFromSearch(String paramString, Bundle paramBundle)
        throws RemoteException
      {
        // Byte code:
        //   0: invokestatic 30	android/os/Parcel:obtain	()Landroid/os/Parcel;
        //   3: astore_3
        //   4: invokestatic 30	android/os/Parcel:obtain	()Landroid/os/Parcel;
        //   7: astore 4
        //   9: aload_3
        //   10: ldc 32
        //   12: invokevirtual 36	android/os/Parcel:writeInterfaceToken	(Ljava/lang/String;)V
        //   15: aload_3
        //   16: aload_1
        //   17: invokevirtual 43	android/os/Parcel:writeString	(Ljava/lang/String;)V
        //   20: aload_2
        //   21: ifnull +45 -> 66
        //   24: aload_3
        //   25: iconst_1
        //   26: invokevirtual 40	android/os/Parcel:writeInt	(I)V
        //   29: aload_2
        //   30: aload_3
        //   31: iconst_0
        //   32: invokevirtual 141	android/os/Bundle:writeToParcel	(Landroid/os/Parcel;I)V
        //   35: aload_0
        //   36: getfield 19	android/media/session/ISessionController$Stub$Proxy:mRemote	Landroid/os/IBinder;
        //   39: bipush 19
        //   41: aload_3
        //   42: aload 4
        //   44: iconst_0
        //   45: invokeinterface 49 5 0
        //   50: pop
        //   51: aload 4
        //   53: invokevirtual 52	android/os/Parcel:readException	()V
        //   56: aload 4
        //   58: invokevirtual 55	android/os/Parcel:recycle	()V
        //   61: aload_3
        //   62: invokevirtual 55	android/os/Parcel:recycle	()V
        //   65: return
        //   66: aload_3
        //   67: iconst_0
        //   68: invokevirtual 40	android/os/Parcel:writeInt	(I)V
        //   71: goto -36 -> 35
        //   74: astore_1
        //   75: aload 4
        //   77: invokevirtual 55	android/os/Parcel:recycle	()V
        //   80: aload_3
        //   81: invokevirtual 55	android/os/Parcel:recycle	()V
        //   84: aload_1
        //   85: athrow
        // Local variable table:
        //   start	length	slot	name	signature
        //   0	86	0	this	Proxy
        //   0	86	1	paramString	String
        //   0	86	2	paramBundle	Bundle
        //   3	78	3	localParcel1	Parcel
        //   7	69	4	localParcel2	Parcel
        // Exception table:
        //   from	to	target	type
        //   9	20	74	finally
        //   24	35	74	finally
        //   35	56	74	finally
        //   66	71	74	finally
      }
      
      public void playFromUri(Uri paramUri, Bundle paramBundle)
        throws RemoteException
      {
        Parcel localParcel1 = Parcel.obtain();
        Parcel localParcel2 = Parcel.obtain();
        for (;;)
        {
          try
          {
            localParcel1.writeInterfaceToken("android.media.session.ISessionController");
            if (paramUri != null)
            {
              localParcel1.writeInt(1);
              paramUri.writeToParcel(localParcel1, 0);
              if (paramBundle != null)
              {
                localParcel1.writeInt(1);
                paramBundle.writeToParcel(localParcel1, 0);
                this.mRemote.transact(20, localParcel1, localParcel2, 0);
                localParcel2.readException();
              }
            }
            else
            {
              localParcel1.writeInt(0);
              continue;
            }
            localParcel1.writeInt(0);
          }
          finally
          {
            localParcel2.recycle();
            localParcel1.recycle();
          }
        }
      }
      
      public void prepare()
        throws RemoteException
      {
        Parcel localParcel1 = Parcel.obtain();
        Parcel localParcel2 = Parcel.obtain();
        try
        {
          localParcel1.writeInterfaceToken("android.media.session.ISessionController");
          this.mRemote.transact(13, localParcel1, localParcel2, 0);
          localParcel2.readException();
          return;
        }
        finally
        {
          localParcel2.recycle();
          localParcel1.recycle();
        }
      }
      
      /* Error */
      public void prepareFromMediaId(String paramString, Bundle paramBundle)
        throws RemoteException
      {
        // Byte code:
        //   0: invokestatic 30	android/os/Parcel:obtain	()Landroid/os/Parcel;
        //   3: astore_3
        //   4: invokestatic 30	android/os/Parcel:obtain	()Landroid/os/Parcel;
        //   7: astore 4
        //   9: aload_3
        //   10: ldc 32
        //   12: invokevirtual 36	android/os/Parcel:writeInterfaceToken	(Ljava/lang/String;)V
        //   15: aload_3
        //   16: aload_1
        //   17: invokevirtual 43	android/os/Parcel:writeString	(Ljava/lang/String;)V
        //   20: aload_2
        //   21: ifnull +45 -> 66
        //   24: aload_3
        //   25: iconst_1
        //   26: invokevirtual 40	android/os/Parcel:writeInt	(I)V
        //   29: aload_2
        //   30: aload_3
        //   31: iconst_0
        //   32: invokevirtual 141	android/os/Bundle:writeToParcel	(Landroid/os/Parcel;I)V
        //   35: aload_0
        //   36: getfield 19	android/media/session/ISessionController$Stub$Proxy:mRemote	Landroid/os/IBinder;
        //   39: bipush 14
        //   41: aload_3
        //   42: aload 4
        //   44: iconst_0
        //   45: invokeinterface 49 5 0
        //   50: pop
        //   51: aload 4
        //   53: invokevirtual 52	android/os/Parcel:readException	()V
        //   56: aload 4
        //   58: invokevirtual 55	android/os/Parcel:recycle	()V
        //   61: aload_3
        //   62: invokevirtual 55	android/os/Parcel:recycle	()V
        //   65: return
        //   66: aload_3
        //   67: iconst_0
        //   68: invokevirtual 40	android/os/Parcel:writeInt	(I)V
        //   71: goto -36 -> 35
        //   74: astore_1
        //   75: aload 4
        //   77: invokevirtual 55	android/os/Parcel:recycle	()V
        //   80: aload_3
        //   81: invokevirtual 55	android/os/Parcel:recycle	()V
        //   84: aload_1
        //   85: athrow
        // Local variable table:
        //   start	length	slot	name	signature
        //   0	86	0	this	Proxy
        //   0	86	1	paramString	String
        //   0	86	2	paramBundle	Bundle
        //   3	78	3	localParcel1	Parcel
        //   7	69	4	localParcel2	Parcel
        // Exception table:
        //   from	to	target	type
        //   9	20	74	finally
        //   24	35	74	finally
        //   35	56	74	finally
        //   66	71	74	finally
      }
      
      /* Error */
      public void prepareFromSearch(String paramString, Bundle paramBundle)
        throws RemoteException
      {
        // Byte code:
        //   0: invokestatic 30	android/os/Parcel:obtain	()Landroid/os/Parcel;
        //   3: astore_3
        //   4: invokestatic 30	android/os/Parcel:obtain	()Landroid/os/Parcel;
        //   7: astore 4
        //   9: aload_3
        //   10: ldc 32
        //   12: invokevirtual 36	android/os/Parcel:writeInterfaceToken	(Ljava/lang/String;)V
        //   15: aload_3
        //   16: aload_1
        //   17: invokevirtual 43	android/os/Parcel:writeString	(Ljava/lang/String;)V
        //   20: aload_2
        //   21: ifnull +45 -> 66
        //   24: aload_3
        //   25: iconst_1
        //   26: invokevirtual 40	android/os/Parcel:writeInt	(I)V
        //   29: aload_2
        //   30: aload_3
        //   31: iconst_0
        //   32: invokevirtual 141	android/os/Bundle:writeToParcel	(Landroid/os/Parcel;I)V
        //   35: aload_0
        //   36: getfield 19	android/media/session/ISessionController$Stub$Proxy:mRemote	Landroid/os/IBinder;
        //   39: bipush 15
        //   41: aload_3
        //   42: aload 4
        //   44: iconst_0
        //   45: invokeinterface 49 5 0
        //   50: pop
        //   51: aload 4
        //   53: invokevirtual 52	android/os/Parcel:readException	()V
        //   56: aload 4
        //   58: invokevirtual 55	android/os/Parcel:recycle	()V
        //   61: aload_3
        //   62: invokevirtual 55	android/os/Parcel:recycle	()V
        //   65: return
        //   66: aload_3
        //   67: iconst_0
        //   68: invokevirtual 40	android/os/Parcel:writeInt	(I)V
        //   71: goto -36 -> 35
        //   74: astore_1
        //   75: aload 4
        //   77: invokevirtual 55	android/os/Parcel:recycle	()V
        //   80: aload_3
        //   81: invokevirtual 55	android/os/Parcel:recycle	()V
        //   84: aload_1
        //   85: athrow
        // Local variable table:
        //   start	length	slot	name	signature
        //   0	86	0	this	Proxy
        //   0	86	1	paramString	String
        //   0	86	2	paramBundle	Bundle
        //   3	78	3	localParcel1	Parcel
        //   7	69	4	localParcel2	Parcel
        // Exception table:
        //   from	to	target	type
        //   9	20	74	finally
        //   24	35	74	finally
        //   35	56	74	finally
        //   66	71	74	finally
      }
      
      public void prepareFromUri(Uri paramUri, Bundle paramBundle)
        throws RemoteException
      {
        Parcel localParcel1 = Parcel.obtain();
        Parcel localParcel2 = Parcel.obtain();
        for (;;)
        {
          try
          {
            localParcel1.writeInterfaceToken("android.media.session.ISessionController");
            if (paramUri != null)
            {
              localParcel1.writeInt(1);
              paramUri.writeToParcel(localParcel1, 0);
              if (paramBundle != null)
              {
                localParcel1.writeInt(1);
                paramBundle.writeToParcel(localParcel1, 0);
                this.mRemote.transact(16, localParcel1, localParcel2, 0);
                localParcel2.readException();
              }
            }
            else
            {
              localParcel1.writeInt(0);
              continue;
            }
            localParcel1.writeInt(0);
          }
          finally
          {
            localParcel2.recycle();
            localParcel1.recycle();
          }
        }
      }
      
      public void previous()
        throws RemoteException
      {
        Parcel localParcel1 = Parcel.obtain();
        Parcel localParcel2 = Parcel.obtain();
        try
        {
          localParcel1.writeInterfaceToken("android.media.session.ISessionController");
          this.mRemote.transact(25, localParcel1, localParcel2, 0);
          localParcel2.readException();
          return;
        }
        finally
        {
          localParcel2.recycle();
          localParcel1.recycle();
        }
      }
      
      /* Error */
      public void rate(Rating paramRating)
        throws RemoteException
      {
        // Byte code:
        //   0: invokestatic 30	android/os/Parcel:obtain	()Landroid/os/Parcel;
        //   3: astore_2
        //   4: invokestatic 30	android/os/Parcel:obtain	()Landroid/os/Parcel;
        //   7: astore_3
        //   8: aload_2
        //   9: ldc 32
        //   11: invokevirtual 36	android/os/Parcel:writeInterfaceToken	(Ljava/lang/String;)V
        //   14: aload_1
        //   15: ifnull +42 -> 57
        //   18: aload_2
        //   19: iconst_1
        //   20: invokevirtual 40	android/os/Parcel:writeInt	(I)V
        //   23: aload_1
        //   24: aload_2
        //   25: iconst_0
        //   26: invokevirtual 157	android/media/Rating:writeToParcel	(Landroid/os/Parcel;I)V
        //   29: aload_0
        //   30: getfield 19	android/media/session/ISessionController$Stub$Proxy:mRemote	Landroid/os/IBinder;
        //   33: bipush 32
        //   35: aload_2
        //   36: aload_3
        //   37: iconst_0
        //   38: invokeinterface 49 5 0
        //   43: pop
        //   44: aload_3
        //   45: invokevirtual 52	android/os/Parcel:readException	()V
        //   48: aload_3
        //   49: invokevirtual 55	android/os/Parcel:recycle	()V
        //   52: aload_2
        //   53: invokevirtual 55	android/os/Parcel:recycle	()V
        //   56: return
        //   57: aload_2
        //   58: iconst_0
        //   59: invokevirtual 40	android/os/Parcel:writeInt	(I)V
        //   62: goto -33 -> 29
        //   65: astore_1
        //   66: aload_3
        //   67: invokevirtual 55	android/os/Parcel:recycle	()V
        //   70: aload_2
        //   71: invokevirtual 55	android/os/Parcel:recycle	()V
        //   74: aload_1
        //   75: athrow
        // Local variable table:
        //   start	length	slot	name	signature
        //   0	76	0	this	Proxy
        //   0	76	1	paramRating	Rating
        //   3	68	2	localParcel1	Parcel
        //   7	60	3	localParcel2	Parcel
        // Exception table:
        //   from	to	target	type
        //   8	14	65	finally
        //   18	29	65	finally
        //   29	48	65	finally
        //   57	62	65	finally
      }
      
      public void registerCallbackListener(ISessionControllerCallback paramISessionControllerCallback)
        throws RemoteException
      {
        IBinder localIBinder = null;
        Parcel localParcel1 = Parcel.obtain();
        Parcel localParcel2 = Parcel.obtain();
        try
        {
          localParcel1.writeInterfaceToken("android.media.session.ISessionController");
          if (paramISessionControllerCallback != null) {
            localIBinder = paramISessionControllerCallback.asBinder();
          }
          localParcel1.writeStrongBinder(localIBinder);
          this.mRemote.transact(3, localParcel1, localParcel2, 0);
          localParcel2.readException();
          return;
        }
        finally
        {
          localParcel2.recycle();
          localParcel1.recycle();
        }
      }
      
      public void rewind()
        throws RemoteException
      {
        Parcel localParcel1 = Parcel.obtain();
        Parcel localParcel2 = Parcel.obtain();
        try
        {
          localParcel1.writeInterfaceToken("android.media.session.ISessionController");
          this.mRemote.transact(27, localParcel1, localParcel2, 0);
          localParcel2.readException();
          return;
        }
        finally
        {
          localParcel2.recycle();
          localParcel1.recycle();
        }
      }
      
      public void seekTo(long paramLong)
        throws RemoteException
      {
        Parcel localParcel1 = Parcel.obtain();
        Parcel localParcel2 = Parcel.obtain();
        try
        {
          localParcel1.writeInterfaceToken("android.media.session.ISessionController");
          localParcel1.writeLong(paramLong);
          this.mRemote.transact(28, localParcel1, localParcel2, 0);
          localParcel2.readException();
          return;
        }
        finally
        {
          localParcel2.recycle();
          localParcel1.recycle();
        }
      }
      
      public void sendCommand(String paramString, Bundle paramBundle, ResultReceiver paramResultReceiver)
        throws RemoteException
      {
        Parcel localParcel1 = Parcel.obtain();
        Parcel localParcel2 = Parcel.obtain();
        for (;;)
        {
          try
          {
            localParcel1.writeInterfaceToken("android.media.session.ISessionController");
            localParcel1.writeString(paramString);
            if (paramBundle != null)
            {
              localParcel1.writeInt(1);
              paramBundle.writeToParcel(localParcel1, 0);
              if (paramResultReceiver != null)
              {
                localParcel1.writeInt(1);
                paramResultReceiver.writeToParcel(localParcel1, 0);
                this.mRemote.transact(1, localParcel1, localParcel2, 0);
                localParcel2.readException();
              }
            }
            else
            {
              localParcel1.writeInt(0);
              continue;
            }
            localParcel1.writeInt(0);
          }
          finally
          {
            localParcel2.recycle();
            localParcel1.recycle();
          }
        }
      }
      
      /* Error */
      public void sendCustomAction(String paramString, Bundle paramBundle)
        throws RemoteException
      {
        // Byte code:
        //   0: invokestatic 30	android/os/Parcel:obtain	()Landroid/os/Parcel;
        //   3: astore_3
        //   4: invokestatic 30	android/os/Parcel:obtain	()Landroid/os/Parcel;
        //   7: astore 4
        //   9: aload_3
        //   10: ldc 32
        //   12: invokevirtual 36	android/os/Parcel:writeInterfaceToken	(Ljava/lang/String;)V
        //   15: aload_3
        //   16: aload_1
        //   17: invokevirtual 43	android/os/Parcel:writeString	(Ljava/lang/String;)V
        //   20: aload_2
        //   21: ifnull +45 -> 66
        //   24: aload_3
        //   25: iconst_1
        //   26: invokevirtual 40	android/os/Parcel:writeInt	(I)V
        //   29: aload_2
        //   30: aload_3
        //   31: iconst_0
        //   32: invokevirtual 141	android/os/Bundle:writeToParcel	(Landroid/os/Parcel;I)V
        //   35: aload_0
        //   36: getfield 19	android/media/session/ISessionController$Stub$Proxy:mRemote	Landroid/os/IBinder;
        //   39: bipush 33
        //   41: aload_3
        //   42: aload 4
        //   44: iconst_0
        //   45: invokeinterface 49 5 0
        //   50: pop
        //   51: aload 4
        //   53: invokevirtual 52	android/os/Parcel:readException	()V
        //   56: aload 4
        //   58: invokevirtual 55	android/os/Parcel:recycle	()V
        //   61: aload_3
        //   62: invokevirtual 55	android/os/Parcel:recycle	()V
        //   65: return
        //   66: aload_3
        //   67: iconst_0
        //   68: invokevirtual 40	android/os/Parcel:writeInt	(I)V
        //   71: goto -36 -> 35
        //   74: astore_1
        //   75: aload 4
        //   77: invokevirtual 55	android/os/Parcel:recycle	()V
        //   80: aload_3
        //   81: invokevirtual 55	android/os/Parcel:recycle	()V
        //   84: aload_1
        //   85: athrow
        // Local variable table:
        //   start	length	slot	name	signature
        //   0	86	0	this	Proxy
        //   0	86	1	paramString	String
        //   0	86	2	paramBundle	Bundle
        //   3	78	3	localParcel1	Parcel
        //   7	69	4	localParcel2	Parcel
        // Exception table:
        //   from	to	target	type
        //   9	20	74	finally
        //   24	35	74	finally
        //   35	56	74	finally
        //   66	71	74	finally
      }
      
      public boolean sendMediaButton(KeyEvent paramKeyEvent)
        throws RemoteException
      {
        Parcel localParcel1 = Parcel.obtain();
        Parcel localParcel2 = Parcel.obtain();
        for (;;)
        {
          try
          {
            localParcel1.writeInterfaceToken("android.media.session.ISessionController");
            if (paramKeyEvent != null)
            {
              localParcel1.writeInt(1);
              paramKeyEvent.writeToParcel(localParcel1, 0);
              this.mRemote.transact(2, localParcel1, localParcel2, 0);
              localParcel2.readException();
              int i = localParcel2.readInt();
              if (i != 0)
              {
                bool = true;
                return bool;
              }
            }
            else
            {
              localParcel1.writeInt(0);
              continue;
            }
            boolean bool = false;
          }
          finally
          {
            localParcel2.recycle();
            localParcel1.recycle();
          }
        }
      }
      
      public void setRemoteControlClientBrowsedPlayer()
        throws RemoteException
      {
        Parcel localParcel1 = Parcel.obtain();
        Parcel localParcel2 = Parcel.obtain();
        try
        {
          localParcel1.writeInterfaceToken("android.media.session.ISessionController");
          this.mRemote.transact(29, localParcel1, localParcel2, 0);
          localParcel2.readException();
          return;
        }
        finally
        {
          localParcel2.recycle();
          localParcel1.recycle();
        }
      }
      
      public void setRemoteControlClientPlayItem(long paramLong, int paramInt)
        throws RemoteException
      {
        Parcel localParcel1 = Parcel.obtain();
        Parcel localParcel2 = Parcel.obtain();
        try
        {
          localParcel1.writeInterfaceToken("android.media.session.ISessionController");
          localParcel1.writeLong(paramLong);
          localParcel1.writeInt(paramInt);
          this.mRemote.transact(30, localParcel1, localParcel2, 0);
          localParcel2.readException();
          return;
        }
        finally
        {
          localParcel2.recycle();
          localParcel1.recycle();
        }
      }
      
      public void setVolumeTo(int paramInt1, int paramInt2, String paramString)
        throws RemoteException
      {
        Parcel localParcel1 = Parcel.obtain();
        Parcel localParcel2 = Parcel.obtain();
        try
        {
          localParcel1.writeInterfaceToken("android.media.session.ISessionController");
          localParcel1.writeInt(paramInt1);
          localParcel1.writeInt(paramInt2);
          localParcel1.writeString(paramString);
          this.mRemote.transact(12, localParcel1, localParcel2, 0);
          localParcel2.readException();
          return;
        }
        finally
        {
          localParcel2.recycle();
          localParcel1.recycle();
        }
      }
      
      public void skipToQueueItem(long paramLong)
        throws RemoteException
      {
        Parcel localParcel1 = Parcel.obtain();
        Parcel localParcel2 = Parcel.obtain();
        try
        {
          localParcel1.writeInterfaceToken("android.media.session.ISessionController");
          localParcel1.writeLong(paramLong);
          this.mRemote.transact(21, localParcel1, localParcel2, 0);
          localParcel2.readException();
          return;
        }
        finally
        {
          localParcel2.recycle();
          localParcel1.recycle();
        }
      }
      
      public void stop()
        throws RemoteException
      {
        Parcel localParcel1 = Parcel.obtain();
        Parcel localParcel2 = Parcel.obtain();
        try
        {
          localParcel1.writeInterfaceToken("android.media.session.ISessionController");
          this.mRemote.transact(23, localParcel1, localParcel2, 0);
          localParcel2.readException();
          return;
        }
        finally
        {
          localParcel2.recycle();
          localParcel1.recycle();
        }
      }
      
      public void unregisterCallbackListener(ISessionControllerCallback paramISessionControllerCallback)
        throws RemoteException
      {
        IBinder localIBinder = null;
        Parcel localParcel1 = Parcel.obtain();
        Parcel localParcel2 = Parcel.obtain();
        try
        {
          localParcel1.writeInterfaceToken("android.media.session.ISessionController");
          if (paramISessionControllerCallback != null) {
            localIBinder = paramISessionControllerCallback.asBinder();
          }
          localParcel1.writeStrongBinder(localIBinder);
          this.mRemote.transact(4, localParcel1, localParcel2, 0);
          localParcel2.readException();
          return;
        }
        finally
        {
          localParcel2.recycle();
          localParcel1.recycle();
        }
      }
    }
  }
}


/* Location:              /Users/joshua/Desktop/system_framework/classes-dex2jar.jar!/android/media/session/ISessionController.class
 * Java compiler version: 6 (50.0)
 * JD-Core Version:       0.7.1
 */