package android.media.session;

import android.app.PendingIntent;
import android.content.pm.ParceledListSlice;
import android.media.AudioAttributes;
import android.media.MediaMetadata;
import android.os.Binder;
import android.os.Bundle;
import android.os.IBinder;
import android.os.IInterface;
import android.os.Parcel;
import android.os.Parcelable.ClassLoaderCreator;
import android.os.Parcelable.Creator;
import android.os.RemoteException;
import android.text.TextUtils;

public abstract interface ISession
  extends IInterface
{
  public abstract void destroy()
    throws RemoteException;
  
  public abstract String getCallingPackage()
    throws RemoteException;
  
  public abstract ISessionController getController()
    throws RemoteException;
  
  public abstract void playItemResponse(boolean paramBoolean)
    throws RemoteException;
  
  public abstract void sendEvent(String paramString, Bundle paramBundle)
    throws RemoteException;
  
  public abstract void setActive(boolean paramBoolean)
    throws RemoteException;
  
  public abstract void setCurrentVolume(int paramInt)
    throws RemoteException;
  
  public abstract void setExtras(Bundle paramBundle)
    throws RemoteException;
  
  public abstract void setFlags(int paramInt)
    throws RemoteException;
  
  public abstract void setLaunchPendingIntent(PendingIntent paramPendingIntent)
    throws RemoteException;
  
  public abstract void setMediaButtonReceiver(PendingIntent paramPendingIntent)
    throws RemoteException;
  
  public abstract void setMetadata(MediaMetadata paramMediaMetadata)
    throws RemoteException;
  
  public abstract void setPlaybackState(PlaybackState paramPlaybackState)
    throws RemoteException;
  
  public abstract void setPlaybackToLocal(AudioAttributes paramAudioAttributes)
    throws RemoteException;
  
  public abstract void setPlaybackToRemote(int paramInt1, int paramInt2)
    throws RemoteException;
  
  public abstract void setQueue(ParceledListSlice paramParceledListSlice)
    throws RemoteException;
  
  public abstract void setQueueTitle(CharSequence paramCharSequence)
    throws RemoteException;
  
  public abstract void setRatingType(int paramInt)
    throws RemoteException;
  
  public abstract void updateFolderInfoBrowsedPlayer(String paramString)
    throws RemoteException;
  
  public abstract void updateNowPlayingContentChange()
    throws RemoteException;
  
  public abstract void updateNowPlayingEntries(long[] paramArrayOfLong)
    throws RemoteException;
  
  public static abstract class Stub
    extends Binder
    implements ISession
  {
    private static final String DESCRIPTOR = "android.media.session.ISession";
    static final int TRANSACTION_destroy = 7;
    static final int TRANSACTION_getCallingPackage = 21;
    static final int TRANSACTION_getController = 2;
    static final int TRANSACTION_playItemResponse = 14;
    static final int TRANSACTION_sendEvent = 1;
    static final int TRANSACTION_setActive = 4;
    static final int TRANSACTION_setCurrentVolume = 20;
    static final int TRANSACTION_setExtras = 12;
    static final int TRANSACTION_setFlags = 3;
    static final int TRANSACTION_setLaunchPendingIntent = 6;
    static final int TRANSACTION_setMediaButtonReceiver = 5;
    static final int TRANSACTION_setMetadata = 8;
    static final int TRANSACTION_setPlaybackState = 9;
    static final int TRANSACTION_setPlaybackToLocal = 18;
    static final int TRANSACTION_setPlaybackToRemote = 19;
    static final int TRANSACTION_setQueue = 10;
    static final int TRANSACTION_setQueueTitle = 11;
    static final int TRANSACTION_setRatingType = 13;
    static final int TRANSACTION_updateFolderInfoBrowsedPlayer = 16;
    static final int TRANSACTION_updateNowPlayingContentChange = 17;
    static final int TRANSACTION_updateNowPlayingEntries = 15;
    
    public Stub()
    {
      attachInterface(this, "android.media.session.ISession");
    }
    
    public static ISession asInterface(IBinder paramIBinder)
    {
      if (paramIBinder == null) {
        return null;
      }
      IInterface localIInterface = paramIBinder.queryLocalInterface("android.media.session.ISession");
      if ((localIInterface != null) && ((localIInterface instanceof ISession))) {
        return (ISession)localIInterface;
      }
      return new Proxy(paramIBinder);
    }
    
    public IBinder asBinder()
    {
      return this;
    }
    
    public boolean onTransact(int paramInt1, Parcel paramParcel1, Parcel paramParcel2, int paramInt2)
      throws RemoteException
    {
      boolean bool;
      switch (paramInt1)
      {
      default: 
        return super.onTransact(paramInt1, paramParcel1, paramParcel2, paramInt2);
      case 1598968902: 
        paramParcel2.writeString("android.media.session.ISession");
        return true;
      case 1: 
        paramParcel1.enforceInterface("android.media.session.ISession");
        String str = paramParcel1.readString();
        if (paramParcel1.readInt() != 0) {}
        for (paramParcel1 = (Bundle)Bundle.CREATOR.createFromParcel(paramParcel1);; paramParcel1 = null)
        {
          sendEvent(str, paramParcel1);
          paramParcel2.writeNoException();
          return true;
        }
      case 2: 
        paramParcel1.enforceInterface("android.media.session.ISession");
        paramParcel1 = getController();
        paramParcel2.writeNoException();
        if (paramParcel1 != null) {}
        for (paramParcel1 = paramParcel1.asBinder();; paramParcel1 = null)
        {
          paramParcel2.writeStrongBinder(paramParcel1);
          return true;
        }
      case 3: 
        paramParcel1.enforceInterface("android.media.session.ISession");
        setFlags(paramParcel1.readInt());
        paramParcel2.writeNoException();
        return true;
      case 4: 
        paramParcel1.enforceInterface("android.media.session.ISession");
        if (paramParcel1.readInt() != 0) {}
        for (bool = true;; bool = false)
        {
          setActive(bool);
          paramParcel2.writeNoException();
          return true;
        }
      case 5: 
        paramParcel1.enforceInterface("android.media.session.ISession");
        if (paramParcel1.readInt() != 0) {}
        for (paramParcel1 = (PendingIntent)PendingIntent.CREATOR.createFromParcel(paramParcel1);; paramParcel1 = null)
        {
          setMediaButtonReceiver(paramParcel1);
          paramParcel2.writeNoException();
          return true;
        }
      case 6: 
        paramParcel1.enforceInterface("android.media.session.ISession");
        if (paramParcel1.readInt() != 0) {}
        for (paramParcel1 = (PendingIntent)PendingIntent.CREATOR.createFromParcel(paramParcel1);; paramParcel1 = null)
        {
          setLaunchPendingIntent(paramParcel1);
          paramParcel2.writeNoException();
          return true;
        }
      case 7: 
        paramParcel1.enforceInterface("android.media.session.ISession");
        destroy();
        paramParcel2.writeNoException();
        return true;
      case 8: 
        paramParcel1.enforceInterface("android.media.session.ISession");
        if (paramParcel1.readInt() != 0) {}
        for (paramParcel1 = (MediaMetadata)MediaMetadata.CREATOR.createFromParcel(paramParcel1);; paramParcel1 = null)
        {
          setMetadata(paramParcel1);
          paramParcel2.writeNoException();
          return true;
        }
      case 9: 
        paramParcel1.enforceInterface("android.media.session.ISession");
        if (paramParcel1.readInt() != 0) {}
        for (paramParcel1 = (PlaybackState)PlaybackState.CREATOR.createFromParcel(paramParcel1);; paramParcel1 = null)
        {
          setPlaybackState(paramParcel1);
          paramParcel2.writeNoException();
          return true;
        }
      case 10: 
        paramParcel1.enforceInterface("android.media.session.ISession");
        if (paramParcel1.readInt() != 0) {}
        for (paramParcel1 = (ParceledListSlice)ParceledListSlice.CREATOR.createFromParcel(paramParcel1);; paramParcel1 = null)
        {
          setQueue(paramParcel1);
          paramParcel2.writeNoException();
          return true;
        }
      case 11: 
        paramParcel1.enforceInterface("android.media.session.ISession");
        if (paramParcel1.readInt() != 0) {}
        for (paramParcel1 = (CharSequence)TextUtils.CHAR_SEQUENCE_CREATOR.createFromParcel(paramParcel1);; paramParcel1 = null)
        {
          setQueueTitle(paramParcel1);
          paramParcel2.writeNoException();
          return true;
        }
      case 12: 
        paramParcel1.enforceInterface("android.media.session.ISession");
        if (paramParcel1.readInt() != 0) {}
        for (paramParcel1 = (Bundle)Bundle.CREATOR.createFromParcel(paramParcel1);; paramParcel1 = null)
        {
          setExtras(paramParcel1);
          paramParcel2.writeNoException();
          return true;
        }
      case 13: 
        paramParcel1.enforceInterface("android.media.session.ISession");
        setRatingType(paramParcel1.readInt());
        paramParcel2.writeNoException();
        return true;
      case 14: 
        paramParcel1.enforceInterface("android.media.session.ISession");
        if (paramParcel1.readInt() != 0) {}
        for (bool = true;; bool = false)
        {
          playItemResponse(bool);
          paramParcel2.writeNoException();
          return true;
        }
      case 15: 
        paramParcel1.enforceInterface("android.media.session.ISession");
        updateNowPlayingEntries(paramParcel1.createLongArray());
        paramParcel2.writeNoException();
        return true;
      case 16: 
        paramParcel1.enforceInterface("android.media.session.ISession");
        updateFolderInfoBrowsedPlayer(paramParcel1.readString());
        paramParcel2.writeNoException();
        return true;
      case 17: 
        paramParcel1.enforceInterface("android.media.session.ISession");
        updateNowPlayingContentChange();
        paramParcel2.writeNoException();
        return true;
      case 18: 
        paramParcel1.enforceInterface("android.media.session.ISession");
        if (paramParcel1.readInt() != 0) {}
        for (paramParcel1 = (AudioAttributes)AudioAttributes.CREATOR.createFromParcel(paramParcel1);; paramParcel1 = null)
        {
          setPlaybackToLocal(paramParcel1);
          paramParcel2.writeNoException();
          return true;
        }
      case 19: 
        paramParcel1.enforceInterface("android.media.session.ISession");
        setPlaybackToRemote(paramParcel1.readInt(), paramParcel1.readInt());
        paramParcel2.writeNoException();
        return true;
      case 20: 
        paramParcel1.enforceInterface("android.media.session.ISession");
        setCurrentVolume(paramParcel1.readInt());
        paramParcel2.writeNoException();
        return true;
      }
      paramParcel1.enforceInterface("android.media.session.ISession");
      paramParcel1 = getCallingPackage();
      paramParcel2.writeNoException();
      paramParcel2.writeString(paramParcel1);
      return true;
    }
    
    private static class Proxy
      implements ISession
    {
      private IBinder mRemote;
      
      Proxy(IBinder paramIBinder)
      {
        this.mRemote = paramIBinder;
      }
      
      public IBinder asBinder()
      {
        return this.mRemote;
      }
      
      public void destroy()
        throws RemoteException
      {
        Parcel localParcel1 = Parcel.obtain();
        Parcel localParcel2 = Parcel.obtain();
        try
        {
          localParcel1.writeInterfaceToken("android.media.session.ISession");
          this.mRemote.transact(7, localParcel1, localParcel2, 0);
          localParcel2.readException();
          return;
        }
        finally
        {
          localParcel2.recycle();
          localParcel1.recycle();
        }
      }
      
      public String getCallingPackage()
        throws RemoteException
      {
        Parcel localParcel1 = Parcel.obtain();
        Parcel localParcel2 = Parcel.obtain();
        try
        {
          localParcel1.writeInterfaceToken("android.media.session.ISession");
          this.mRemote.transact(21, localParcel1, localParcel2, 0);
          localParcel2.readException();
          String str = localParcel2.readString();
          return str;
        }
        finally
        {
          localParcel2.recycle();
          localParcel1.recycle();
        }
      }
      
      public ISessionController getController()
        throws RemoteException
      {
        Parcel localParcel1 = Parcel.obtain();
        Parcel localParcel2 = Parcel.obtain();
        try
        {
          localParcel1.writeInterfaceToken("android.media.session.ISession");
          this.mRemote.transact(2, localParcel1, localParcel2, 0);
          localParcel2.readException();
          ISessionController localISessionController = ISessionController.Stub.asInterface(localParcel2.readStrongBinder());
          return localISessionController;
        }
        finally
        {
          localParcel2.recycle();
          localParcel1.recycle();
        }
      }
      
      public String getInterfaceDescriptor()
      {
        return "android.media.session.ISession";
      }
      
      public void playItemResponse(boolean paramBoolean)
        throws RemoteException
      {
        int i = 0;
        Parcel localParcel1 = Parcel.obtain();
        Parcel localParcel2 = Parcel.obtain();
        try
        {
          localParcel1.writeInterfaceToken("android.media.session.ISession");
          if (paramBoolean) {
            i = 1;
          }
          localParcel1.writeInt(i);
          this.mRemote.transact(14, localParcel1, localParcel2, 0);
          localParcel2.readException();
          return;
        }
        finally
        {
          localParcel2.recycle();
          localParcel1.recycle();
        }
      }
      
      /* Error */
      public void sendEvent(String paramString, Bundle paramBundle)
        throws RemoteException
      {
        // Byte code:
        //   0: invokestatic 31	android/os/Parcel:obtain	()Landroid/os/Parcel;
        //   3: astore_3
        //   4: invokestatic 31	android/os/Parcel:obtain	()Landroid/os/Parcel;
        //   7: astore 4
        //   9: aload_3
        //   10: ldc 33
        //   12: invokevirtual 37	android/os/Parcel:writeInterfaceToken	(Ljava/lang/String;)V
        //   15: aload_3
        //   16: aload_1
        //   17: invokevirtual 78	android/os/Parcel:writeString	(Ljava/lang/String;)V
        //   20: aload_2
        //   21: ifnull +44 -> 65
        //   24: aload_3
        //   25: iconst_1
        //   26: invokevirtual 73	android/os/Parcel:writeInt	(I)V
        //   29: aload_2
        //   30: aload_3
        //   31: iconst_0
        //   32: invokevirtual 84	android/os/Bundle:writeToParcel	(Landroid/os/Parcel;I)V
        //   35: aload_0
        //   36: getfield 19	android/media/session/ISession$Stub$Proxy:mRemote	Landroid/os/IBinder;
        //   39: iconst_1
        //   40: aload_3
        //   41: aload 4
        //   43: iconst_0
        //   44: invokeinterface 43 5 0
        //   49: pop
        //   50: aload 4
        //   52: invokevirtual 46	android/os/Parcel:readException	()V
        //   55: aload 4
        //   57: invokevirtual 49	android/os/Parcel:recycle	()V
        //   60: aload_3
        //   61: invokevirtual 49	android/os/Parcel:recycle	()V
        //   64: return
        //   65: aload_3
        //   66: iconst_0
        //   67: invokevirtual 73	android/os/Parcel:writeInt	(I)V
        //   70: goto -35 -> 35
        //   73: astore_1
        //   74: aload 4
        //   76: invokevirtual 49	android/os/Parcel:recycle	()V
        //   79: aload_3
        //   80: invokevirtual 49	android/os/Parcel:recycle	()V
        //   83: aload_1
        //   84: athrow
        // Local variable table:
        //   start	length	slot	name	signature
        //   0	85	0	this	Proxy
        //   0	85	1	paramString	String
        //   0	85	2	paramBundle	Bundle
        //   3	77	3	localParcel1	Parcel
        //   7	68	4	localParcel2	Parcel
        // Exception table:
        //   from	to	target	type
        //   9	20	73	finally
        //   24	35	73	finally
        //   35	55	73	finally
        //   65	70	73	finally
      }
      
      public void setActive(boolean paramBoolean)
        throws RemoteException
      {
        int i = 0;
        Parcel localParcel1 = Parcel.obtain();
        Parcel localParcel2 = Parcel.obtain();
        try
        {
          localParcel1.writeInterfaceToken("android.media.session.ISession");
          if (paramBoolean) {
            i = 1;
          }
          localParcel1.writeInt(i);
          this.mRemote.transact(4, localParcel1, localParcel2, 0);
          localParcel2.readException();
          return;
        }
        finally
        {
          localParcel2.recycle();
          localParcel1.recycle();
        }
      }
      
      public void setCurrentVolume(int paramInt)
        throws RemoteException
      {
        Parcel localParcel1 = Parcel.obtain();
        Parcel localParcel2 = Parcel.obtain();
        try
        {
          localParcel1.writeInterfaceToken("android.media.session.ISession");
          localParcel1.writeInt(paramInt);
          this.mRemote.transact(20, localParcel1, localParcel2, 0);
          localParcel2.readException();
          return;
        }
        finally
        {
          localParcel2.recycle();
          localParcel1.recycle();
        }
      }
      
      /* Error */
      public void setExtras(Bundle paramBundle)
        throws RemoteException
      {
        // Byte code:
        //   0: invokestatic 31	android/os/Parcel:obtain	()Landroid/os/Parcel;
        //   3: astore_2
        //   4: invokestatic 31	android/os/Parcel:obtain	()Landroid/os/Parcel;
        //   7: astore_3
        //   8: aload_2
        //   9: ldc 33
        //   11: invokevirtual 37	android/os/Parcel:writeInterfaceToken	(Ljava/lang/String;)V
        //   14: aload_1
        //   15: ifnull +42 -> 57
        //   18: aload_2
        //   19: iconst_1
        //   20: invokevirtual 73	android/os/Parcel:writeInt	(I)V
        //   23: aload_1
        //   24: aload_2
        //   25: iconst_0
        //   26: invokevirtual 84	android/os/Bundle:writeToParcel	(Landroid/os/Parcel;I)V
        //   29: aload_0
        //   30: getfield 19	android/media/session/ISession$Stub$Proxy:mRemote	Landroid/os/IBinder;
        //   33: bipush 12
        //   35: aload_2
        //   36: aload_3
        //   37: iconst_0
        //   38: invokeinterface 43 5 0
        //   43: pop
        //   44: aload_3
        //   45: invokevirtual 46	android/os/Parcel:readException	()V
        //   48: aload_3
        //   49: invokevirtual 49	android/os/Parcel:recycle	()V
        //   52: aload_2
        //   53: invokevirtual 49	android/os/Parcel:recycle	()V
        //   56: return
        //   57: aload_2
        //   58: iconst_0
        //   59: invokevirtual 73	android/os/Parcel:writeInt	(I)V
        //   62: goto -33 -> 29
        //   65: astore_1
        //   66: aload_3
        //   67: invokevirtual 49	android/os/Parcel:recycle	()V
        //   70: aload_2
        //   71: invokevirtual 49	android/os/Parcel:recycle	()V
        //   74: aload_1
        //   75: athrow
        // Local variable table:
        //   start	length	slot	name	signature
        //   0	76	0	this	Proxy
        //   0	76	1	paramBundle	Bundle
        //   3	68	2	localParcel1	Parcel
        //   7	60	3	localParcel2	Parcel
        // Exception table:
        //   from	to	target	type
        //   8	14	65	finally
        //   18	29	65	finally
        //   29	48	65	finally
        //   57	62	65	finally
      }
      
      public void setFlags(int paramInt)
        throws RemoteException
      {
        Parcel localParcel1 = Parcel.obtain();
        Parcel localParcel2 = Parcel.obtain();
        try
        {
          localParcel1.writeInterfaceToken("android.media.session.ISession");
          localParcel1.writeInt(paramInt);
          this.mRemote.transact(3, localParcel1, localParcel2, 0);
          localParcel2.readException();
          return;
        }
        finally
        {
          localParcel2.recycle();
          localParcel1.recycle();
        }
      }
      
      /* Error */
      public void setLaunchPendingIntent(PendingIntent paramPendingIntent)
        throws RemoteException
      {
        // Byte code:
        //   0: invokestatic 31	android/os/Parcel:obtain	()Landroid/os/Parcel;
        //   3: astore_2
        //   4: invokestatic 31	android/os/Parcel:obtain	()Landroid/os/Parcel;
        //   7: astore_3
        //   8: aload_2
        //   9: ldc 33
        //   11: invokevirtual 37	android/os/Parcel:writeInterfaceToken	(Ljava/lang/String;)V
        //   14: aload_1
        //   15: ifnull +42 -> 57
        //   18: aload_2
        //   19: iconst_1
        //   20: invokevirtual 73	android/os/Parcel:writeInt	(I)V
        //   23: aload_1
        //   24: aload_2
        //   25: iconst_0
        //   26: invokevirtual 94	android/app/PendingIntent:writeToParcel	(Landroid/os/Parcel;I)V
        //   29: aload_0
        //   30: getfield 19	android/media/session/ISession$Stub$Proxy:mRemote	Landroid/os/IBinder;
        //   33: bipush 6
        //   35: aload_2
        //   36: aload_3
        //   37: iconst_0
        //   38: invokeinterface 43 5 0
        //   43: pop
        //   44: aload_3
        //   45: invokevirtual 46	android/os/Parcel:readException	()V
        //   48: aload_3
        //   49: invokevirtual 49	android/os/Parcel:recycle	()V
        //   52: aload_2
        //   53: invokevirtual 49	android/os/Parcel:recycle	()V
        //   56: return
        //   57: aload_2
        //   58: iconst_0
        //   59: invokevirtual 73	android/os/Parcel:writeInt	(I)V
        //   62: goto -33 -> 29
        //   65: astore_1
        //   66: aload_3
        //   67: invokevirtual 49	android/os/Parcel:recycle	()V
        //   70: aload_2
        //   71: invokevirtual 49	android/os/Parcel:recycle	()V
        //   74: aload_1
        //   75: athrow
        // Local variable table:
        //   start	length	slot	name	signature
        //   0	76	0	this	Proxy
        //   0	76	1	paramPendingIntent	PendingIntent
        //   3	68	2	localParcel1	Parcel
        //   7	60	3	localParcel2	Parcel
        // Exception table:
        //   from	to	target	type
        //   8	14	65	finally
        //   18	29	65	finally
        //   29	48	65	finally
        //   57	62	65	finally
      }
      
      /* Error */
      public void setMediaButtonReceiver(PendingIntent paramPendingIntent)
        throws RemoteException
      {
        // Byte code:
        //   0: invokestatic 31	android/os/Parcel:obtain	()Landroid/os/Parcel;
        //   3: astore_2
        //   4: invokestatic 31	android/os/Parcel:obtain	()Landroid/os/Parcel;
        //   7: astore_3
        //   8: aload_2
        //   9: ldc 33
        //   11: invokevirtual 37	android/os/Parcel:writeInterfaceToken	(Ljava/lang/String;)V
        //   14: aload_1
        //   15: ifnull +41 -> 56
        //   18: aload_2
        //   19: iconst_1
        //   20: invokevirtual 73	android/os/Parcel:writeInt	(I)V
        //   23: aload_1
        //   24: aload_2
        //   25: iconst_0
        //   26: invokevirtual 94	android/app/PendingIntent:writeToParcel	(Landroid/os/Parcel;I)V
        //   29: aload_0
        //   30: getfield 19	android/media/session/ISession$Stub$Proxy:mRemote	Landroid/os/IBinder;
        //   33: iconst_5
        //   34: aload_2
        //   35: aload_3
        //   36: iconst_0
        //   37: invokeinterface 43 5 0
        //   42: pop
        //   43: aload_3
        //   44: invokevirtual 46	android/os/Parcel:readException	()V
        //   47: aload_3
        //   48: invokevirtual 49	android/os/Parcel:recycle	()V
        //   51: aload_2
        //   52: invokevirtual 49	android/os/Parcel:recycle	()V
        //   55: return
        //   56: aload_2
        //   57: iconst_0
        //   58: invokevirtual 73	android/os/Parcel:writeInt	(I)V
        //   61: goto -32 -> 29
        //   64: astore_1
        //   65: aload_3
        //   66: invokevirtual 49	android/os/Parcel:recycle	()V
        //   69: aload_2
        //   70: invokevirtual 49	android/os/Parcel:recycle	()V
        //   73: aload_1
        //   74: athrow
        // Local variable table:
        //   start	length	slot	name	signature
        //   0	75	0	this	Proxy
        //   0	75	1	paramPendingIntent	PendingIntent
        //   3	67	2	localParcel1	Parcel
        //   7	59	3	localParcel2	Parcel
        // Exception table:
        //   from	to	target	type
        //   8	14	64	finally
        //   18	29	64	finally
        //   29	47	64	finally
        //   56	61	64	finally
      }
      
      /* Error */
      public void setMetadata(MediaMetadata paramMediaMetadata)
        throws RemoteException
      {
        // Byte code:
        //   0: invokestatic 31	android/os/Parcel:obtain	()Landroid/os/Parcel;
        //   3: astore_2
        //   4: invokestatic 31	android/os/Parcel:obtain	()Landroid/os/Parcel;
        //   7: astore_3
        //   8: aload_2
        //   9: ldc 33
        //   11: invokevirtual 37	android/os/Parcel:writeInterfaceToken	(Ljava/lang/String;)V
        //   14: aload_1
        //   15: ifnull +42 -> 57
        //   18: aload_2
        //   19: iconst_1
        //   20: invokevirtual 73	android/os/Parcel:writeInt	(I)V
        //   23: aload_1
        //   24: aload_2
        //   25: iconst_0
        //   26: invokevirtual 100	android/media/MediaMetadata:writeToParcel	(Landroid/os/Parcel;I)V
        //   29: aload_0
        //   30: getfield 19	android/media/session/ISession$Stub$Proxy:mRemote	Landroid/os/IBinder;
        //   33: bipush 8
        //   35: aload_2
        //   36: aload_3
        //   37: iconst_0
        //   38: invokeinterface 43 5 0
        //   43: pop
        //   44: aload_3
        //   45: invokevirtual 46	android/os/Parcel:readException	()V
        //   48: aload_3
        //   49: invokevirtual 49	android/os/Parcel:recycle	()V
        //   52: aload_2
        //   53: invokevirtual 49	android/os/Parcel:recycle	()V
        //   56: return
        //   57: aload_2
        //   58: iconst_0
        //   59: invokevirtual 73	android/os/Parcel:writeInt	(I)V
        //   62: goto -33 -> 29
        //   65: astore_1
        //   66: aload_3
        //   67: invokevirtual 49	android/os/Parcel:recycle	()V
        //   70: aload_2
        //   71: invokevirtual 49	android/os/Parcel:recycle	()V
        //   74: aload_1
        //   75: athrow
        // Local variable table:
        //   start	length	slot	name	signature
        //   0	76	0	this	Proxy
        //   0	76	1	paramMediaMetadata	MediaMetadata
        //   3	68	2	localParcel1	Parcel
        //   7	60	3	localParcel2	Parcel
        // Exception table:
        //   from	to	target	type
        //   8	14	65	finally
        //   18	29	65	finally
        //   29	48	65	finally
        //   57	62	65	finally
      }
      
      /* Error */
      public void setPlaybackState(PlaybackState paramPlaybackState)
        throws RemoteException
      {
        // Byte code:
        //   0: invokestatic 31	android/os/Parcel:obtain	()Landroid/os/Parcel;
        //   3: astore_2
        //   4: invokestatic 31	android/os/Parcel:obtain	()Landroid/os/Parcel;
        //   7: astore_3
        //   8: aload_2
        //   9: ldc 33
        //   11: invokevirtual 37	android/os/Parcel:writeInterfaceToken	(Ljava/lang/String;)V
        //   14: aload_1
        //   15: ifnull +42 -> 57
        //   18: aload_2
        //   19: iconst_1
        //   20: invokevirtual 73	android/os/Parcel:writeInt	(I)V
        //   23: aload_1
        //   24: aload_2
        //   25: iconst_0
        //   26: invokevirtual 105	android/media/session/PlaybackState:writeToParcel	(Landroid/os/Parcel;I)V
        //   29: aload_0
        //   30: getfield 19	android/media/session/ISession$Stub$Proxy:mRemote	Landroid/os/IBinder;
        //   33: bipush 9
        //   35: aload_2
        //   36: aload_3
        //   37: iconst_0
        //   38: invokeinterface 43 5 0
        //   43: pop
        //   44: aload_3
        //   45: invokevirtual 46	android/os/Parcel:readException	()V
        //   48: aload_3
        //   49: invokevirtual 49	android/os/Parcel:recycle	()V
        //   52: aload_2
        //   53: invokevirtual 49	android/os/Parcel:recycle	()V
        //   56: return
        //   57: aload_2
        //   58: iconst_0
        //   59: invokevirtual 73	android/os/Parcel:writeInt	(I)V
        //   62: goto -33 -> 29
        //   65: astore_1
        //   66: aload_3
        //   67: invokevirtual 49	android/os/Parcel:recycle	()V
        //   70: aload_2
        //   71: invokevirtual 49	android/os/Parcel:recycle	()V
        //   74: aload_1
        //   75: athrow
        // Local variable table:
        //   start	length	slot	name	signature
        //   0	76	0	this	Proxy
        //   0	76	1	paramPlaybackState	PlaybackState
        //   3	68	2	localParcel1	Parcel
        //   7	60	3	localParcel2	Parcel
        // Exception table:
        //   from	to	target	type
        //   8	14	65	finally
        //   18	29	65	finally
        //   29	48	65	finally
        //   57	62	65	finally
      }
      
      /* Error */
      public void setPlaybackToLocal(AudioAttributes paramAudioAttributes)
        throws RemoteException
      {
        // Byte code:
        //   0: invokestatic 31	android/os/Parcel:obtain	()Landroid/os/Parcel;
        //   3: astore_2
        //   4: invokestatic 31	android/os/Parcel:obtain	()Landroid/os/Parcel;
        //   7: astore_3
        //   8: aload_2
        //   9: ldc 33
        //   11: invokevirtual 37	android/os/Parcel:writeInterfaceToken	(Ljava/lang/String;)V
        //   14: aload_1
        //   15: ifnull +42 -> 57
        //   18: aload_2
        //   19: iconst_1
        //   20: invokevirtual 73	android/os/Parcel:writeInt	(I)V
        //   23: aload_1
        //   24: aload_2
        //   25: iconst_0
        //   26: invokevirtual 110	android/media/AudioAttributes:writeToParcel	(Landroid/os/Parcel;I)V
        //   29: aload_0
        //   30: getfield 19	android/media/session/ISession$Stub$Proxy:mRemote	Landroid/os/IBinder;
        //   33: bipush 18
        //   35: aload_2
        //   36: aload_3
        //   37: iconst_0
        //   38: invokeinterface 43 5 0
        //   43: pop
        //   44: aload_3
        //   45: invokevirtual 46	android/os/Parcel:readException	()V
        //   48: aload_3
        //   49: invokevirtual 49	android/os/Parcel:recycle	()V
        //   52: aload_2
        //   53: invokevirtual 49	android/os/Parcel:recycle	()V
        //   56: return
        //   57: aload_2
        //   58: iconst_0
        //   59: invokevirtual 73	android/os/Parcel:writeInt	(I)V
        //   62: goto -33 -> 29
        //   65: astore_1
        //   66: aload_3
        //   67: invokevirtual 49	android/os/Parcel:recycle	()V
        //   70: aload_2
        //   71: invokevirtual 49	android/os/Parcel:recycle	()V
        //   74: aload_1
        //   75: athrow
        // Local variable table:
        //   start	length	slot	name	signature
        //   0	76	0	this	Proxy
        //   0	76	1	paramAudioAttributes	AudioAttributes
        //   3	68	2	localParcel1	Parcel
        //   7	60	3	localParcel2	Parcel
        // Exception table:
        //   from	to	target	type
        //   8	14	65	finally
        //   18	29	65	finally
        //   29	48	65	finally
        //   57	62	65	finally
      }
      
      public void setPlaybackToRemote(int paramInt1, int paramInt2)
        throws RemoteException
      {
        Parcel localParcel1 = Parcel.obtain();
        Parcel localParcel2 = Parcel.obtain();
        try
        {
          localParcel1.writeInterfaceToken("android.media.session.ISession");
          localParcel1.writeInt(paramInt1);
          localParcel1.writeInt(paramInt2);
          this.mRemote.transact(19, localParcel1, localParcel2, 0);
          localParcel2.readException();
          return;
        }
        finally
        {
          localParcel2.recycle();
          localParcel1.recycle();
        }
      }
      
      /* Error */
      public void setQueue(ParceledListSlice paramParceledListSlice)
        throws RemoteException
      {
        // Byte code:
        //   0: invokestatic 31	android/os/Parcel:obtain	()Landroid/os/Parcel;
        //   3: astore_2
        //   4: invokestatic 31	android/os/Parcel:obtain	()Landroid/os/Parcel;
        //   7: astore_3
        //   8: aload_2
        //   9: ldc 33
        //   11: invokevirtual 37	android/os/Parcel:writeInterfaceToken	(Ljava/lang/String;)V
        //   14: aload_1
        //   15: ifnull +42 -> 57
        //   18: aload_2
        //   19: iconst_1
        //   20: invokevirtual 73	android/os/Parcel:writeInt	(I)V
        //   23: aload_1
        //   24: aload_2
        //   25: iconst_0
        //   26: invokevirtual 117	android/content/pm/ParceledListSlice:writeToParcel	(Landroid/os/Parcel;I)V
        //   29: aload_0
        //   30: getfield 19	android/media/session/ISession$Stub$Proxy:mRemote	Landroid/os/IBinder;
        //   33: bipush 10
        //   35: aload_2
        //   36: aload_3
        //   37: iconst_0
        //   38: invokeinterface 43 5 0
        //   43: pop
        //   44: aload_3
        //   45: invokevirtual 46	android/os/Parcel:readException	()V
        //   48: aload_3
        //   49: invokevirtual 49	android/os/Parcel:recycle	()V
        //   52: aload_2
        //   53: invokevirtual 49	android/os/Parcel:recycle	()V
        //   56: return
        //   57: aload_2
        //   58: iconst_0
        //   59: invokevirtual 73	android/os/Parcel:writeInt	(I)V
        //   62: goto -33 -> 29
        //   65: astore_1
        //   66: aload_3
        //   67: invokevirtual 49	android/os/Parcel:recycle	()V
        //   70: aload_2
        //   71: invokevirtual 49	android/os/Parcel:recycle	()V
        //   74: aload_1
        //   75: athrow
        // Local variable table:
        //   start	length	slot	name	signature
        //   0	76	0	this	Proxy
        //   0	76	1	paramParceledListSlice	ParceledListSlice
        //   3	68	2	localParcel1	Parcel
        //   7	60	3	localParcel2	Parcel
        // Exception table:
        //   from	to	target	type
        //   8	14	65	finally
        //   18	29	65	finally
        //   29	48	65	finally
        //   57	62	65	finally
      }
      
      /* Error */
      public void setQueueTitle(CharSequence paramCharSequence)
        throws RemoteException
      {
        // Byte code:
        //   0: invokestatic 31	android/os/Parcel:obtain	()Landroid/os/Parcel;
        //   3: astore_2
        //   4: invokestatic 31	android/os/Parcel:obtain	()Landroid/os/Parcel;
        //   7: astore_3
        //   8: aload_2
        //   9: ldc 33
        //   11: invokevirtual 37	android/os/Parcel:writeInterfaceToken	(Ljava/lang/String;)V
        //   14: aload_1
        //   15: ifnull +42 -> 57
        //   18: aload_2
        //   19: iconst_1
        //   20: invokevirtual 73	android/os/Parcel:writeInt	(I)V
        //   23: aload_1
        //   24: aload_2
        //   25: iconst_0
        //   26: invokestatic 124	android/text/TextUtils:writeToParcel	(Ljava/lang/CharSequence;Landroid/os/Parcel;I)V
        //   29: aload_0
        //   30: getfield 19	android/media/session/ISession$Stub$Proxy:mRemote	Landroid/os/IBinder;
        //   33: bipush 11
        //   35: aload_2
        //   36: aload_3
        //   37: iconst_0
        //   38: invokeinterface 43 5 0
        //   43: pop
        //   44: aload_3
        //   45: invokevirtual 46	android/os/Parcel:readException	()V
        //   48: aload_3
        //   49: invokevirtual 49	android/os/Parcel:recycle	()V
        //   52: aload_2
        //   53: invokevirtual 49	android/os/Parcel:recycle	()V
        //   56: return
        //   57: aload_2
        //   58: iconst_0
        //   59: invokevirtual 73	android/os/Parcel:writeInt	(I)V
        //   62: goto -33 -> 29
        //   65: astore_1
        //   66: aload_3
        //   67: invokevirtual 49	android/os/Parcel:recycle	()V
        //   70: aload_2
        //   71: invokevirtual 49	android/os/Parcel:recycle	()V
        //   74: aload_1
        //   75: athrow
        // Local variable table:
        //   start	length	slot	name	signature
        //   0	76	0	this	Proxy
        //   0	76	1	paramCharSequence	CharSequence
        //   3	68	2	localParcel1	Parcel
        //   7	60	3	localParcel2	Parcel
        // Exception table:
        //   from	to	target	type
        //   8	14	65	finally
        //   18	29	65	finally
        //   29	48	65	finally
        //   57	62	65	finally
      }
      
      public void setRatingType(int paramInt)
        throws RemoteException
      {
        Parcel localParcel1 = Parcel.obtain();
        Parcel localParcel2 = Parcel.obtain();
        try
        {
          localParcel1.writeInterfaceToken("android.media.session.ISession");
          localParcel1.writeInt(paramInt);
          this.mRemote.transact(13, localParcel1, localParcel2, 0);
          localParcel2.readException();
          return;
        }
        finally
        {
          localParcel2.recycle();
          localParcel1.recycle();
        }
      }
      
      public void updateFolderInfoBrowsedPlayer(String paramString)
        throws RemoteException
      {
        Parcel localParcel1 = Parcel.obtain();
        Parcel localParcel2 = Parcel.obtain();
        try
        {
          localParcel1.writeInterfaceToken("android.media.session.ISession");
          localParcel1.writeString(paramString);
          this.mRemote.transact(16, localParcel1, localParcel2, 0);
          localParcel2.readException();
          return;
        }
        finally
        {
          localParcel2.recycle();
          localParcel1.recycle();
        }
      }
      
      public void updateNowPlayingContentChange()
        throws RemoteException
      {
        Parcel localParcel1 = Parcel.obtain();
        Parcel localParcel2 = Parcel.obtain();
        try
        {
          localParcel1.writeInterfaceToken("android.media.session.ISession");
          this.mRemote.transact(17, localParcel1, localParcel2, 0);
          localParcel2.readException();
          return;
        }
        finally
        {
          localParcel2.recycle();
          localParcel1.recycle();
        }
      }
      
      public void updateNowPlayingEntries(long[] paramArrayOfLong)
        throws RemoteException
      {
        Parcel localParcel1 = Parcel.obtain();
        Parcel localParcel2 = Parcel.obtain();
        try
        {
          localParcel1.writeInterfaceToken("android.media.session.ISession");
          localParcel1.writeLongArray(paramArrayOfLong);
          this.mRemote.transact(15, localParcel1, localParcel2, 0);
          localParcel2.readException();
          return;
        }
        finally
        {
          localParcel2.recycle();
          localParcel1.recycle();
        }
      }
    }
  }
}


/* Location:              /Users/joshua/Desktop/system_framework/classes-dex2jar.jar!/android/media/session/ISession.class
 * Java compiler version: 6 (50.0)
 * JD-Core Version:       0.7.1
 */