package com.amap.api.mapcore2d;

public class ek
{
  /* Error */
  static byte[] a(du paramdu, String paramString)
  {
    // Byte code:
    //   0: aconst_null
    //   1: astore_3
    //   2: aconst_null
    //   3: astore 4
    //   5: aconst_null
    //   6: astore 6
    //   8: aconst_null
    //   9: astore_2
    //   10: iconst_0
    //   11: newarray <illegal type>
    //   13: astore 7
    //   15: aload_0
    //   16: aload_1
    //   17: invokevirtual 13	com/amap/api/mapcore2d/du:a	(Ljava/lang/String;)Lcom/amap/api/mapcore2d/du$b;
    //   20: astore 5
    //   22: aload 5
    //   24: astore_3
    //   25: aload_3
    //   26: ifnull +102 -> 128
    //   29: aload 4
    //   31: astore_2
    //   32: aload_3
    //   33: astore 4
    //   35: aload 7
    //   37: astore 5
    //   39: aload_3
    //   40: iconst_0
    //   41: invokevirtual 18	com/amap/api/mapcore2d/du$b:a	(I)Ljava/io/InputStream;
    //   44: astore 8
    //   46: aload 8
    //   48: ifnull +87 -> 135
    //   51: aload 8
    //   53: astore_2
    //   54: aload_3
    //   55: astore 4
    //   57: aload 7
    //   59: astore 5
    //   61: aload 8
    //   63: astore 6
    //   65: aload 8
    //   67: invokevirtual 24	java/io/InputStream:available	()I
    //   70: newarray <illegal type>
    //   72: astore 7
    //   74: aload 8
    //   76: astore_2
    //   77: aload_3
    //   78: astore 4
    //   80: aload 7
    //   82: astore 5
    //   84: aload 8
    //   86: astore 6
    //   88: aload 8
    //   90: aload 7
    //   92: invokevirtual 28	java/io/InputStream:read	([B)I
    //   95: pop
    //   96: aload 8
    //   98: astore_2
    //   99: aload_3
    //   100: astore 4
    //   102: aload 7
    //   104: astore 5
    //   106: aload 8
    //   108: astore 6
    //   110: aload_0
    //   111: aload_1
    //   112: invokevirtual 32	com/amap/api/mapcore2d/du:c	(Ljava/lang/String;)Z
    //   115: pop
    //   116: aload 8
    //   118: ifnonnull +128 -> 246
    //   121: aload_3
    //   122: ifnonnull +140 -> 262
    //   125: aload 7
    //   127: areturn
    //   128: aload_3
    //   129: ifnonnull +71 -> 200
    //   132: aload 7
    //   134: areturn
    //   135: aload 8
    //   137: ifnonnull +78 -> 215
    //   140: aload_3
    //   141: ifnonnull +90 -> 231
    //   144: aload 7
    //   146: areturn
    //   147: astore_0
    //   148: aconst_null
    //   149: astore_3
    //   150: aload_2
    //   151: astore 6
    //   153: aload 7
    //   155: astore 5
    //   157: aload 6
    //   159: astore_2
    //   160: aload_3
    //   161: astore 4
    //   163: aload_0
    //   164: ldc 34
    //   166: ldc 36
    //   168: invokestatic 41	com/amap/api/mapcore2d/cy:a	(Ljava/lang/Throwable;Ljava/lang/String;Ljava/lang/String;)V
    //   171: aload 6
    //   173: ifnonnull +104 -> 277
    //   176: aload_3
    //   177: ifnonnull +116 -> 293
    //   180: aload 5
    //   182: areturn
    //   183: astore_0
    //   184: aconst_null
    //   185: astore 4
    //   187: aload_3
    //   188: astore_2
    //   189: aload_2
    //   190: ifnonnull +118 -> 308
    //   193: aload 4
    //   195: ifnonnull +128 -> 323
    //   198: aload_0
    //   199: athrow
    //   200: aload_3
    //   201: invokevirtual 45	com/amap/api/mapcore2d/du$b:close	()V
    //   204: aload 7
    //   206: areturn
    //   207: astore_0
    //   208: aload_0
    //   209: invokevirtual 48	java/lang/Throwable:printStackTrace	()V
    //   212: aload 7
    //   214: areturn
    //   215: aload 8
    //   217: invokevirtual 49	java/io/InputStream:close	()V
    //   220: goto -80 -> 140
    //   223: astore_0
    //   224: aload_0
    //   225: invokevirtual 48	java/lang/Throwable:printStackTrace	()V
    //   228: goto -88 -> 140
    //   231: aload_3
    //   232: invokevirtual 45	com/amap/api/mapcore2d/du$b:close	()V
    //   235: aload 7
    //   237: areturn
    //   238: astore_0
    //   239: aload_0
    //   240: invokevirtual 48	java/lang/Throwable:printStackTrace	()V
    //   243: aload 7
    //   245: areturn
    //   246: aload 8
    //   248: invokevirtual 49	java/io/InputStream:close	()V
    //   251: goto -130 -> 121
    //   254: astore_0
    //   255: aload_0
    //   256: invokevirtual 48	java/lang/Throwable:printStackTrace	()V
    //   259: goto -138 -> 121
    //   262: aload_3
    //   263: invokevirtual 45	com/amap/api/mapcore2d/du$b:close	()V
    //   266: aload 7
    //   268: areturn
    //   269: astore_0
    //   270: aload_0
    //   271: invokevirtual 48	java/lang/Throwable:printStackTrace	()V
    //   274: aload 7
    //   276: areturn
    //   277: aload 6
    //   279: invokevirtual 49	java/io/InputStream:close	()V
    //   282: goto -106 -> 176
    //   285: astore_0
    //   286: aload_0
    //   287: invokevirtual 48	java/lang/Throwable:printStackTrace	()V
    //   290: goto -114 -> 176
    //   293: aload_3
    //   294: invokevirtual 45	com/amap/api/mapcore2d/du$b:close	()V
    //   297: aload 5
    //   299: areturn
    //   300: astore_0
    //   301: aload_0
    //   302: invokevirtual 48	java/lang/Throwable:printStackTrace	()V
    //   305: aload 5
    //   307: areturn
    //   308: aload_2
    //   309: invokevirtual 49	java/io/InputStream:close	()V
    //   312: goto -119 -> 193
    //   315: astore_1
    //   316: aload_1
    //   317: invokevirtual 48	java/lang/Throwable:printStackTrace	()V
    //   320: goto -127 -> 193
    //   323: aload 4
    //   325: invokevirtual 45	com/amap/api/mapcore2d/du$b:close	()V
    //   328: goto -130 -> 198
    //   331: astore_1
    //   332: aload_1
    //   333: invokevirtual 48	java/lang/Throwable:printStackTrace	()V
    //   336: goto -138 -> 198
    //   339: astore_0
    //   340: goto -151 -> 189
    //   343: astore_0
    //   344: goto -187 -> 157
    // Local variable table:
    //   start	length	slot	name	signature
    //   0	347	0	paramdu	du
    //   0	347	1	paramString	String
    //   9	300	2	localObject1	Object
    //   1	293	3	localObject2	Object
    //   3	321	4	localObject3	Object
    //   20	286	5	localObject4	Object
    //   6	272	6	localObject5	Object
    //   13	262	7	arrayOfByte	byte[]
    //   44	203	8	localInputStream	java.io.InputStream
    // Exception table:
    //   from	to	target	type
    //   15	22	147	java/lang/Throwable
    //   15	22	183	finally
    //   200	204	207	java/lang/Throwable
    //   215	220	223	java/lang/Throwable
    //   231	235	238	java/lang/Throwable
    //   246	251	254	java/lang/Throwable
    //   262	266	269	java/lang/Throwable
    //   277	282	285	java/lang/Throwable
    //   293	297	300	java/lang/Throwable
    //   308	312	315	java/lang/Throwable
    //   323	328	331	java/lang/Throwable
    //   39	46	339	finally
    //   65	74	339	finally
    //   88	96	339	finally
    //   110	116	339	finally
    //   163	171	339	finally
    //   39	46	343	java/lang/Throwable
    //   65	74	343	java/lang/Throwable
    //   88	96	343	java/lang/Throwable
    //   110	116	343	java/lang/Throwable
  }
}


/* Location:              /Users/joshua/Desktop/system_framework/classes-dex2jar.jar!/com/amap/api/mapcore2d/ek.class
 * Java compiler version: 6 (50.0)
 * JD-Core Version:       0.7.1
 */