package android.bluetooth;

import android.os.Binder;
import android.os.Bundle;
import android.os.IBinder;
import android.os.IInterface;
import android.os.Parcel;
import android.os.Parcelable.Creator;
import android.os.RemoteException;
import java.util.ArrayList;
import java.util.List;

public abstract interface IBluetoothHeadsetClient
  extends IInterface
{
  public abstract boolean acceptCall(BluetoothDevice paramBluetoothDevice, int paramInt)
    throws RemoteException;
  
  public abstract boolean acceptIncomingConnect(BluetoothDevice paramBluetoothDevice)
    throws RemoteException;
  
  public abstract boolean connect(BluetoothDevice paramBluetoothDevice)
    throws RemoteException;
  
  public abstract boolean connectAudio()
    throws RemoteException;
  
  public abstract boolean dial(BluetoothDevice paramBluetoothDevice, String paramString)
    throws RemoteException;
  
  public abstract boolean dialMemory(BluetoothDevice paramBluetoothDevice, int paramInt)
    throws RemoteException;
  
  public abstract boolean disconnect(BluetoothDevice paramBluetoothDevice)
    throws RemoteException;
  
  public abstract boolean disconnectAudio()
    throws RemoteException;
  
  public abstract boolean enterPrivateMode(BluetoothDevice paramBluetoothDevice, int paramInt)
    throws RemoteException;
  
  public abstract boolean explicitCallTransfer(BluetoothDevice paramBluetoothDevice)
    throws RemoteException;
  
  public abstract boolean getAudioRouteAllowed()
    throws RemoteException;
  
  public abstract int getAudioState(BluetoothDevice paramBluetoothDevice)
    throws RemoteException;
  
  public abstract List<BluetoothDevice> getConnectedDevices()
    throws RemoteException;
  
  public abstract int getConnectionState(BluetoothDevice paramBluetoothDevice)
    throws RemoteException;
  
  public abstract Bundle getCurrentAgEvents(BluetoothDevice paramBluetoothDevice)
    throws RemoteException;
  
  public abstract Bundle getCurrentAgFeatures(BluetoothDevice paramBluetoothDevice)
    throws RemoteException;
  
  public abstract List<BluetoothHeadsetClientCall> getCurrentCalls(BluetoothDevice paramBluetoothDevice)
    throws RemoteException;
  
  public abstract List<BluetoothDevice> getDevicesMatchingConnectionStates(int[] paramArrayOfInt)
    throws RemoteException;
  
  public abstract boolean getLastVoiceTagNumber(BluetoothDevice paramBluetoothDevice)
    throws RemoteException;
  
  public abstract int getPriority(BluetoothDevice paramBluetoothDevice)
    throws RemoteException;
  
  public abstract boolean holdCall(BluetoothDevice paramBluetoothDevice)
    throws RemoteException;
  
  public abstract boolean redial(BluetoothDevice paramBluetoothDevice)
    throws RemoteException;
  
  public abstract boolean rejectCall(BluetoothDevice paramBluetoothDevice)
    throws RemoteException;
  
  public abstract boolean rejectIncomingConnect(BluetoothDevice paramBluetoothDevice)
    throws RemoteException;
  
  public abstract boolean sendDTMF(BluetoothDevice paramBluetoothDevice, byte paramByte)
    throws RemoteException;
  
  public abstract void setAudioRouteAllowed(boolean paramBoolean)
    throws RemoteException;
  
  public abstract boolean setPriority(BluetoothDevice paramBluetoothDevice, int paramInt)
    throws RemoteException;
  
  public abstract boolean startVoiceRecognition(BluetoothDevice paramBluetoothDevice)
    throws RemoteException;
  
  public abstract boolean stopVoiceRecognition(BluetoothDevice paramBluetoothDevice)
    throws RemoteException;
  
  public abstract boolean terminateCall(BluetoothDevice paramBluetoothDevice, int paramInt)
    throws RemoteException;
  
  public static abstract class Stub
    extends Binder
    implements IBluetoothHeadsetClient
  {
    private static final String DESCRIPTOR = "android.bluetooth.IBluetoothHeadsetClient";
    static final int TRANSACTION_acceptCall = 14;
    static final int TRANSACTION_acceptIncomingConnect = 3;
    static final int TRANSACTION_connect = 1;
    static final int TRANSACTION_connectAudio = 26;
    static final int TRANSACTION_dial = 21;
    static final int TRANSACTION_dialMemory = 22;
    static final int TRANSACTION_disconnect = 2;
    static final int TRANSACTION_disconnectAudio = 27;
    static final int TRANSACTION_enterPrivateMode = 18;
    static final int TRANSACTION_explicitCallTransfer = 19;
    static final int TRANSACTION_getAudioRouteAllowed = 29;
    static final int TRANSACTION_getAudioState = 25;
    static final int TRANSACTION_getConnectedDevices = 5;
    static final int TRANSACTION_getConnectionState = 7;
    static final int TRANSACTION_getCurrentAgEvents = 13;
    static final int TRANSACTION_getCurrentAgFeatures = 30;
    static final int TRANSACTION_getCurrentCalls = 12;
    static final int TRANSACTION_getDevicesMatchingConnectionStates = 6;
    static final int TRANSACTION_getLastVoiceTagNumber = 24;
    static final int TRANSACTION_getPriority = 9;
    static final int TRANSACTION_holdCall = 15;
    static final int TRANSACTION_redial = 20;
    static final int TRANSACTION_rejectCall = 16;
    static final int TRANSACTION_rejectIncomingConnect = 4;
    static final int TRANSACTION_sendDTMF = 23;
    static final int TRANSACTION_setAudioRouteAllowed = 28;
    static final int TRANSACTION_setPriority = 8;
    static final int TRANSACTION_startVoiceRecognition = 10;
    static final int TRANSACTION_stopVoiceRecognition = 11;
    static final int TRANSACTION_terminateCall = 17;
    
    public Stub()
    {
      attachInterface(this, "android.bluetooth.IBluetoothHeadsetClient");
    }
    
    public static IBluetoothHeadsetClient asInterface(IBinder paramIBinder)
    {
      if (paramIBinder == null) {
        return null;
      }
      IInterface localIInterface = paramIBinder.queryLocalInterface("android.bluetooth.IBluetoothHeadsetClient");
      if ((localIInterface != null) && ((localIInterface instanceof IBluetoothHeadsetClient))) {
        return (IBluetoothHeadsetClient)localIInterface;
      }
      return new Proxy(paramIBinder);
    }
    
    public IBinder asBinder()
    {
      return this;
    }
    
    public boolean onTransact(int paramInt1, Parcel paramParcel1, Parcel paramParcel2, int paramInt2)
      throws RemoteException
    {
      boolean bool;
      label334:
      label395:
      label456:
      label517:
      BluetoothDevice localBluetoothDevice;
      switch (paramInt1)
      {
      default: 
        return super.onTransact(paramInt1, paramParcel1, paramParcel2, paramInt2);
      case 1598968902: 
        paramParcel2.writeString("android.bluetooth.IBluetoothHeadsetClient");
        return true;
      case 1: 
        paramParcel1.enforceInterface("android.bluetooth.IBluetoothHeadsetClient");
        if (paramParcel1.readInt() != 0)
        {
          paramParcel1 = (BluetoothDevice)BluetoothDevice.CREATOR.createFromParcel(paramParcel1);
          bool = connect(paramParcel1);
          paramParcel2.writeNoException();
          if (!bool) {
            break label334;
          }
        }
        for (paramInt1 = 1;; paramInt1 = 0)
        {
          paramParcel2.writeInt(paramInt1);
          return true;
          paramParcel1 = null;
          break;
        }
      case 2: 
        paramParcel1.enforceInterface("android.bluetooth.IBluetoothHeadsetClient");
        if (paramParcel1.readInt() != 0)
        {
          paramParcel1 = (BluetoothDevice)BluetoothDevice.CREATOR.createFromParcel(paramParcel1);
          bool = disconnect(paramParcel1);
          paramParcel2.writeNoException();
          if (!bool) {
            break label395;
          }
        }
        for (paramInt1 = 1;; paramInt1 = 0)
        {
          paramParcel2.writeInt(paramInt1);
          return true;
          paramParcel1 = null;
          break;
        }
      case 3: 
        paramParcel1.enforceInterface("android.bluetooth.IBluetoothHeadsetClient");
        if (paramParcel1.readInt() != 0)
        {
          paramParcel1 = (BluetoothDevice)BluetoothDevice.CREATOR.createFromParcel(paramParcel1);
          bool = acceptIncomingConnect(paramParcel1);
          paramParcel2.writeNoException();
          if (!bool) {
            break label456;
          }
        }
        for (paramInt1 = 1;; paramInt1 = 0)
        {
          paramParcel2.writeInt(paramInt1);
          return true;
          paramParcel1 = null;
          break;
        }
      case 4: 
        paramParcel1.enforceInterface("android.bluetooth.IBluetoothHeadsetClient");
        if (paramParcel1.readInt() != 0)
        {
          paramParcel1 = (BluetoothDevice)BluetoothDevice.CREATOR.createFromParcel(paramParcel1);
          bool = rejectIncomingConnect(paramParcel1);
          paramParcel2.writeNoException();
          if (!bool) {
            break label517;
          }
        }
        for (paramInt1 = 1;; paramInt1 = 0)
        {
          paramParcel2.writeInt(paramInt1);
          return true;
          paramParcel1 = null;
          break;
        }
      case 5: 
        paramParcel1.enforceInterface("android.bluetooth.IBluetoothHeadsetClient");
        paramParcel1 = getConnectedDevices();
        paramParcel2.writeNoException();
        paramParcel2.writeTypedList(paramParcel1);
        return true;
      case 6: 
        paramParcel1.enforceInterface("android.bluetooth.IBluetoothHeadsetClient");
        paramParcel1 = getDevicesMatchingConnectionStates(paramParcel1.createIntArray());
        paramParcel2.writeNoException();
        paramParcel2.writeTypedList(paramParcel1);
        return true;
      case 7: 
        paramParcel1.enforceInterface("android.bluetooth.IBluetoothHeadsetClient");
        if (paramParcel1.readInt() != 0) {}
        for (paramParcel1 = (BluetoothDevice)BluetoothDevice.CREATOR.createFromParcel(paramParcel1);; paramParcel1 = null)
        {
          paramInt1 = getConnectionState(paramParcel1);
          paramParcel2.writeNoException();
          paramParcel2.writeInt(paramInt1);
          return true;
        }
      case 8: 
        paramParcel1.enforceInterface("android.bluetooth.IBluetoothHeadsetClient");
        if (paramParcel1.readInt() != 0)
        {
          localBluetoothDevice = (BluetoothDevice)BluetoothDevice.CREATOR.createFromParcel(paramParcel1);
          bool = setPriority(localBluetoothDevice, paramParcel1.readInt());
          paramParcel2.writeNoException();
          if (!bool) {
            break label681;
          }
        }
        for (paramInt1 = 1;; paramInt1 = 0)
        {
          paramParcel2.writeInt(paramInt1);
          return true;
          localBluetoothDevice = null;
          break;
        }
      case 9: 
        paramParcel1.enforceInterface("android.bluetooth.IBluetoothHeadsetClient");
        if (paramParcel1.readInt() != 0) {}
        for (paramParcel1 = (BluetoothDevice)BluetoothDevice.CREATOR.createFromParcel(paramParcel1);; paramParcel1 = null)
        {
          paramInt1 = getPriority(paramParcel1);
          paramParcel2.writeNoException();
          paramParcel2.writeInt(paramInt1);
          return true;
        }
      case 10: 
        paramParcel1.enforceInterface("android.bluetooth.IBluetoothHeadsetClient");
        if (paramParcel1.readInt() != 0)
        {
          paramParcel1 = (BluetoothDevice)BluetoothDevice.CREATOR.createFromParcel(paramParcel1);
          bool = startVoiceRecognition(paramParcel1);
          paramParcel2.writeNoException();
          if (!bool) {
            break label790;
          }
        }
        for (paramInt1 = 1;; paramInt1 = 0)
        {
          paramParcel2.writeInt(paramInt1);
          return true;
          paramParcel1 = null;
          break;
        }
      case 11: 
        paramParcel1.enforceInterface("android.bluetooth.IBluetoothHeadsetClient");
        if (paramParcel1.readInt() != 0)
        {
          paramParcel1 = (BluetoothDevice)BluetoothDevice.CREATOR.createFromParcel(paramParcel1);
          bool = stopVoiceRecognition(paramParcel1);
          paramParcel2.writeNoException();
          if (!bool) {
            break label851;
          }
        }
        for (paramInt1 = 1;; paramInt1 = 0)
        {
          paramParcel2.writeInt(paramInt1);
          return true;
          paramParcel1 = null;
          break;
        }
      case 12: 
        paramParcel1.enforceInterface("android.bluetooth.IBluetoothHeadsetClient");
        if (paramParcel1.readInt() != 0) {}
        for (paramParcel1 = (BluetoothDevice)BluetoothDevice.CREATOR.createFromParcel(paramParcel1);; paramParcel1 = null)
        {
          paramParcel1 = getCurrentCalls(paramParcel1);
          paramParcel2.writeNoException();
          paramParcel2.writeTypedList(paramParcel1);
          return true;
        }
      case 13: 
        paramParcel1.enforceInterface("android.bluetooth.IBluetoothHeadsetClient");
        if (paramParcel1.readInt() != 0)
        {
          paramParcel1 = (BluetoothDevice)BluetoothDevice.CREATOR.createFromParcel(paramParcel1);
          paramParcel1 = getCurrentAgEvents(paramParcel1);
          paramParcel2.writeNoException();
          if (paramParcel1 == null) {
            break label962;
          }
          paramParcel2.writeInt(1);
          paramParcel1.writeToParcel(paramParcel2, 1);
        }
        for (;;)
        {
          return true;
          paramParcel1 = null;
          break;
          paramParcel2.writeInt(0);
        }
      case 14: 
        paramParcel1.enforceInterface("android.bluetooth.IBluetoothHeadsetClient");
        if (paramParcel1.readInt() != 0)
        {
          localBluetoothDevice = (BluetoothDevice)BluetoothDevice.CREATOR.createFromParcel(paramParcel1);
          bool = acceptCall(localBluetoothDevice, paramParcel1.readInt());
          paramParcel2.writeNoException();
          if (!bool) {
            break label1033;
          }
        }
        for (paramInt1 = 1;; paramInt1 = 0)
        {
          paramParcel2.writeInt(paramInt1);
          return true;
          localBluetoothDevice = null;
          break;
        }
      case 15: 
        paramParcel1.enforceInterface("android.bluetooth.IBluetoothHeadsetClient");
        if (paramParcel1.readInt() != 0)
        {
          paramParcel1 = (BluetoothDevice)BluetoothDevice.CREATOR.createFromParcel(paramParcel1);
          bool = holdCall(paramParcel1);
          paramParcel2.writeNoException();
          if (!bool) {
            break label1094;
          }
        }
        for (paramInt1 = 1;; paramInt1 = 0)
        {
          paramParcel2.writeInt(paramInt1);
          return true;
          paramParcel1 = null;
          break;
        }
      case 16: 
        paramParcel1.enforceInterface("android.bluetooth.IBluetoothHeadsetClient");
        if (paramParcel1.readInt() != 0)
        {
          paramParcel1 = (BluetoothDevice)BluetoothDevice.CREATOR.createFromParcel(paramParcel1);
          bool = rejectCall(paramParcel1);
          paramParcel2.writeNoException();
          if (!bool) {
            break label1155;
          }
        }
        for (paramInt1 = 1;; paramInt1 = 0)
        {
          paramParcel2.writeInt(paramInt1);
          return true;
          paramParcel1 = null;
          break;
        }
      case 17: 
        paramParcel1.enforceInterface("android.bluetooth.IBluetoothHeadsetClient");
        if (paramParcel1.readInt() != 0)
        {
          localBluetoothDevice = (BluetoothDevice)BluetoothDevice.CREATOR.createFromParcel(paramParcel1);
          bool = terminateCall(localBluetoothDevice, paramParcel1.readInt());
          paramParcel2.writeNoException();
          if (!bool) {
            break label1223;
          }
        }
        for (paramInt1 = 1;; paramInt1 = 0)
        {
          paramParcel2.writeInt(paramInt1);
          return true;
          localBluetoothDevice = null;
          break;
        }
      case 18: 
        paramParcel1.enforceInterface("android.bluetooth.IBluetoothHeadsetClient");
        if (paramParcel1.readInt() != 0)
        {
          localBluetoothDevice = (BluetoothDevice)BluetoothDevice.CREATOR.createFromParcel(paramParcel1);
          bool = enterPrivateMode(localBluetoothDevice, paramParcel1.readInt());
          paramParcel2.writeNoException();
          if (!bool) {
            break label1291;
          }
        }
        for (paramInt1 = 1;; paramInt1 = 0)
        {
          paramParcel2.writeInt(paramInt1);
          return true;
          localBluetoothDevice = null;
          break;
        }
      case 19: 
        paramParcel1.enforceInterface("android.bluetooth.IBluetoothHeadsetClient");
        if (paramParcel1.readInt() != 0)
        {
          paramParcel1 = (BluetoothDevice)BluetoothDevice.CREATOR.createFromParcel(paramParcel1);
          bool = explicitCallTransfer(paramParcel1);
          paramParcel2.writeNoException();
          if (!bool) {
            break label1352;
          }
        }
        for (paramInt1 = 1;; paramInt1 = 0)
        {
          paramParcel2.writeInt(paramInt1);
          return true;
          paramParcel1 = null;
          break;
        }
      case 20: 
        paramParcel1.enforceInterface("android.bluetooth.IBluetoothHeadsetClient");
        if (paramParcel1.readInt() != 0)
        {
          paramParcel1 = (BluetoothDevice)BluetoothDevice.CREATOR.createFromParcel(paramParcel1);
          bool = redial(paramParcel1);
          paramParcel2.writeNoException();
          if (!bool) {
            break label1413;
          }
        }
        for (paramInt1 = 1;; paramInt1 = 0)
        {
          paramParcel2.writeInt(paramInt1);
          return true;
          paramParcel1 = null;
          break;
        }
      case 21: 
        paramParcel1.enforceInterface("android.bluetooth.IBluetoothHeadsetClient");
        if (paramParcel1.readInt() != 0)
        {
          localBluetoothDevice = (BluetoothDevice)BluetoothDevice.CREATOR.createFromParcel(paramParcel1);
          bool = dial(localBluetoothDevice, paramParcel1.readString());
          paramParcel2.writeNoException();
          if (!bool) {
            break label1481;
          }
        }
        for (paramInt1 = 1;; paramInt1 = 0)
        {
          paramParcel2.writeInt(paramInt1);
          return true;
          localBluetoothDevice = null;
          break;
        }
      case 22: 
        paramParcel1.enforceInterface("android.bluetooth.IBluetoothHeadsetClient");
        if (paramParcel1.readInt() != 0)
        {
          localBluetoothDevice = (BluetoothDevice)BluetoothDevice.CREATOR.createFromParcel(paramParcel1);
          bool = dialMemory(localBluetoothDevice, paramParcel1.readInt());
          paramParcel2.writeNoException();
          if (!bool) {
            break label1549;
          }
        }
        for (paramInt1 = 1;; paramInt1 = 0)
        {
          paramParcel2.writeInt(paramInt1);
          return true;
          localBluetoothDevice = null;
          break;
        }
      case 23: 
        paramParcel1.enforceInterface("android.bluetooth.IBluetoothHeadsetClient");
        if (paramParcel1.readInt() != 0)
        {
          localBluetoothDevice = (BluetoothDevice)BluetoothDevice.CREATOR.createFromParcel(paramParcel1);
          bool = sendDTMF(localBluetoothDevice, paramParcel1.readByte());
          paramParcel2.writeNoException();
          if (!bool) {
            break label1617;
          }
        }
        for (paramInt1 = 1;; paramInt1 = 0)
        {
          paramParcel2.writeInt(paramInt1);
          return true;
          localBluetoothDevice = null;
          break;
        }
      case 24: 
        paramParcel1.enforceInterface("android.bluetooth.IBluetoothHeadsetClient");
        if (paramParcel1.readInt() != 0)
        {
          paramParcel1 = (BluetoothDevice)BluetoothDevice.CREATOR.createFromParcel(paramParcel1);
          bool = getLastVoiceTagNumber(paramParcel1);
          paramParcel2.writeNoException();
          if (!bool) {
            break label1678;
          }
        }
        for (paramInt1 = 1;; paramInt1 = 0)
        {
          paramParcel2.writeInt(paramInt1);
          return true;
          paramParcel1 = null;
          break;
        }
      case 25: 
        paramParcel1.enforceInterface("android.bluetooth.IBluetoothHeadsetClient");
        if (paramParcel1.readInt() != 0) {}
        for (paramParcel1 = (BluetoothDevice)BluetoothDevice.CREATOR.createFromParcel(paramParcel1);; paramParcel1 = null)
        {
          paramInt1 = getAudioState(paramParcel1);
          paramParcel2.writeNoException();
          paramParcel2.writeInt(paramInt1);
          return true;
        }
      case 26: 
        paramParcel1.enforceInterface("android.bluetooth.IBluetoothHeadsetClient");
        bool = connectAudio();
        paramParcel2.writeNoException();
        if (bool) {}
        for (paramInt1 = 1;; paramInt1 = 0)
        {
          paramParcel2.writeInt(paramInt1);
          return true;
        }
      case 27: 
        paramParcel1.enforceInterface("android.bluetooth.IBluetoothHeadsetClient");
        bool = disconnectAudio();
        paramParcel2.writeNoException();
        if (bool) {}
        for (paramInt1 = 1;; paramInt1 = 0)
        {
          paramParcel2.writeInt(paramInt1);
          return true;
        }
      case 28: 
        paramParcel1.enforceInterface("android.bluetooth.IBluetoothHeadsetClient");
        if (paramParcel1.readInt() != 0) {}
        for (bool = true;; bool = false)
        {
          setAudioRouteAllowed(bool);
          paramParcel2.writeNoException();
          return true;
        }
      case 29: 
        label681:
        label790:
        label851:
        label962:
        label1033:
        label1094:
        label1155:
        label1223:
        label1291:
        label1352:
        label1413:
        label1481:
        label1549:
        label1617:
        label1678:
        paramParcel1.enforceInterface("android.bluetooth.IBluetoothHeadsetClient");
        bool = getAudioRouteAllowed();
        paramParcel2.writeNoException();
        if (bool) {}
        for (paramInt1 = 1;; paramInt1 = 0)
        {
          paramParcel2.writeInt(paramInt1);
          return true;
        }
      }
      paramParcel1.enforceInterface("android.bluetooth.IBluetoothHeadsetClient");
      if (paramParcel1.readInt() != 0)
      {
        paramParcel1 = (BluetoothDevice)BluetoothDevice.CREATOR.createFromParcel(paramParcel1);
        paramParcel1 = getCurrentAgFeatures(paramParcel1);
        paramParcel2.writeNoException();
        if (paramParcel1 == null) {
          break label1928;
        }
        paramParcel2.writeInt(1);
        paramParcel1.writeToParcel(paramParcel2, 1);
      }
      for (;;)
      {
        return true;
        paramParcel1 = null;
        break;
        label1928:
        paramParcel2.writeInt(0);
      }
    }
    
    private static class Proxy
      implements IBluetoothHeadsetClient
    {
      private IBinder mRemote;
      
      Proxy(IBinder paramIBinder)
      {
        this.mRemote = paramIBinder;
      }
      
      public boolean acceptCall(BluetoothDevice paramBluetoothDevice, int paramInt)
        throws RemoteException
      {
        Parcel localParcel1 = Parcel.obtain();
        Parcel localParcel2 = Parcel.obtain();
        for (;;)
        {
          try
          {
            localParcel1.writeInterfaceToken("android.bluetooth.IBluetoothHeadsetClient");
            if (paramBluetoothDevice != null)
            {
              localParcel1.writeInt(1);
              paramBluetoothDevice.writeToParcel(localParcel1, 0);
              localParcel1.writeInt(paramInt);
              this.mRemote.transact(14, localParcel1, localParcel2, 0);
              localParcel2.readException();
              paramInt = localParcel2.readInt();
              if (paramInt != 0)
              {
                bool = true;
                return bool;
              }
            }
            else
            {
              localParcel1.writeInt(0);
              continue;
            }
            boolean bool = false;
          }
          finally
          {
            localParcel2.recycle();
            localParcel1.recycle();
          }
        }
      }
      
      public boolean acceptIncomingConnect(BluetoothDevice paramBluetoothDevice)
        throws RemoteException
      {
        Parcel localParcel1 = Parcel.obtain();
        Parcel localParcel2 = Parcel.obtain();
        for (;;)
        {
          try
          {
            localParcel1.writeInterfaceToken("android.bluetooth.IBluetoothHeadsetClient");
            if (paramBluetoothDevice != null)
            {
              localParcel1.writeInt(1);
              paramBluetoothDevice.writeToParcel(localParcel1, 0);
              this.mRemote.transact(3, localParcel1, localParcel2, 0);
              localParcel2.readException();
              int i = localParcel2.readInt();
              if (i != 0)
              {
                bool = true;
                return bool;
              }
            }
            else
            {
              localParcel1.writeInt(0);
              continue;
            }
            boolean bool = false;
          }
          finally
          {
            localParcel2.recycle();
            localParcel1.recycle();
          }
        }
      }
      
      public IBinder asBinder()
      {
        return this.mRemote;
      }
      
      public boolean connect(BluetoothDevice paramBluetoothDevice)
        throws RemoteException
      {
        Parcel localParcel1 = Parcel.obtain();
        Parcel localParcel2 = Parcel.obtain();
        for (;;)
        {
          try
          {
            localParcel1.writeInterfaceToken("android.bluetooth.IBluetoothHeadsetClient");
            if (paramBluetoothDevice != null)
            {
              localParcel1.writeInt(1);
              paramBluetoothDevice.writeToParcel(localParcel1, 0);
              this.mRemote.transact(1, localParcel1, localParcel2, 0);
              localParcel2.readException();
              int i = localParcel2.readInt();
              if (i != 0)
              {
                bool = true;
                return bool;
              }
            }
            else
            {
              localParcel1.writeInt(0);
              continue;
            }
            boolean bool = false;
          }
          finally
          {
            localParcel2.recycle();
            localParcel1.recycle();
          }
        }
      }
      
      /* Error */
      public boolean connectAudio()
        throws RemoteException
      {
        // Byte code:
        //   0: invokestatic 30	android/os/Parcel:obtain	()Landroid/os/Parcel;
        //   3: astore_3
        //   4: invokestatic 30	android/os/Parcel:obtain	()Landroid/os/Parcel;
        //   7: astore 4
        //   9: aload_3
        //   10: ldc 32
        //   12: invokevirtual 36	android/os/Parcel:writeInterfaceToken	(Ljava/lang/String;)V
        //   15: aload_0
        //   16: getfield 19	android/bluetooth/IBluetoothHeadsetClient$Stub$Proxy:mRemote	Landroid/os/IBinder;
        //   19: bipush 26
        //   21: aload_3
        //   22: aload 4
        //   24: iconst_0
        //   25: invokeinterface 52 5 0
        //   30: pop
        //   31: aload 4
        //   33: invokevirtual 55	android/os/Parcel:readException	()V
        //   36: aload 4
        //   38: invokevirtual 59	android/os/Parcel:readInt	()I
        //   41: istore_1
        //   42: iload_1
        //   43: ifeq +16 -> 59
        //   46: iconst_1
        //   47: istore_2
        //   48: aload 4
        //   50: invokevirtual 62	android/os/Parcel:recycle	()V
        //   53: aload_3
        //   54: invokevirtual 62	android/os/Parcel:recycle	()V
        //   57: iload_2
        //   58: ireturn
        //   59: iconst_0
        //   60: istore_2
        //   61: goto -13 -> 48
        //   64: astore 5
        //   66: aload 4
        //   68: invokevirtual 62	android/os/Parcel:recycle	()V
        //   71: aload_3
        //   72: invokevirtual 62	android/os/Parcel:recycle	()V
        //   75: aload 5
        //   77: athrow
        // Local variable table:
        //   start	length	slot	name	signature
        //   0	78	0	this	Proxy
        //   41	2	1	i	int
        //   47	14	2	bool	boolean
        //   3	69	3	localParcel1	Parcel
        //   7	60	4	localParcel2	Parcel
        //   64	12	5	localObject	Object
        // Exception table:
        //   from	to	target	type
        //   9	42	64	finally
      }
      
      public boolean dial(BluetoothDevice paramBluetoothDevice, String paramString)
        throws RemoteException
      {
        Parcel localParcel1 = Parcel.obtain();
        Parcel localParcel2 = Parcel.obtain();
        for (;;)
        {
          try
          {
            localParcel1.writeInterfaceToken("android.bluetooth.IBluetoothHeadsetClient");
            if (paramBluetoothDevice != null)
            {
              localParcel1.writeInt(1);
              paramBluetoothDevice.writeToParcel(localParcel1, 0);
              localParcel1.writeString(paramString);
              this.mRemote.transact(21, localParcel1, localParcel2, 0);
              localParcel2.readException();
              int i = localParcel2.readInt();
              if (i != 0)
              {
                bool = true;
                return bool;
              }
            }
            else
            {
              localParcel1.writeInt(0);
              continue;
            }
            boolean bool = false;
          }
          finally
          {
            localParcel2.recycle();
            localParcel1.recycle();
          }
        }
      }
      
      public boolean dialMemory(BluetoothDevice paramBluetoothDevice, int paramInt)
        throws RemoteException
      {
        Parcel localParcel1 = Parcel.obtain();
        Parcel localParcel2 = Parcel.obtain();
        for (;;)
        {
          try
          {
            localParcel1.writeInterfaceToken("android.bluetooth.IBluetoothHeadsetClient");
            if (paramBluetoothDevice != null)
            {
              localParcel1.writeInt(1);
              paramBluetoothDevice.writeToParcel(localParcel1, 0);
              localParcel1.writeInt(paramInt);
              this.mRemote.transact(22, localParcel1, localParcel2, 0);
              localParcel2.readException();
              paramInt = localParcel2.readInt();
              if (paramInt != 0)
              {
                bool = true;
                return bool;
              }
            }
            else
            {
              localParcel1.writeInt(0);
              continue;
            }
            boolean bool = false;
          }
          finally
          {
            localParcel2.recycle();
            localParcel1.recycle();
          }
        }
      }
      
      public boolean disconnect(BluetoothDevice paramBluetoothDevice)
        throws RemoteException
      {
        Parcel localParcel1 = Parcel.obtain();
        Parcel localParcel2 = Parcel.obtain();
        for (;;)
        {
          try
          {
            localParcel1.writeInterfaceToken("android.bluetooth.IBluetoothHeadsetClient");
            if (paramBluetoothDevice != null)
            {
              localParcel1.writeInt(1);
              paramBluetoothDevice.writeToParcel(localParcel1, 0);
              this.mRemote.transact(2, localParcel1, localParcel2, 0);
              localParcel2.readException();
              int i = localParcel2.readInt();
              if (i != 0)
              {
                bool = true;
                return bool;
              }
            }
            else
            {
              localParcel1.writeInt(0);
              continue;
            }
            boolean bool = false;
          }
          finally
          {
            localParcel2.recycle();
            localParcel1.recycle();
          }
        }
      }
      
      /* Error */
      public boolean disconnectAudio()
        throws RemoteException
      {
        // Byte code:
        //   0: invokestatic 30	android/os/Parcel:obtain	()Landroid/os/Parcel;
        //   3: astore_3
        //   4: invokestatic 30	android/os/Parcel:obtain	()Landroid/os/Parcel;
        //   7: astore 4
        //   9: aload_3
        //   10: ldc 32
        //   12: invokevirtual 36	android/os/Parcel:writeInterfaceToken	(Ljava/lang/String;)V
        //   15: aload_0
        //   16: getfield 19	android/bluetooth/IBluetoothHeadsetClient$Stub$Proxy:mRemote	Landroid/os/IBinder;
        //   19: bipush 27
        //   21: aload_3
        //   22: aload 4
        //   24: iconst_0
        //   25: invokeinterface 52 5 0
        //   30: pop
        //   31: aload 4
        //   33: invokevirtual 55	android/os/Parcel:readException	()V
        //   36: aload 4
        //   38: invokevirtual 59	android/os/Parcel:readInt	()I
        //   41: istore_1
        //   42: iload_1
        //   43: ifeq +16 -> 59
        //   46: iconst_1
        //   47: istore_2
        //   48: aload 4
        //   50: invokevirtual 62	android/os/Parcel:recycle	()V
        //   53: aload_3
        //   54: invokevirtual 62	android/os/Parcel:recycle	()V
        //   57: iload_2
        //   58: ireturn
        //   59: iconst_0
        //   60: istore_2
        //   61: goto -13 -> 48
        //   64: astore 5
        //   66: aload 4
        //   68: invokevirtual 62	android/os/Parcel:recycle	()V
        //   71: aload_3
        //   72: invokevirtual 62	android/os/Parcel:recycle	()V
        //   75: aload 5
        //   77: athrow
        // Local variable table:
        //   start	length	slot	name	signature
        //   0	78	0	this	Proxy
        //   41	2	1	i	int
        //   47	14	2	bool	boolean
        //   3	69	3	localParcel1	Parcel
        //   7	60	4	localParcel2	Parcel
        //   64	12	5	localObject	Object
        // Exception table:
        //   from	to	target	type
        //   9	42	64	finally
      }
      
      public boolean enterPrivateMode(BluetoothDevice paramBluetoothDevice, int paramInt)
        throws RemoteException
      {
        Parcel localParcel1 = Parcel.obtain();
        Parcel localParcel2 = Parcel.obtain();
        for (;;)
        {
          try
          {
            localParcel1.writeInterfaceToken("android.bluetooth.IBluetoothHeadsetClient");
            if (paramBluetoothDevice != null)
            {
              localParcel1.writeInt(1);
              paramBluetoothDevice.writeToParcel(localParcel1, 0);
              localParcel1.writeInt(paramInt);
              this.mRemote.transact(18, localParcel1, localParcel2, 0);
              localParcel2.readException();
              paramInt = localParcel2.readInt();
              if (paramInt != 0)
              {
                bool = true;
                return bool;
              }
            }
            else
            {
              localParcel1.writeInt(0);
              continue;
            }
            boolean bool = false;
          }
          finally
          {
            localParcel2.recycle();
            localParcel1.recycle();
          }
        }
      }
      
      public boolean explicitCallTransfer(BluetoothDevice paramBluetoothDevice)
        throws RemoteException
      {
        Parcel localParcel1 = Parcel.obtain();
        Parcel localParcel2 = Parcel.obtain();
        for (;;)
        {
          try
          {
            localParcel1.writeInterfaceToken("android.bluetooth.IBluetoothHeadsetClient");
            if (paramBluetoothDevice != null)
            {
              localParcel1.writeInt(1);
              paramBluetoothDevice.writeToParcel(localParcel1, 0);
              this.mRemote.transact(19, localParcel1, localParcel2, 0);
              localParcel2.readException();
              int i = localParcel2.readInt();
              if (i != 0)
              {
                bool = true;
                return bool;
              }
            }
            else
            {
              localParcel1.writeInt(0);
              continue;
            }
            boolean bool = false;
          }
          finally
          {
            localParcel2.recycle();
            localParcel1.recycle();
          }
        }
      }
      
      /* Error */
      public boolean getAudioRouteAllowed()
        throws RemoteException
      {
        // Byte code:
        //   0: invokestatic 30	android/os/Parcel:obtain	()Landroid/os/Parcel;
        //   3: astore_3
        //   4: invokestatic 30	android/os/Parcel:obtain	()Landroid/os/Parcel;
        //   7: astore 4
        //   9: aload_3
        //   10: ldc 32
        //   12: invokevirtual 36	android/os/Parcel:writeInterfaceToken	(Ljava/lang/String;)V
        //   15: aload_0
        //   16: getfield 19	android/bluetooth/IBluetoothHeadsetClient$Stub$Proxy:mRemote	Landroid/os/IBinder;
        //   19: bipush 29
        //   21: aload_3
        //   22: aload 4
        //   24: iconst_0
        //   25: invokeinterface 52 5 0
        //   30: pop
        //   31: aload 4
        //   33: invokevirtual 55	android/os/Parcel:readException	()V
        //   36: aload 4
        //   38: invokevirtual 59	android/os/Parcel:readInt	()I
        //   41: istore_1
        //   42: iload_1
        //   43: ifeq +16 -> 59
        //   46: iconst_1
        //   47: istore_2
        //   48: aload 4
        //   50: invokevirtual 62	android/os/Parcel:recycle	()V
        //   53: aload_3
        //   54: invokevirtual 62	android/os/Parcel:recycle	()V
        //   57: iload_2
        //   58: ireturn
        //   59: iconst_0
        //   60: istore_2
        //   61: goto -13 -> 48
        //   64: astore 5
        //   66: aload 4
        //   68: invokevirtual 62	android/os/Parcel:recycle	()V
        //   71: aload_3
        //   72: invokevirtual 62	android/os/Parcel:recycle	()V
        //   75: aload 5
        //   77: athrow
        // Local variable table:
        //   start	length	slot	name	signature
        //   0	78	0	this	Proxy
        //   41	2	1	i	int
        //   47	14	2	bool	boolean
        //   3	69	3	localParcel1	Parcel
        //   7	60	4	localParcel2	Parcel
        //   64	12	5	localObject	Object
        // Exception table:
        //   from	to	target	type
        //   9	42	64	finally
      }
      
      /* Error */
      public int getAudioState(BluetoothDevice paramBluetoothDevice)
        throws RemoteException
      {
        // Byte code:
        //   0: invokestatic 30	android/os/Parcel:obtain	()Landroid/os/Parcel;
        //   3: astore_3
        //   4: invokestatic 30	android/os/Parcel:obtain	()Landroid/os/Parcel;
        //   7: astore 4
        //   9: aload_3
        //   10: ldc 32
        //   12: invokevirtual 36	android/os/Parcel:writeInterfaceToken	(Ljava/lang/String;)V
        //   15: aload_1
        //   16: ifnull +52 -> 68
        //   19: aload_3
        //   20: iconst_1
        //   21: invokevirtual 40	android/os/Parcel:writeInt	(I)V
        //   24: aload_1
        //   25: aload_3
        //   26: iconst_0
        //   27: invokevirtual 46	android/bluetooth/BluetoothDevice:writeToParcel	(Landroid/os/Parcel;I)V
        //   30: aload_0
        //   31: getfield 19	android/bluetooth/IBluetoothHeadsetClient$Stub$Proxy:mRemote	Landroid/os/IBinder;
        //   34: bipush 25
        //   36: aload_3
        //   37: aload 4
        //   39: iconst_0
        //   40: invokeinterface 52 5 0
        //   45: pop
        //   46: aload 4
        //   48: invokevirtual 55	android/os/Parcel:readException	()V
        //   51: aload 4
        //   53: invokevirtual 59	android/os/Parcel:readInt	()I
        //   56: istore_2
        //   57: aload 4
        //   59: invokevirtual 62	android/os/Parcel:recycle	()V
        //   62: aload_3
        //   63: invokevirtual 62	android/os/Parcel:recycle	()V
        //   66: iload_2
        //   67: ireturn
        //   68: aload_3
        //   69: iconst_0
        //   70: invokevirtual 40	android/os/Parcel:writeInt	(I)V
        //   73: goto -43 -> 30
        //   76: astore_1
        //   77: aload 4
        //   79: invokevirtual 62	android/os/Parcel:recycle	()V
        //   82: aload_3
        //   83: invokevirtual 62	android/os/Parcel:recycle	()V
        //   86: aload_1
        //   87: athrow
        // Local variable table:
        //   start	length	slot	name	signature
        //   0	88	0	this	Proxy
        //   0	88	1	paramBluetoothDevice	BluetoothDevice
        //   56	11	2	i	int
        //   3	80	3	localParcel1	Parcel
        //   7	71	4	localParcel2	Parcel
        // Exception table:
        //   from	to	target	type
        //   9	15	76	finally
        //   19	30	76	finally
        //   30	57	76	finally
        //   68	73	76	finally
      }
      
      public List<BluetoothDevice> getConnectedDevices()
        throws RemoteException
      {
        Parcel localParcel1 = Parcel.obtain();
        Parcel localParcel2 = Parcel.obtain();
        try
        {
          localParcel1.writeInterfaceToken("android.bluetooth.IBluetoothHeadsetClient");
          this.mRemote.transact(5, localParcel1, localParcel2, 0);
          localParcel2.readException();
          ArrayList localArrayList = localParcel2.createTypedArrayList(BluetoothDevice.CREATOR);
          return localArrayList;
        }
        finally
        {
          localParcel2.recycle();
          localParcel1.recycle();
        }
      }
      
      /* Error */
      public int getConnectionState(BluetoothDevice paramBluetoothDevice)
        throws RemoteException
      {
        // Byte code:
        //   0: invokestatic 30	android/os/Parcel:obtain	()Landroid/os/Parcel;
        //   3: astore_3
        //   4: invokestatic 30	android/os/Parcel:obtain	()Landroid/os/Parcel;
        //   7: astore 4
        //   9: aload_3
        //   10: ldc 32
        //   12: invokevirtual 36	android/os/Parcel:writeInterfaceToken	(Ljava/lang/String;)V
        //   15: aload_1
        //   16: ifnull +52 -> 68
        //   19: aload_3
        //   20: iconst_1
        //   21: invokevirtual 40	android/os/Parcel:writeInt	(I)V
        //   24: aload_1
        //   25: aload_3
        //   26: iconst_0
        //   27: invokevirtual 46	android/bluetooth/BluetoothDevice:writeToParcel	(Landroid/os/Parcel;I)V
        //   30: aload_0
        //   31: getfield 19	android/bluetooth/IBluetoothHeadsetClient$Stub$Proxy:mRemote	Landroid/os/IBinder;
        //   34: bipush 7
        //   36: aload_3
        //   37: aload 4
        //   39: iconst_0
        //   40: invokeinterface 52 5 0
        //   45: pop
        //   46: aload 4
        //   48: invokevirtual 55	android/os/Parcel:readException	()V
        //   51: aload 4
        //   53: invokevirtual 59	android/os/Parcel:readInt	()I
        //   56: istore_2
        //   57: aload 4
        //   59: invokevirtual 62	android/os/Parcel:recycle	()V
        //   62: aload_3
        //   63: invokevirtual 62	android/os/Parcel:recycle	()V
        //   66: iload_2
        //   67: ireturn
        //   68: aload_3
        //   69: iconst_0
        //   70: invokevirtual 40	android/os/Parcel:writeInt	(I)V
        //   73: goto -43 -> 30
        //   76: astore_1
        //   77: aload 4
        //   79: invokevirtual 62	android/os/Parcel:recycle	()V
        //   82: aload_3
        //   83: invokevirtual 62	android/os/Parcel:recycle	()V
        //   86: aload_1
        //   87: athrow
        // Local variable table:
        //   start	length	slot	name	signature
        //   0	88	0	this	Proxy
        //   0	88	1	paramBluetoothDevice	BluetoothDevice
        //   56	11	2	i	int
        //   3	80	3	localParcel1	Parcel
        //   7	71	4	localParcel2	Parcel
        // Exception table:
        //   from	to	target	type
        //   9	15	76	finally
        //   19	30	76	finally
        //   30	57	76	finally
        //   68	73	76	finally
      }
      
      public Bundle getCurrentAgEvents(BluetoothDevice paramBluetoothDevice)
        throws RemoteException
      {
        Parcel localParcel1 = Parcel.obtain();
        Parcel localParcel2 = Parcel.obtain();
        for (;;)
        {
          try
          {
            localParcel1.writeInterfaceToken("android.bluetooth.IBluetoothHeadsetClient");
            if (paramBluetoothDevice != null)
            {
              localParcel1.writeInt(1);
              paramBluetoothDevice.writeToParcel(localParcel1, 0);
              this.mRemote.transact(13, localParcel1, localParcel2, 0);
              localParcel2.readException();
              if (localParcel2.readInt() != 0)
              {
                paramBluetoothDevice = (Bundle)Bundle.CREATOR.createFromParcel(localParcel2);
                return paramBluetoothDevice;
              }
            }
            else
            {
              localParcel1.writeInt(0);
              continue;
            }
            paramBluetoothDevice = null;
          }
          finally
          {
            localParcel2.recycle();
            localParcel1.recycle();
          }
        }
      }
      
      public Bundle getCurrentAgFeatures(BluetoothDevice paramBluetoothDevice)
        throws RemoteException
      {
        Parcel localParcel1 = Parcel.obtain();
        Parcel localParcel2 = Parcel.obtain();
        for (;;)
        {
          try
          {
            localParcel1.writeInterfaceToken("android.bluetooth.IBluetoothHeadsetClient");
            if (paramBluetoothDevice != null)
            {
              localParcel1.writeInt(1);
              paramBluetoothDevice.writeToParcel(localParcel1, 0);
              this.mRemote.transact(30, localParcel1, localParcel2, 0);
              localParcel2.readException();
              if (localParcel2.readInt() != 0)
              {
                paramBluetoothDevice = (Bundle)Bundle.CREATOR.createFromParcel(localParcel2);
                return paramBluetoothDevice;
              }
            }
            else
            {
              localParcel1.writeInt(0);
              continue;
            }
            paramBluetoothDevice = null;
          }
          finally
          {
            localParcel2.recycle();
            localParcel1.recycle();
          }
        }
      }
      
      /* Error */
      public List<BluetoothHeadsetClientCall> getCurrentCalls(BluetoothDevice paramBluetoothDevice)
        throws RemoteException
      {
        // Byte code:
        //   0: invokestatic 30	android/os/Parcel:obtain	()Landroid/os/Parcel;
        //   3: astore_2
        //   4: invokestatic 30	android/os/Parcel:obtain	()Landroid/os/Parcel;
        //   7: astore_3
        //   8: aload_2
        //   9: ldc 32
        //   11: invokevirtual 36	android/os/Parcel:writeInterfaceToken	(Ljava/lang/String;)V
        //   14: aload_1
        //   15: ifnull +51 -> 66
        //   18: aload_2
        //   19: iconst_1
        //   20: invokevirtual 40	android/os/Parcel:writeInt	(I)V
        //   23: aload_1
        //   24: aload_2
        //   25: iconst_0
        //   26: invokevirtual 46	android/bluetooth/BluetoothDevice:writeToParcel	(Landroid/os/Parcel;I)V
        //   29: aload_0
        //   30: getfield 19	android/bluetooth/IBluetoothHeadsetClient$Stub$Proxy:mRemote	Landroid/os/IBinder;
        //   33: bipush 12
        //   35: aload_2
        //   36: aload_3
        //   37: iconst_0
        //   38: invokeinterface 52 5 0
        //   43: pop
        //   44: aload_3
        //   45: invokevirtual 55	android/os/Parcel:readException	()V
        //   48: aload_3
        //   49: getstatic 113	android/bluetooth/BluetoothHeadsetClientCall:CREATOR	Landroid/os/Parcelable$Creator;
        //   52: invokevirtual 93	android/os/Parcel:createTypedArrayList	(Landroid/os/Parcelable$Creator;)Ljava/util/ArrayList;
        //   55: astore_1
        //   56: aload_3
        //   57: invokevirtual 62	android/os/Parcel:recycle	()V
        //   60: aload_2
        //   61: invokevirtual 62	android/os/Parcel:recycle	()V
        //   64: aload_1
        //   65: areturn
        //   66: aload_2
        //   67: iconst_0
        //   68: invokevirtual 40	android/os/Parcel:writeInt	(I)V
        //   71: goto -42 -> 29
        //   74: astore_1
        //   75: aload_3
        //   76: invokevirtual 62	android/os/Parcel:recycle	()V
        //   79: aload_2
        //   80: invokevirtual 62	android/os/Parcel:recycle	()V
        //   83: aload_1
        //   84: athrow
        // Local variable table:
        //   start	length	slot	name	signature
        //   0	85	0	this	Proxy
        //   0	85	1	paramBluetoothDevice	BluetoothDevice
        //   3	77	2	localParcel1	Parcel
        //   7	69	3	localParcel2	Parcel
        // Exception table:
        //   from	to	target	type
        //   8	14	74	finally
        //   18	29	74	finally
        //   29	56	74	finally
        //   66	71	74	finally
      }
      
      public List<BluetoothDevice> getDevicesMatchingConnectionStates(int[] paramArrayOfInt)
        throws RemoteException
      {
        Parcel localParcel1 = Parcel.obtain();
        Parcel localParcel2 = Parcel.obtain();
        try
        {
          localParcel1.writeInterfaceToken("android.bluetooth.IBluetoothHeadsetClient");
          localParcel1.writeIntArray(paramArrayOfInt);
          this.mRemote.transact(6, localParcel1, localParcel2, 0);
          localParcel2.readException();
          paramArrayOfInt = localParcel2.createTypedArrayList(BluetoothDevice.CREATOR);
          return paramArrayOfInt;
        }
        finally
        {
          localParcel2.recycle();
          localParcel1.recycle();
        }
      }
      
      public String getInterfaceDescriptor()
      {
        return "android.bluetooth.IBluetoothHeadsetClient";
      }
      
      public boolean getLastVoiceTagNumber(BluetoothDevice paramBluetoothDevice)
        throws RemoteException
      {
        Parcel localParcel1 = Parcel.obtain();
        Parcel localParcel2 = Parcel.obtain();
        for (;;)
        {
          try
          {
            localParcel1.writeInterfaceToken("android.bluetooth.IBluetoothHeadsetClient");
            if (paramBluetoothDevice != null)
            {
              localParcel1.writeInt(1);
              paramBluetoothDevice.writeToParcel(localParcel1, 0);
              this.mRemote.transact(24, localParcel1, localParcel2, 0);
              localParcel2.readException();
              int i = localParcel2.readInt();
              if (i != 0)
              {
                bool = true;
                return bool;
              }
            }
            else
            {
              localParcel1.writeInt(0);
              continue;
            }
            boolean bool = false;
          }
          finally
          {
            localParcel2.recycle();
            localParcel1.recycle();
          }
        }
      }
      
      /* Error */
      public int getPriority(BluetoothDevice paramBluetoothDevice)
        throws RemoteException
      {
        // Byte code:
        //   0: invokestatic 30	android/os/Parcel:obtain	()Landroid/os/Parcel;
        //   3: astore_3
        //   4: invokestatic 30	android/os/Parcel:obtain	()Landroid/os/Parcel;
        //   7: astore 4
        //   9: aload_3
        //   10: ldc 32
        //   12: invokevirtual 36	android/os/Parcel:writeInterfaceToken	(Ljava/lang/String;)V
        //   15: aload_1
        //   16: ifnull +52 -> 68
        //   19: aload_3
        //   20: iconst_1
        //   21: invokevirtual 40	android/os/Parcel:writeInt	(I)V
        //   24: aload_1
        //   25: aload_3
        //   26: iconst_0
        //   27: invokevirtual 46	android/bluetooth/BluetoothDevice:writeToParcel	(Landroid/os/Parcel;I)V
        //   30: aload_0
        //   31: getfield 19	android/bluetooth/IBluetoothHeadsetClient$Stub$Proxy:mRemote	Landroid/os/IBinder;
        //   34: bipush 9
        //   36: aload_3
        //   37: aload 4
        //   39: iconst_0
        //   40: invokeinterface 52 5 0
        //   45: pop
        //   46: aload 4
        //   48: invokevirtual 55	android/os/Parcel:readException	()V
        //   51: aload 4
        //   53: invokevirtual 59	android/os/Parcel:readInt	()I
        //   56: istore_2
        //   57: aload 4
        //   59: invokevirtual 62	android/os/Parcel:recycle	()V
        //   62: aload_3
        //   63: invokevirtual 62	android/os/Parcel:recycle	()V
        //   66: iload_2
        //   67: ireturn
        //   68: aload_3
        //   69: iconst_0
        //   70: invokevirtual 40	android/os/Parcel:writeInt	(I)V
        //   73: goto -43 -> 30
        //   76: astore_1
        //   77: aload 4
        //   79: invokevirtual 62	android/os/Parcel:recycle	()V
        //   82: aload_3
        //   83: invokevirtual 62	android/os/Parcel:recycle	()V
        //   86: aload_1
        //   87: athrow
        // Local variable table:
        //   start	length	slot	name	signature
        //   0	88	0	this	Proxy
        //   0	88	1	paramBluetoothDevice	BluetoothDevice
        //   56	11	2	i	int
        //   3	80	3	localParcel1	Parcel
        //   7	71	4	localParcel2	Parcel
        // Exception table:
        //   from	to	target	type
        //   9	15	76	finally
        //   19	30	76	finally
        //   30	57	76	finally
        //   68	73	76	finally
      }
      
      public boolean holdCall(BluetoothDevice paramBluetoothDevice)
        throws RemoteException
      {
        Parcel localParcel1 = Parcel.obtain();
        Parcel localParcel2 = Parcel.obtain();
        for (;;)
        {
          try
          {
            localParcel1.writeInterfaceToken("android.bluetooth.IBluetoothHeadsetClient");
            if (paramBluetoothDevice != null)
            {
              localParcel1.writeInt(1);
              paramBluetoothDevice.writeToParcel(localParcel1, 0);
              this.mRemote.transact(15, localParcel1, localParcel2, 0);
              localParcel2.readException();
              int i = localParcel2.readInt();
              if (i != 0)
              {
                bool = true;
                return bool;
              }
            }
            else
            {
              localParcel1.writeInt(0);
              continue;
            }
            boolean bool = false;
          }
          finally
          {
            localParcel2.recycle();
            localParcel1.recycle();
          }
        }
      }
      
      public boolean redial(BluetoothDevice paramBluetoothDevice)
        throws RemoteException
      {
        Parcel localParcel1 = Parcel.obtain();
        Parcel localParcel2 = Parcel.obtain();
        for (;;)
        {
          try
          {
            localParcel1.writeInterfaceToken("android.bluetooth.IBluetoothHeadsetClient");
            if (paramBluetoothDevice != null)
            {
              localParcel1.writeInt(1);
              paramBluetoothDevice.writeToParcel(localParcel1, 0);
              this.mRemote.transact(20, localParcel1, localParcel2, 0);
              localParcel2.readException();
              int i = localParcel2.readInt();
              if (i != 0)
              {
                bool = true;
                return bool;
              }
            }
            else
            {
              localParcel1.writeInt(0);
              continue;
            }
            boolean bool = false;
          }
          finally
          {
            localParcel2.recycle();
            localParcel1.recycle();
          }
        }
      }
      
      public boolean rejectCall(BluetoothDevice paramBluetoothDevice)
        throws RemoteException
      {
        Parcel localParcel1 = Parcel.obtain();
        Parcel localParcel2 = Parcel.obtain();
        for (;;)
        {
          try
          {
            localParcel1.writeInterfaceToken("android.bluetooth.IBluetoothHeadsetClient");
            if (paramBluetoothDevice != null)
            {
              localParcel1.writeInt(1);
              paramBluetoothDevice.writeToParcel(localParcel1, 0);
              this.mRemote.transact(16, localParcel1, localParcel2, 0);
              localParcel2.readException();
              int i = localParcel2.readInt();
              if (i != 0)
              {
                bool = true;
                return bool;
              }
            }
            else
            {
              localParcel1.writeInt(0);
              continue;
            }
            boolean bool = false;
          }
          finally
          {
            localParcel2.recycle();
            localParcel1.recycle();
          }
        }
      }
      
      public boolean rejectIncomingConnect(BluetoothDevice paramBluetoothDevice)
        throws RemoteException
      {
        Parcel localParcel1 = Parcel.obtain();
        Parcel localParcel2 = Parcel.obtain();
        for (;;)
        {
          try
          {
            localParcel1.writeInterfaceToken("android.bluetooth.IBluetoothHeadsetClient");
            if (paramBluetoothDevice != null)
            {
              localParcel1.writeInt(1);
              paramBluetoothDevice.writeToParcel(localParcel1, 0);
              this.mRemote.transact(4, localParcel1, localParcel2, 0);
              localParcel2.readException();
              int i = localParcel2.readInt();
              if (i != 0)
              {
                bool = true;
                return bool;
              }
            }
            else
            {
              localParcel1.writeInt(0);
              continue;
            }
            boolean bool = false;
          }
          finally
          {
            localParcel2.recycle();
            localParcel1.recycle();
          }
        }
      }
      
      public boolean sendDTMF(BluetoothDevice paramBluetoothDevice, byte paramByte)
        throws RemoteException
      {
        Parcel localParcel1 = Parcel.obtain();
        Parcel localParcel2 = Parcel.obtain();
        for (;;)
        {
          try
          {
            localParcel1.writeInterfaceToken("android.bluetooth.IBluetoothHeadsetClient");
            if (paramBluetoothDevice != null)
            {
              localParcel1.writeInt(1);
              paramBluetoothDevice.writeToParcel(localParcel1, 0);
              localParcel1.writeByte(paramByte);
              this.mRemote.transact(23, localParcel1, localParcel2, 0);
              localParcel2.readException();
              int i = localParcel2.readInt();
              if (i != 0)
              {
                bool = true;
                return bool;
              }
            }
            else
            {
              localParcel1.writeInt(0);
              continue;
            }
            boolean bool = false;
          }
          finally
          {
            localParcel2.recycle();
            localParcel1.recycle();
          }
        }
      }
      
      public void setAudioRouteAllowed(boolean paramBoolean)
        throws RemoteException
      {
        int i = 0;
        Parcel localParcel1 = Parcel.obtain();
        Parcel localParcel2 = Parcel.obtain();
        try
        {
          localParcel1.writeInterfaceToken("android.bluetooth.IBluetoothHeadsetClient");
          if (paramBoolean) {
            i = 1;
          }
          localParcel1.writeInt(i);
          this.mRemote.transact(28, localParcel1, localParcel2, 0);
          localParcel2.readException();
          return;
        }
        finally
        {
          localParcel2.recycle();
          localParcel1.recycle();
        }
      }
      
      public boolean setPriority(BluetoothDevice paramBluetoothDevice, int paramInt)
        throws RemoteException
      {
        Parcel localParcel1 = Parcel.obtain();
        Parcel localParcel2 = Parcel.obtain();
        for (;;)
        {
          try
          {
            localParcel1.writeInterfaceToken("android.bluetooth.IBluetoothHeadsetClient");
            if (paramBluetoothDevice != null)
            {
              localParcel1.writeInt(1);
              paramBluetoothDevice.writeToParcel(localParcel1, 0);
              localParcel1.writeInt(paramInt);
              this.mRemote.transact(8, localParcel1, localParcel2, 0);
              localParcel2.readException();
              paramInt = localParcel2.readInt();
              if (paramInt != 0)
              {
                bool = true;
                return bool;
              }
            }
            else
            {
              localParcel1.writeInt(0);
              continue;
            }
            boolean bool = false;
          }
          finally
          {
            localParcel2.recycle();
            localParcel1.recycle();
          }
        }
      }
      
      public boolean startVoiceRecognition(BluetoothDevice paramBluetoothDevice)
        throws RemoteException
      {
        Parcel localParcel1 = Parcel.obtain();
        Parcel localParcel2 = Parcel.obtain();
        for (;;)
        {
          try
          {
            localParcel1.writeInterfaceToken("android.bluetooth.IBluetoothHeadsetClient");
            if (paramBluetoothDevice != null)
            {
              localParcel1.writeInt(1);
              paramBluetoothDevice.writeToParcel(localParcel1, 0);
              this.mRemote.transact(10, localParcel1, localParcel2, 0);
              localParcel2.readException();
              int i = localParcel2.readInt();
              if (i != 0)
              {
                bool = true;
                return bool;
              }
            }
            else
            {
              localParcel1.writeInt(0);
              continue;
            }
            boolean bool = false;
          }
          finally
          {
            localParcel2.recycle();
            localParcel1.recycle();
          }
        }
      }
      
      public boolean stopVoiceRecognition(BluetoothDevice paramBluetoothDevice)
        throws RemoteException
      {
        Parcel localParcel1 = Parcel.obtain();
        Parcel localParcel2 = Parcel.obtain();
        for (;;)
        {
          try
          {
            localParcel1.writeInterfaceToken("android.bluetooth.IBluetoothHeadsetClient");
            if (paramBluetoothDevice != null)
            {
              localParcel1.writeInt(1);
              paramBluetoothDevice.writeToParcel(localParcel1, 0);
              this.mRemote.transact(11, localParcel1, localParcel2, 0);
              localParcel2.readException();
              int i = localParcel2.readInt();
              if (i != 0)
              {
                bool = true;
                return bool;
              }
            }
            else
            {
              localParcel1.writeInt(0);
              continue;
            }
            boolean bool = false;
          }
          finally
          {
            localParcel2.recycle();
            localParcel1.recycle();
          }
        }
      }
      
      public boolean terminateCall(BluetoothDevice paramBluetoothDevice, int paramInt)
        throws RemoteException
      {
        Parcel localParcel1 = Parcel.obtain();
        Parcel localParcel2 = Parcel.obtain();
        for (;;)
        {
          try
          {
            localParcel1.writeInterfaceToken("android.bluetooth.IBluetoothHeadsetClient");
            if (paramBluetoothDevice != null)
            {
              localParcel1.writeInt(1);
              paramBluetoothDevice.writeToParcel(localParcel1, 0);
              localParcel1.writeInt(paramInt);
              this.mRemote.transact(17, localParcel1, localParcel2, 0);
              localParcel2.readException();
              paramInt = localParcel2.readInt();
              if (paramInt != 0)
              {
                bool = true;
                return bool;
              }
            }
            else
            {
              localParcel1.writeInt(0);
              continue;
            }
            boolean bool = false;
          }
          finally
          {
            localParcel2.recycle();
            localParcel1.recycle();
          }
        }
      }
    }
  }
}


/* Location:              /Users/joshua/Desktop/system_framework/classes-dex2jar.jar!/android/bluetooth/IBluetoothHeadsetClient.class
 * Java compiler version: 6 (50.0)
 * JD-Core Version:       0.7.1
 */