package android.net;

import android.os.Binder;
import android.os.IBinder;
import android.os.IInterface;
import android.os.Parcel;
import android.os.Parcelable.Creator;
import android.os.RemoteException;

public abstract interface IEthernetManager
  extends IInterface
{
  public abstract void addListener(IEthernetServiceListener paramIEthernetServiceListener)
    throws RemoteException;
  
  public abstract IpConfiguration getConfiguration()
    throws RemoteException;
  
  public abstract boolean isAvailable()
    throws RemoteException;
  
  public abstract void removeListener(IEthernetServiceListener paramIEthernetServiceListener)
    throws RemoteException;
  
  public abstract void setConfiguration(IpConfiguration paramIpConfiguration)
    throws RemoteException;
  
  public static abstract class Stub
    extends Binder
    implements IEthernetManager
  {
    private static final String DESCRIPTOR = "android.net.IEthernetManager";
    static final int TRANSACTION_addListener = 4;
    static final int TRANSACTION_getConfiguration = 1;
    static final int TRANSACTION_isAvailable = 3;
    static final int TRANSACTION_removeListener = 5;
    static final int TRANSACTION_setConfiguration = 2;
    
    public Stub()
    {
      attachInterface(this, "android.net.IEthernetManager");
    }
    
    public static IEthernetManager asInterface(IBinder paramIBinder)
    {
      if (paramIBinder == null) {
        return null;
      }
      IInterface localIInterface = paramIBinder.queryLocalInterface("android.net.IEthernetManager");
      if ((localIInterface != null) && ((localIInterface instanceof IEthernetManager))) {
        return (IEthernetManager)localIInterface;
      }
      return new Proxy(paramIBinder);
    }
    
    public IBinder asBinder()
    {
      return this;
    }
    
    public boolean onTransact(int paramInt1, Parcel paramParcel1, Parcel paramParcel2, int paramInt2)
      throws RemoteException
    {
      int i = 0;
      switch (paramInt1)
      {
      default: 
        return super.onTransact(paramInt1, paramParcel1, paramParcel2, paramInt2);
      case 1598968902: 
        paramParcel2.writeString("android.net.IEthernetManager");
        return true;
      case 1: 
        paramParcel1.enforceInterface("android.net.IEthernetManager");
        paramParcel1 = getConfiguration();
        paramParcel2.writeNoException();
        if (paramParcel1 != null)
        {
          paramParcel2.writeInt(1);
          paramParcel1.writeToParcel(paramParcel2, 1);
          return true;
        }
        paramParcel2.writeInt(0);
        return true;
      case 2: 
        paramParcel1.enforceInterface("android.net.IEthernetManager");
        if (paramParcel1.readInt() != 0) {}
        for (paramParcel1 = (IpConfiguration)IpConfiguration.CREATOR.createFromParcel(paramParcel1);; paramParcel1 = null)
        {
          setConfiguration(paramParcel1);
          paramParcel2.writeNoException();
          return true;
        }
      case 3: 
        paramParcel1.enforceInterface("android.net.IEthernetManager");
        boolean bool = isAvailable();
        paramParcel2.writeNoException();
        paramInt1 = i;
        if (bool) {
          paramInt1 = 1;
        }
        paramParcel2.writeInt(paramInt1);
        return true;
      case 4: 
        paramParcel1.enforceInterface("android.net.IEthernetManager");
        addListener(IEthernetServiceListener.Stub.asInterface(paramParcel1.readStrongBinder()));
        paramParcel2.writeNoException();
        return true;
      }
      paramParcel1.enforceInterface("android.net.IEthernetManager");
      removeListener(IEthernetServiceListener.Stub.asInterface(paramParcel1.readStrongBinder()));
      paramParcel2.writeNoException();
      return true;
    }
    
    private static class Proxy
      implements IEthernetManager
    {
      private IBinder mRemote;
      
      Proxy(IBinder paramIBinder)
      {
        this.mRemote = paramIBinder;
      }
      
      public void addListener(IEthernetServiceListener paramIEthernetServiceListener)
        throws RemoteException
      {
        IBinder localIBinder = null;
        Parcel localParcel1 = Parcel.obtain();
        Parcel localParcel2 = Parcel.obtain();
        try
        {
          localParcel1.writeInterfaceToken("android.net.IEthernetManager");
          if (paramIEthernetServiceListener != null) {
            localIBinder = paramIEthernetServiceListener.asBinder();
          }
          localParcel1.writeStrongBinder(localIBinder);
          this.mRemote.transact(4, localParcel1, localParcel2, 0);
          localParcel2.readException();
          return;
        }
        finally
        {
          localParcel2.recycle();
          localParcel1.recycle();
        }
      }
      
      public IBinder asBinder()
      {
        return this.mRemote;
      }
      
      /* Error */
      public IpConfiguration getConfiguration()
        throws RemoteException
      {
        // Byte code:
        //   0: invokestatic 30	android/os/Parcel:obtain	()Landroid/os/Parcel;
        //   3: astore_2
        //   4: invokestatic 30	android/os/Parcel:obtain	()Landroid/os/Parcel;
        //   7: astore_3
        //   8: aload_2
        //   9: ldc 32
        //   11: invokevirtual 36	android/os/Parcel:writeInterfaceToken	(Ljava/lang/String;)V
        //   14: aload_0
        //   15: getfield 19	android/net/IEthernetManager$Stub$Proxy:mRemote	Landroid/os/IBinder;
        //   18: iconst_1
        //   19: aload_2
        //   20: aload_3
        //   21: iconst_0
        //   22: invokeinterface 51 5 0
        //   27: pop
        //   28: aload_3
        //   29: invokevirtual 54	android/os/Parcel:readException	()V
        //   32: aload_3
        //   33: invokevirtual 64	android/os/Parcel:readInt	()I
        //   36: ifeq +26 -> 62
        //   39: getstatic 70	android/net/IpConfiguration:CREATOR	Landroid/os/Parcelable$Creator;
        //   42: aload_3
        //   43: invokeinterface 76 2 0
        //   48: checkcast 66	android/net/IpConfiguration
        //   51: astore_1
        //   52: aload_3
        //   53: invokevirtual 57	android/os/Parcel:recycle	()V
        //   56: aload_2
        //   57: invokevirtual 57	android/os/Parcel:recycle	()V
        //   60: aload_1
        //   61: areturn
        //   62: aconst_null
        //   63: astore_1
        //   64: goto -12 -> 52
        //   67: astore_1
        //   68: aload_3
        //   69: invokevirtual 57	android/os/Parcel:recycle	()V
        //   72: aload_2
        //   73: invokevirtual 57	android/os/Parcel:recycle	()V
        //   76: aload_1
        //   77: athrow
        // Local variable table:
        //   start	length	slot	name	signature
        //   0	78	0	this	Proxy
        //   51	13	1	localIpConfiguration	IpConfiguration
        //   67	10	1	localObject	Object
        //   3	70	2	localParcel1	Parcel
        //   7	62	3	localParcel2	Parcel
        // Exception table:
        //   from	to	target	type
        //   8	52	67	finally
      }
      
      public String getInterfaceDescriptor()
      {
        return "android.net.IEthernetManager";
      }
      
      /* Error */
      public boolean isAvailable()
        throws RemoteException
      {
        // Byte code:
        //   0: invokestatic 30	android/os/Parcel:obtain	()Landroid/os/Parcel;
        //   3: astore_3
        //   4: invokestatic 30	android/os/Parcel:obtain	()Landroid/os/Parcel;
        //   7: astore 4
        //   9: aload_3
        //   10: ldc 32
        //   12: invokevirtual 36	android/os/Parcel:writeInterfaceToken	(Ljava/lang/String;)V
        //   15: aload_0
        //   16: getfield 19	android/net/IEthernetManager$Stub$Proxy:mRemote	Landroid/os/IBinder;
        //   19: iconst_3
        //   20: aload_3
        //   21: aload 4
        //   23: iconst_0
        //   24: invokeinterface 51 5 0
        //   29: pop
        //   30: aload 4
        //   32: invokevirtual 54	android/os/Parcel:readException	()V
        //   35: aload 4
        //   37: invokevirtual 64	android/os/Parcel:readInt	()I
        //   40: istore_1
        //   41: iload_1
        //   42: ifeq +16 -> 58
        //   45: iconst_1
        //   46: istore_2
        //   47: aload 4
        //   49: invokevirtual 57	android/os/Parcel:recycle	()V
        //   52: aload_3
        //   53: invokevirtual 57	android/os/Parcel:recycle	()V
        //   56: iload_2
        //   57: ireturn
        //   58: iconst_0
        //   59: istore_2
        //   60: goto -13 -> 47
        //   63: astore 5
        //   65: aload 4
        //   67: invokevirtual 57	android/os/Parcel:recycle	()V
        //   70: aload_3
        //   71: invokevirtual 57	android/os/Parcel:recycle	()V
        //   74: aload 5
        //   76: athrow
        // Local variable table:
        //   start	length	slot	name	signature
        //   0	77	0	this	Proxy
        //   40	2	1	i	int
        //   46	14	2	bool	boolean
        //   3	68	3	localParcel1	Parcel
        //   7	59	4	localParcel2	Parcel
        //   63	12	5	localObject	Object
        // Exception table:
        //   from	to	target	type
        //   9	41	63	finally
      }
      
      public void removeListener(IEthernetServiceListener paramIEthernetServiceListener)
        throws RemoteException
      {
        IBinder localIBinder = null;
        Parcel localParcel1 = Parcel.obtain();
        Parcel localParcel2 = Parcel.obtain();
        try
        {
          localParcel1.writeInterfaceToken("android.net.IEthernetManager");
          if (paramIEthernetServiceListener != null) {
            localIBinder = paramIEthernetServiceListener.asBinder();
          }
          localParcel1.writeStrongBinder(localIBinder);
          this.mRemote.transact(5, localParcel1, localParcel2, 0);
          localParcel2.readException();
          return;
        }
        finally
        {
          localParcel2.recycle();
          localParcel1.recycle();
        }
      }
      
      /* Error */
      public void setConfiguration(IpConfiguration paramIpConfiguration)
        throws RemoteException
      {
        // Byte code:
        //   0: invokestatic 30	android/os/Parcel:obtain	()Landroid/os/Parcel;
        //   3: astore_2
        //   4: invokestatic 30	android/os/Parcel:obtain	()Landroid/os/Parcel;
        //   7: astore_3
        //   8: aload_2
        //   9: ldc 32
        //   11: invokevirtual 36	android/os/Parcel:writeInterfaceToken	(Ljava/lang/String;)V
        //   14: aload_1
        //   15: ifnull +41 -> 56
        //   18: aload_2
        //   19: iconst_1
        //   20: invokevirtual 87	android/os/Parcel:writeInt	(I)V
        //   23: aload_1
        //   24: aload_2
        //   25: iconst_0
        //   26: invokevirtual 91	android/net/IpConfiguration:writeToParcel	(Landroid/os/Parcel;I)V
        //   29: aload_0
        //   30: getfield 19	android/net/IEthernetManager$Stub$Proxy:mRemote	Landroid/os/IBinder;
        //   33: iconst_2
        //   34: aload_2
        //   35: aload_3
        //   36: iconst_0
        //   37: invokeinterface 51 5 0
        //   42: pop
        //   43: aload_3
        //   44: invokevirtual 54	android/os/Parcel:readException	()V
        //   47: aload_3
        //   48: invokevirtual 57	android/os/Parcel:recycle	()V
        //   51: aload_2
        //   52: invokevirtual 57	android/os/Parcel:recycle	()V
        //   55: return
        //   56: aload_2
        //   57: iconst_0
        //   58: invokevirtual 87	android/os/Parcel:writeInt	(I)V
        //   61: goto -32 -> 29
        //   64: astore_1
        //   65: aload_3
        //   66: invokevirtual 57	android/os/Parcel:recycle	()V
        //   69: aload_2
        //   70: invokevirtual 57	android/os/Parcel:recycle	()V
        //   73: aload_1
        //   74: athrow
        // Local variable table:
        //   start	length	slot	name	signature
        //   0	75	0	this	Proxy
        //   0	75	1	paramIpConfiguration	IpConfiguration
        //   3	67	2	localParcel1	Parcel
        //   7	59	3	localParcel2	Parcel
        // Exception table:
        //   from	to	target	type
        //   8	14	64	finally
        //   18	29	64	finally
        //   29	47	64	finally
        //   56	61	64	finally
      }
    }
  }
}


/* Location:              /Users/joshua/Desktop/system_framework/classes-dex2jar.jar!/android/net/IEthernetManager.class
 * Java compiler version: 6 (50.0)
 * JD-Core Version:       0.7.1
 */