package android.net;

import android.os.Binder;
import android.os.IBinder;
import android.os.IInterface;
import android.os.Parcel;
import android.os.RemoteException;

public abstract interface INetd
  extends IInterface
{
  public static final int CONF = 1;
  public static final int IPV4 = 4;
  public static final int IPV6 = 6;
  public static final int NEIGH = 2;
  public static final int RESOLVER_PARAMS_COUNT = 4;
  public static final int RESOLVER_PARAMS_MAX_SAMPLES = 3;
  public static final int RESOLVER_PARAMS_MIN_SAMPLES = 2;
  public static final int RESOLVER_PARAMS_SAMPLE_VALIDITY = 0;
  public static final int RESOLVER_PARAMS_SUCCESS_THRESHOLD = 1;
  public static final int RESOLVER_STATS_COUNT = 7;
  public static final int RESOLVER_STATS_ERRORS = 1;
  public static final int RESOLVER_STATS_INTERNAL_ERRORS = 3;
  public static final int RESOLVER_STATS_LAST_SAMPLE_TIME = 5;
  public static final int RESOLVER_STATS_RTT_AVG = 4;
  public static final int RESOLVER_STATS_SUCCESSES = 0;
  public static final int RESOLVER_STATS_TIMEOUTS = 2;
  public static final int RESOLVER_STATS_USABLE = 6;
  
  public abstract boolean bandwidthEnableDataSaver(boolean paramBoolean)
    throws RemoteException;
  
  public abstract boolean firewallReplaceUidChain(String paramString, boolean paramBoolean, int[] paramArrayOfInt)
    throws RemoteException;
  
  public abstract void getResolverInfo(int paramInt, String[] paramArrayOfString1, String[] paramArrayOfString2, int[] paramArrayOfInt1, int[] paramArrayOfInt2)
    throws RemoteException;
  
  public abstract void interfaceAddAddress(String paramString1, String paramString2, int paramInt)
    throws RemoteException;
  
  public abstract void interfaceDelAddress(String paramString1, String paramString2, int paramInt)
    throws RemoteException;
  
  public abstract boolean isAlive()
    throws RemoteException;
  
  public abstract void networkRejectNonSecureVpn(boolean paramBoolean, UidRange[] paramArrayOfUidRange)
    throws RemoteException;
  
  public abstract void setProcSysNet(int paramInt1, int paramInt2, String paramString1, String paramString2, String paramString3)
    throws RemoteException;
  
  public abstract void setResolverConfiguration(int paramInt, String[] paramArrayOfString1, String[] paramArrayOfString2, int[] paramArrayOfInt)
    throws RemoteException;
  
  public abstract void socketDestroy(UidRange[] paramArrayOfUidRange, int[] paramArrayOfInt)
    throws RemoteException;
  
  public abstract boolean tetherApplyDnsInterfaces()
    throws RemoteException;
  
  public static abstract class Stub
    extends Binder
    implements INetd
  {
    private static final String DESCRIPTOR = "android.net.INetd";
    static final int TRANSACTION_bandwidthEnableDataSaver = 3;
    static final int TRANSACTION_firewallReplaceUidChain = 2;
    static final int TRANSACTION_getResolverInfo = 7;
    static final int TRANSACTION_interfaceAddAddress = 9;
    static final int TRANSACTION_interfaceDelAddress = 10;
    static final int TRANSACTION_isAlive = 1;
    static final int TRANSACTION_networkRejectNonSecureVpn = 4;
    static final int TRANSACTION_setProcSysNet = 11;
    static final int TRANSACTION_setResolverConfiguration = 6;
    static final int TRANSACTION_socketDestroy = 5;
    static final int TRANSACTION_tetherApplyDnsInterfaces = 8;
    
    public Stub()
    {
      attachInterface(this, "android.net.INetd");
    }
    
    public static INetd asInterface(IBinder paramIBinder)
    {
      if (paramIBinder == null) {
        return null;
      }
      IInterface localIInterface = paramIBinder.queryLocalInterface("android.net.INetd");
      if ((localIInterface != null) && ((localIInterface instanceof INetd))) {
        return (INetd)localIInterface;
      }
      return new Proxy(paramIBinder);
    }
    
    public IBinder asBinder()
    {
      return this;
    }
    
    public boolean onTransact(int paramInt1, Parcel paramParcel1, Parcel paramParcel2, int paramInt2)
      throws RemoteException
    {
      boolean bool;
      Object localObject;
      switch (paramInt1)
      {
      default: 
        return super.onTransact(paramInt1, paramParcel1, paramParcel2, paramInt2);
      case 1598968902: 
        paramParcel2.writeString("android.net.INetd");
        return true;
      case 1: 
        paramParcel1.enforceInterface("android.net.INetd");
        bool = isAlive();
        paramParcel2.writeNoException();
        if (bool) {}
        for (paramInt1 = 1;; paramInt1 = 0)
        {
          paramParcel2.writeInt(paramInt1);
          return true;
        }
      case 2: 
        paramParcel1.enforceInterface("android.net.INetd");
        localObject = paramParcel1.readString();
        if (paramParcel1.readInt() != 0)
        {
          bool = true;
          bool = firewallReplaceUidChain((String)localObject, bool, paramParcel1.createIntArray());
          paramParcel2.writeNoException();
          if (!bool) {
            break label221;
          }
        }
        for (paramInt1 = 1;; paramInt1 = 0)
        {
          paramParcel2.writeInt(paramInt1);
          return true;
          bool = false;
          break;
        }
      case 3: 
        paramParcel1.enforceInterface("android.net.INetd");
        if (paramParcel1.readInt() != 0)
        {
          bool = true;
          bool = bandwidthEnableDataSaver(bool);
          paramParcel2.writeNoException();
          if (!bool) {
            break label274;
          }
        }
        for (paramInt1 = 1;; paramInt1 = 0)
        {
          paramParcel2.writeInt(paramInt1);
          return true;
          bool = false;
          break;
        }
      case 4: 
        paramParcel1.enforceInterface("android.net.INetd");
        if (paramParcel1.readInt() != 0) {}
        for (bool = true;; bool = false)
        {
          networkRejectNonSecureVpn(bool, (UidRange[])paramParcel1.createTypedArray(UidRange.CREATOR));
          paramParcel2.writeNoException();
          return true;
        }
      case 5: 
        paramParcel1.enforceInterface("android.net.INetd");
        socketDestroy((UidRange[])paramParcel1.createTypedArray(UidRange.CREATOR), paramParcel1.createIntArray());
        paramParcel2.writeNoException();
        return true;
      case 6: 
        paramParcel1.enforceInterface("android.net.INetd");
        setResolverConfiguration(paramParcel1.readInt(), paramParcel1.createStringArray(), paramParcel1.createStringArray(), paramParcel1.createIntArray());
        paramParcel2.writeNoException();
        return true;
      case 7: 
        paramParcel1.enforceInterface("android.net.INetd");
        paramInt1 = paramParcel1.readInt();
        paramInt2 = paramParcel1.readInt();
        String[] arrayOfString;
        int[] arrayOfInt;
        if (paramInt2 < 0)
        {
          localObject = null;
          paramInt2 = paramParcel1.readInt();
          if (paramInt2 >= 0) {
            break label502;
          }
          arrayOfString = null;
          paramInt2 = paramParcel1.readInt();
          if (paramInt2 >= 0) {
            break label512;
          }
          arrayOfInt = null;
          paramInt2 = paramParcel1.readInt();
          if (paramInt2 >= 0) {
            break label521;
          }
        }
        for (paramParcel1 = null;; paramParcel1 = new int[paramInt2])
        {
          getResolverInfo(paramInt1, (String[])localObject, arrayOfString, arrayOfInt, paramParcel1);
          paramParcel2.writeNoException();
          paramParcel2.writeStringArray((String[])localObject);
          paramParcel2.writeStringArray(arrayOfString);
          paramParcel2.writeIntArray(arrayOfInt);
          paramParcel2.writeIntArray(paramParcel1);
          return true;
          localObject = new String[paramInt2];
          break;
          arrayOfString = new String[paramInt2];
          break label424;
          arrayOfInt = new int[paramInt2];
          break label438;
        }
      case 8: 
        paramParcel1.enforceInterface("android.net.INetd");
        bool = tetherApplyDnsInterfaces();
        paramParcel2.writeNoException();
        if (bool) {}
        for (paramInt1 = 1;; paramInt1 = 0)
        {
          paramParcel2.writeInt(paramInt1);
          return true;
        }
      case 9: 
        paramParcel1.enforceInterface("android.net.INetd");
        interfaceAddAddress(paramParcel1.readString(), paramParcel1.readString(), paramParcel1.readInt());
        paramParcel2.writeNoException();
        return true;
      case 10: 
        label221:
        label274:
        label424:
        label438:
        label502:
        label512:
        label521:
        paramParcel1.enforceInterface("android.net.INetd");
        interfaceDelAddress(paramParcel1.readString(), paramParcel1.readString(), paramParcel1.readInt());
        paramParcel2.writeNoException();
        return true;
      }
      paramParcel1.enforceInterface("android.net.INetd");
      setProcSysNet(paramParcel1.readInt(), paramParcel1.readInt(), paramParcel1.readString(), paramParcel1.readString(), paramParcel1.readString());
      paramParcel2.writeNoException();
      return true;
    }
    
    private static class Proxy
      implements INetd
    {
      private IBinder mRemote;
      
      Proxy(IBinder paramIBinder)
      {
        this.mRemote = paramIBinder;
      }
      
      public IBinder asBinder()
      {
        return this.mRemote;
      }
      
      /* Error */
      public boolean bandwidthEnableDataSaver(boolean paramBoolean)
        throws RemoteException
      {
        // Byte code:
        //   0: iconst_0
        //   1: istore_2
        //   2: invokestatic 32	android/os/Parcel:obtain	()Landroid/os/Parcel;
        //   5: astore_3
        //   6: invokestatic 32	android/os/Parcel:obtain	()Landroid/os/Parcel;
        //   9: astore 4
        //   11: aload_3
        //   12: ldc 34
        //   14: invokevirtual 38	android/os/Parcel:writeInterfaceToken	(Ljava/lang/String;)V
        //   17: iload_1
        //   18: ifeq +5 -> 23
        //   21: iconst_1
        //   22: istore_2
        //   23: aload_3
        //   24: iload_2
        //   25: invokevirtual 42	android/os/Parcel:writeInt	(I)V
        //   28: aload_0
        //   29: getfield 19	android/net/INetd$Stub$Proxy:mRemote	Landroid/os/IBinder;
        //   32: iconst_3
        //   33: aload_3
        //   34: aload 4
        //   36: iconst_0
        //   37: invokeinterface 48 5 0
        //   42: pop
        //   43: aload 4
        //   45: invokevirtual 51	android/os/Parcel:readException	()V
        //   48: aload 4
        //   50: invokevirtual 55	android/os/Parcel:readInt	()I
        //   53: istore_2
        //   54: iload_2
        //   55: ifeq +16 -> 71
        //   58: iconst_1
        //   59: istore_1
        //   60: aload 4
        //   62: invokevirtual 58	android/os/Parcel:recycle	()V
        //   65: aload_3
        //   66: invokevirtual 58	android/os/Parcel:recycle	()V
        //   69: iload_1
        //   70: ireturn
        //   71: iconst_0
        //   72: istore_1
        //   73: goto -13 -> 60
        //   76: astore 5
        //   78: aload 4
        //   80: invokevirtual 58	android/os/Parcel:recycle	()V
        //   83: aload_3
        //   84: invokevirtual 58	android/os/Parcel:recycle	()V
        //   87: aload 5
        //   89: athrow
        // Local variable table:
        //   start	length	slot	name	signature
        //   0	90	0	this	Proxy
        //   0	90	1	paramBoolean	boolean
        //   1	54	2	i	int
        //   5	79	3	localParcel1	Parcel
        //   9	70	4	localParcel2	Parcel
        //   76	12	5	localObject	Object
        // Exception table:
        //   from	to	target	type
        //   11	17	76	finally
        //   23	54	76	finally
      }
      
      /* Error */
      public boolean firewallReplaceUidChain(String paramString, boolean paramBoolean, int[] paramArrayOfInt)
        throws RemoteException
      {
        // Byte code:
        //   0: iconst_0
        //   1: istore 4
        //   3: invokestatic 32	android/os/Parcel:obtain	()Landroid/os/Parcel;
        //   6: astore 5
        //   8: invokestatic 32	android/os/Parcel:obtain	()Landroid/os/Parcel;
        //   11: astore 6
        //   13: aload 5
        //   15: ldc 34
        //   17: invokevirtual 38	android/os/Parcel:writeInterfaceToken	(Ljava/lang/String;)V
        //   20: aload 5
        //   22: aload_1
        //   23: invokevirtual 64	android/os/Parcel:writeString	(Ljava/lang/String;)V
        //   26: iload_2
        //   27: ifeq +6 -> 33
        //   30: iconst_1
        //   31: istore 4
        //   33: aload 5
        //   35: iload 4
        //   37: invokevirtual 42	android/os/Parcel:writeInt	(I)V
        //   40: aload 5
        //   42: aload_3
        //   43: invokevirtual 68	android/os/Parcel:writeIntArray	([I)V
        //   46: aload_0
        //   47: getfield 19	android/net/INetd$Stub$Proxy:mRemote	Landroid/os/IBinder;
        //   50: iconst_2
        //   51: aload 5
        //   53: aload 6
        //   55: iconst_0
        //   56: invokeinterface 48 5 0
        //   61: pop
        //   62: aload 6
        //   64: invokevirtual 51	android/os/Parcel:readException	()V
        //   67: aload 6
        //   69: invokevirtual 55	android/os/Parcel:readInt	()I
        //   72: istore 4
        //   74: iload 4
        //   76: ifeq +17 -> 93
        //   79: iconst_1
        //   80: istore_2
        //   81: aload 6
        //   83: invokevirtual 58	android/os/Parcel:recycle	()V
        //   86: aload 5
        //   88: invokevirtual 58	android/os/Parcel:recycle	()V
        //   91: iload_2
        //   92: ireturn
        //   93: iconst_0
        //   94: istore_2
        //   95: goto -14 -> 81
        //   98: astore_1
        //   99: aload 6
        //   101: invokevirtual 58	android/os/Parcel:recycle	()V
        //   104: aload 5
        //   106: invokevirtual 58	android/os/Parcel:recycle	()V
        //   109: aload_1
        //   110: athrow
        // Local variable table:
        //   start	length	slot	name	signature
        //   0	111	0	this	Proxy
        //   0	111	1	paramString	String
        //   0	111	2	paramBoolean	boolean
        //   0	111	3	paramArrayOfInt	int[]
        //   1	74	4	i	int
        //   6	99	5	localParcel1	Parcel
        //   11	89	6	localParcel2	Parcel
        // Exception table:
        //   from	to	target	type
        //   13	26	98	finally
        //   33	74	98	finally
      }
      
      public String getInterfaceDescriptor()
      {
        return "android.net.INetd";
      }
      
      public void getResolverInfo(int paramInt, String[] paramArrayOfString1, String[] paramArrayOfString2, int[] paramArrayOfInt1, int[] paramArrayOfInt2)
        throws RemoteException
      {
        Parcel localParcel1 = Parcel.obtain();
        Parcel localParcel2 = Parcel.obtain();
        for (;;)
        {
          try
          {
            localParcel1.writeInterfaceToken("android.net.INetd");
            localParcel1.writeInt(paramInt);
            if (paramArrayOfString1 == null)
            {
              localParcel1.writeInt(-1);
              if (paramArrayOfString2 == null)
              {
                localParcel1.writeInt(-1);
                if (paramArrayOfInt1 != null) {
                  break label157;
                }
                localParcel1.writeInt(-1);
                if (paramArrayOfInt2 != null) {
                  break label168;
                }
                localParcel1.writeInt(-1);
                this.mRemote.transact(7, localParcel1, localParcel2, 0);
                localParcel2.readException();
                localParcel2.readStringArray(paramArrayOfString1);
                localParcel2.readStringArray(paramArrayOfString2);
                localParcel2.readIntArray(paramArrayOfInt1);
                localParcel2.readIntArray(paramArrayOfInt2);
              }
            }
            else
            {
              localParcel1.writeInt(paramArrayOfString1.length);
              continue;
            }
            localParcel1.writeInt(paramArrayOfString2.length);
          }
          finally
          {
            localParcel2.recycle();
            localParcel1.recycle();
          }
          continue;
          label157:
          localParcel1.writeInt(paramArrayOfInt1.length);
          continue;
          label168:
          localParcel1.writeInt(paramArrayOfInt2.length);
        }
      }
      
      public void interfaceAddAddress(String paramString1, String paramString2, int paramInt)
        throws RemoteException
      {
        Parcel localParcel1 = Parcel.obtain();
        Parcel localParcel2 = Parcel.obtain();
        try
        {
          localParcel1.writeInterfaceToken("android.net.INetd");
          localParcel1.writeString(paramString1);
          localParcel1.writeString(paramString2);
          localParcel1.writeInt(paramInt);
          this.mRemote.transact(9, localParcel1, localParcel2, 0);
          localParcel2.readException();
          return;
        }
        finally
        {
          localParcel2.recycle();
          localParcel1.recycle();
        }
      }
      
      public void interfaceDelAddress(String paramString1, String paramString2, int paramInt)
        throws RemoteException
      {
        Parcel localParcel1 = Parcel.obtain();
        Parcel localParcel2 = Parcel.obtain();
        try
        {
          localParcel1.writeInterfaceToken("android.net.INetd");
          localParcel1.writeString(paramString1);
          localParcel1.writeString(paramString2);
          localParcel1.writeInt(paramInt);
          this.mRemote.transact(10, localParcel1, localParcel2, 0);
          localParcel2.readException();
          return;
        }
        finally
        {
          localParcel2.recycle();
          localParcel1.recycle();
        }
      }
      
      /* Error */
      public boolean isAlive()
        throws RemoteException
      {
        // Byte code:
        //   0: invokestatic 32	android/os/Parcel:obtain	()Landroid/os/Parcel;
        //   3: astore_3
        //   4: invokestatic 32	android/os/Parcel:obtain	()Landroid/os/Parcel;
        //   7: astore 4
        //   9: aload_3
        //   10: ldc 34
        //   12: invokevirtual 38	android/os/Parcel:writeInterfaceToken	(Ljava/lang/String;)V
        //   15: aload_0
        //   16: getfield 19	android/net/INetd$Stub$Proxy:mRemote	Landroid/os/IBinder;
        //   19: iconst_1
        //   20: aload_3
        //   21: aload 4
        //   23: iconst_0
        //   24: invokeinterface 48 5 0
        //   29: pop
        //   30: aload 4
        //   32: invokevirtual 51	android/os/Parcel:readException	()V
        //   35: aload 4
        //   37: invokevirtual 55	android/os/Parcel:readInt	()I
        //   40: istore_1
        //   41: iload_1
        //   42: ifeq +16 -> 58
        //   45: iconst_1
        //   46: istore_2
        //   47: aload 4
        //   49: invokevirtual 58	android/os/Parcel:recycle	()V
        //   52: aload_3
        //   53: invokevirtual 58	android/os/Parcel:recycle	()V
        //   56: iload_2
        //   57: ireturn
        //   58: iconst_0
        //   59: istore_2
        //   60: goto -13 -> 47
        //   63: astore 5
        //   65: aload 4
        //   67: invokevirtual 58	android/os/Parcel:recycle	()V
        //   70: aload_3
        //   71: invokevirtual 58	android/os/Parcel:recycle	()V
        //   74: aload 5
        //   76: athrow
        // Local variable table:
        //   start	length	slot	name	signature
        //   0	77	0	this	Proxy
        //   40	2	1	i	int
        //   46	14	2	bool	boolean
        //   3	68	3	localParcel1	Parcel
        //   7	59	4	localParcel2	Parcel
        //   63	12	5	localObject	Object
        // Exception table:
        //   from	to	target	type
        //   9	41	63	finally
      }
      
      public void networkRejectNonSecureVpn(boolean paramBoolean, UidRange[] paramArrayOfUidRange)
        throws RemoteException
      {
        int i = 0;
        Parcel localParcel1 = Parcel.obtain();
        Parcel localParcel2 = Parcel.obtain();
        try
        {
          localParcel1.writeInterfaceToken("android.net.INetd");
          if (paramBoolean) {
            i = 1;
          }
          localParcel1.writeInt(i);
          localParcel1.writeTypedArray(paramArrayOfUidRange, 0);
          this.mRemote.transact(4, localParcel1, localParcel2, 0);
          localParcel2.readException();
          return;
        }
        finally
        {
          localParcel2.recycle();
          localParcel1.recycle();
        }
      }
      
      public void setProcSysNet(int paramInt1, int paramInt2, String paramString1, String paramString2, String paramString3)
        throws RemoteException
      {
        Parcel localParcel1 = Parcel.obtain();
        Parcel localParcel2 = Parcel.obtain();
        try
        {
          localParcel1.writeInterfaceToken("android.net.INetd");
          localParcel1.writeInt(paramInt1);
          localParcel1.writeInt(paramInt2);
          localParcel1.writeString(paramString1);
          localParcel1.writeString(paramString2);
          localParcel1.writeString(paramString3);
          this.mRemote.transact(11, localParcel1, localParcel2, 0);
          localParcel2.readException();
          return;
        }
        finally
        {
          localParcel2.recycle();
          localParcel1.recycle();
        }
      }
      
      public void setResolverConfiguration(int paramInt, String[] paramArrayOfString1, String[] paramArrayOfString2, int[] paramArrayOfInt)
        throws RemoteException
      {
        Parcel localParcel1 = Parcel.obtain();
        Parcel localParcel2 = Parcel.obtain();
        try
        {
          localParcel1.writeInterfaceToken("android.net.INetd");
          localParcel1.writeInt(paramInt);
          localParcel1.writeStringArray(paramArrayOfString1);
          localParcel1.writeStringArray(paramArrayOfString2);
          localParcel1.writeIntArray(paramArrayOfInt);
          this.mRemote.transact(6, localParcel1, localParcel2, 0);
          localParcel2.readException();
          return;
        }
        finally
        {
          localParcel2.recycle();
          localParcel1.recycle();
        }
      }
      
      public void socketDestroy(UidRange[] paramArrayOfUidRange, int[] paramArrayOfInt)
        throws RemoteException
      {
        Parcel localParcel1 = Parcel.obtain();
        Parcel localParcel2 = Parcel.obtain();
        try
        {
          localParcel1.writeInterfaceToken("android.net.INetd");
          localParcel1.writeTypedArray(paramArrayOfUidRange, 0);
          localParcel1.writeIntArray(paramArrayOfInt);
          this.mRemote.transact(5, localParcel1, localParcel2, 0);
          localParcel2.readException();
          return;
        }
        finally
        {
          localParcel2.recycle();
          localParcel1.recycle();
        }
      }
      
      /* Error */
      public boolean tetherApplyDnsInterfaces()
        throws RemoteException
      {
        // Byte code:
        //   0: invokestatic 32	android/os/Parcel:obtain	()Landroid/os/Parcel;
        //   3: astore_3
        //   4: invokestatic 32	android/os/Parcel:obtain	()Landroid/os/Parcel;
        //   7: astore 4
        //   9: aload_3
        //   10: ldc 34
        //   12: invokevirtual 38	android/os/Parcel:writeInterfaceToken	(Ljava/lang/String;)V
        //   15: aload_0
        //   16: getfield 19	android/net/INetd$Stub$Proxy:mRemote	Landroid/os/IBinder;
        //   19: bipush 8
        //   21: aload_3
        //   22: aload 4
        //   24: iconst_0
        //   25: invokeinterface 48 5 0
        //   30: pop
        //   31: aload 4
        //   33: invokevirtual 51	android/os/Parcel:readException	()V
        //   36: aload 4
        //   38: invokevirtual 55	android/os/Parcel:readInt	()I
        //   41: istore_1
        //   42: iload_1
        //   43: ifeq +16 -> 59
        //   46: iconst_1
        //   47: istore_2
        //   48: aload 4
        //   50: invokevirtual 58	android/os/Parcel:recycle	()V
        //   53: aload_3
        //   54: invokevirtual 58	android/os/Parcel:recycle	()V
        //   57: iload_2
        //   58: ireturn
        //   59: iconst_0
        //   60: istore_2
        //   61: goto -13 -> 48
        //   64: astore 5
        //   66: aload 4
        //   68: invokevirtual 58	android/os/Parcel:recycle	()V
        //   71: aload_3
        //   72: invokevirtual 58	android/os/Parcel:recycle	()V
        //   75: aload 5
        //   77: athrow
        // Local variable table:
        //   start	length	slot	name	signature
        //   0	78	0	this	Proxy
        //   41	2	1	i	int
        //   47	14	2	bool	boolean
        //   3	69	3	localParcel1	Parcel
        //   7	60	4	localParcel2	Parcel
        //   64	12	5	localObject	Object
        // Exception table:
        //   from	to	target	type
        //   9	42	64	finally
      }
    }
  }
}


/* Location:              /Users/joshua/Desktop/system_framework/classes-dex2jar.jar!/android/net/INetd.class
 * Java compiler version: 6 (50.0)
 * JD-Core Version:       0.7.1
 */