package com.aps;

final class al
  extends Thread
{
  al(ak paramak, String paramString)
  {
    super(paramString);
  }
  
  /* Error */
  public final void run()
  {
    // Byte code:
    //   0: invokestatic 23	android/os/Looper:prepare	()V
    //   3: aload_0
    //   4: getfield 10	com/aps/al:a	Lcom/aps/ak;
    //   7: invokestatic 27	android/os/Looper:myLooper	()Landroid/os/Looper;
    //   10: invokestatic 32	com/aps/ak:a	(Lcom/aps/ak;Landroid/os/Looper;)Landroid/os/Looper;
    //   13: pop
    //   14: aload_0
    //   15: getfield 10	com/aps/al:a	Lcom/aps/ak;
    //   18: new 34	java/util/Timer
    //   21: dup
    //   22: invokespecial 36	java/util/Timer:<init>	()V
    //   25: invokestatic 39	com/aps/ak:a	(Lcom/aps/ak;Ljava/util/Timer;)Ljava/util/Timer;
    //   28: pop
    //   29: aload_0
    //   30: getfield 10	com/aps/al:a	Lcom/aps/ak;
    //   33: new 41	com/aps/am
    //   36: dup
    //   37: aload_0
    //   38: getfield 10	com/aps/al:a	Lcom/aps/ak;
    //   41: iconst_0
    //   42: invokespecial 44	com/aps/am:<init>	(Lcom/aps/ak;B)V
    //   45: invokestatic 47	com/aps/ak:a	(Lcom/aps/ak;Lcom/aps/am;)Lcom/aps/am;
    //   48: pop
    //   49: aload_0
    //   50: getfield 10	com/aps/al:a	Lcom/aps/ak;
    //   53: aload_0
    //   54: getfield 10	com/aps/al:a	Lcom/aps/ak;
    //   57: invokestatic 50	com/aps/ak:a	(Lcom/aps/ak;)Lcom/aps/am;
    //   60: invokestatic 53	com/aps/ak:a	(Lcom/aps/ak;Landroid/telephony/PhoneStateListener;)V
    //   63: aload_0
    //   64: getfield 10	com/aps/al:a	Lcom/aps/ak;
    //   67: new 55	com/aps/an
    //   70: dup
    //   71: aload_0
    //   72: getfield 10	com/aps/al:a	Lcom/aps/ak;
    //   75: iconst_0
    //   76: invokespecial 56	com/aps/an:<init>	(Lcom/aps/ak;B)V
    //   79: invokestatic 59	com/aps/ak:a	(Lcom/aps/ak;Lcom/aps/an;)Lcom/aps/an;
    //   82: pop
    //   83: aload_0
    //   84: getfield 10	com/aps/al:a	Lcom/aps/ak;
    //   87: aload_0
    //   88: getfield 10	com/aps/al:a	Lcom/aps/ak;
    //   91: invokestatic 63	com/aps/ak:b	(Lcom/aps/ak;)Lcom/aps/an;
    //   94: invokestatic 66	com/aps/ak:a	(Lcom/aps/ak;Landroid/location/GpsStatus$NmeaListener;)V
    //   97: invokestatic 69	android/os/Looper:loop	()V
    //   100: return
    //   101: astore_1
    //   102: return
    //   103: astore_1
    //   104: goto -7 -> 97
    // Local variable table:
    //   start	length	slot	name	signature
    //   0	107	0	this	al
    //   101	1	1	localException1	Exception
    //   103	1	1	localException2	Exception
    // Exception table:
    //   from	to	target	type
    //   0	83	101	java/lang/Exception
    //   97	100	101	java/lang/Exception
    //   83	97	103	java/lang/Exception
  }
}


/* Location:              /Users/joshua/Desktop/system_framework/classes-dex2jar.jar!/com/aps/al.class
 * Java compiler version: 6 (50.0)
 * JD-Core Version:       0.7.1
 */