package com.aps;

import android.net.NetworkInfo;
import android.net.Proxy;
import android.telephony.TelephonyManager;
import android.text.TextUtils;
import android.util.SparseArray;
import com.amap.api.location.core.c;
import org.apache.http.Header;
import org.apache.http.HttpResponse;
import org.json.JSONException;
import org.json.JSONObject;

public class l
{
  private static l a = null;
  
  public static int a(NetworkInfo paramNetworkInfo)
  {
    int j = -1;
    int i = j;
    if (paramNetworkInfo != null)
    {
      i = j;
      if (paramNetworkInfo.isAvailable())
      {
        i = j;
        if (paramNetworkInfo.isConnected()) {
          i = paramNetworkInfo.getType();
        }
      }
    }
    return i;
  }
  
  public static l a()
  {
    if (a != null) {}
    for (;;)
    {
      return a;
      a = new l();
    }
  }
  
  public static String a(TelephonyManager paramTelephonyManager)
  {
    int i = 0;
    if (paramTelephonyManager == null) {}
    for (;;)
    {
      return (String)f.l.get(i, "UNKNOWN");
      i = paramTelephonyManager.getNetworkType();
    }
  }
  
  /* Error */
  public static org.apache.http.client.HttpClient a(android.content.Context paramContext, NetworkInfo paramNetworkInfo)
    throws java.lang.Exception
  {
    // Byte code:
    //   0: iconst_m1
    //   1: istore_3
    //   2: iconst_1
    //   3: istore_2
    //   4: aconst_null
    //   5: astore 5
    //   7: aconst_null
    //   8: astore 7
    //   10: new 59	org/apache/http/params/BasicHttpParams
    //   13: dup
    //   14: invokespecial 60	org/apache/http/params/BasicHttpParams:<init>	()V
    //   17: astore 8
    //   19: aload_1
    //   20: invokevirtual 28	android/net/NetworkInfo:getType	()I
    //   23: ifeq +77 -> 100
    //   26: aload 7
    //   28: astore_0
    //   29: iload_3
    //   30: istore_2
    //   31: aload_0
    //   32: iload_2
    //   33: invokestatic 63	com/aps/l:a	(Ljava/lang/String;I)Z
    //   36: ifne +524 -> 560
    //   39: aload 8
    //   41: sipush 30000
    //   44: invokestatic 68	com/aps/t:a	(Lorg/apache/http/params/HttpParams;I)V
    //   47: aload 8
    //   49: iconst_0
    //   50: invokestatic 74	org/apache/http/params/HttpProtocolParams:setUseExpectContinue	(Lorg/apache/http/params/HttpParams;Z)V
    //   53: new 76	org/apache/http/conn/scheme/SchemeRegistry
    //   56: dup
    //   57: invokespecial 77	org/apache/http/conn/scheme/SchemeRegistry:<init>	()V
    //   60: astore_0
    //   61: aload_0
    //   62: new 79	org/apache/http/conn/scheme/Scheme
    //   65: dup
    //   66: ldc 81
    //   68: invokestatic 87	org/apache/http/conn/scheme/PlainSocketFactory:getSocketFactory	()Lorg/apache/http/conn/scheme/PlainSocketFactory;
    //   71: bipush 80
    //   73: invokespecial 90	org/apache/http/conn/scheme/Scheme:<init>	(Ljava/lang/String;Lorg/apache/http/conn/scheme/SocketFactory;I)V
    //   76: invokevirtual 94	org/apache/http/conn/scheme/SchemeRegistry:register	(Lorg/apache/http/conn/scheme/Scheme;)Lorg/apache/http/conn/scheme/Scheme;
    //   79: pop
    //   80: new 96	org/apache/http/impl/client/DefaultHttpClient
    //   83: dup
    //   84: new 98	org/apache/http/impl/conn/tsccm/ThreadSafeClientConnManager
    //   87: dup
    //   88: aload 8
    //   90: aload_0
    //   91: invokespecial 101	org/apache/http/impl/conn/tsccm/ThreadSafeClientConnManager:<init>	(Lorg/apache/http/params/HttpParams;Lorg/apache/http/conn/scheme/SchemeRegistry;)V
    //   94: aload 8
    //   96: invokespecial 104	org/apache/http/impl/client/DefaultHttpClient:<init>	(Lorg/apache/http/conn/ClientConnectionManager;Lorg/apache/http/params/HttpParams;)V
    //   99: areturn
    //   100: ldc 106
    //   102: invokestatic 112	android/net/Uri:parse	(Ljava/lang/String;)Landroid/net/Uri;
    //   105: astore 6
    //   107: aload_0
    //   108: invokevirtual 118	android/content/Context:getContentResolver	()Landroid/content/ContentResolver;
    //   111: astore_0
    //   112: aload_0
    //   113: aload 6
    //   115: aconst_null
    //   116: aconst_null
    //   117: aconst_null
    //   118: aconst_null
    //   119: invokevirtual 124	android/content/ContentResolver:query	(Landroid/net/Uri;[Ljava/lang/String;Ljava/lang/String;[Ljava/lang/String;Ljava/lang/String;)Landroid/database/Cursor;
    //   122: astore_0
    //   123: aload_0
    //   124: astore 5
    //   126: aload 5
    //   128: ifnonnull +15 -> 143
    //   131: iconst_m1
    //   132: istore_2
    //   133: aconst_null
    //   134: astore_0
    //   135: aload 5
    //   137: ifnonnull +447 -> 584
    //   140: goto -109 -> 31
    //   143: aload 5
    //   145: astore_0
    //   146: aload 5
    //   148: invokeinterface 129 1 0
    //   153: ifeq -22 -> 131
    //   156: aload 5
    //   158: astore_0
    //   159: aload 5
    //   161: aload 5
    //   163: ldc -125
    //   165: invokeinterface 135 2 0
    //   170: invokeinterface 139 2 0
    //   175: astore 6
    //   177: aload 6
    //   179: ifnonnull +6 -> 185
    //   182: goto +450 -> 632
    //   185: aload 5
    //   187: astore_0
    //   188: aload 6
    //   190: getstatic 145	java/util/Locale:US	Ljava/util/Locale;
    //   193: invokevirtual 149	java/lang/String:toLowerCase	(Ljava/util/Locale;)Ljava/lang/String;
    //   196: astore 6
    //   198: aload 5
    //   200: astore_0
    //   201: iconst_2
    //   202: anewarray 4	java/lang/Object
    //   205: dup
    //   206: iconst_0
    //   207: ldc -105
    //   209: aastore
    //   210: dup
    //   211: iconst_1
    //   212: aload 6
    //   214: aastore
    //   215: invokestatic 154	com/aps/t:a	([Ljava/lang/Object;)V
    //   218: goto +414 -> 632
    //   221: astore_0
    //   222: aconst_null
    //   223: astore 6
    //   225: aconst_null
    //   226: astore 7
    //   228: aconst_null
    //   229: astore_0
    //   230: aload_1
    //   231: invokevirtual 158	android/net/NetworkInfo:getExtraInfo	()Ljava/lang/String;
    //   234: astore 9
    //   236: aload 9
    //   238: ifnonnull +167 -> 405
    //   241: iload_3
    //   242: istore_2
    //   243: aload 5
    //   245: ifnonnull +349 -> 594
    //   248: goto -217 -> 31
    //   251: aload 5
    //   253: astore_0
    //   254: aload 6
    //   256: ldc -96
    //   258: invokevirtual 164	java/lang/String:contains	(Ljava/lang/CharSequence;)Z
    //   261: ifeq +376 -> 637
    //   264: aload 5
    //   266: astore_0
    //   267: invokestatic 167	com/aps/l:b	()Ljava/lang/String;
    //   270: astore 6
    //   272: aload 5
    //   274: astore_0
    //   275: aload 6
    //   277: invokestatic 172	android/text/TextUtils:isEmpty	(Ljava/lang/CharSequence;)Z
    //   280: ifeq +10 -> 290
    //   283: iconst_0
    //   284: istore_2
    //   285: aconst_null
    //   286: astore_0
    //   287: goto +362 -> 649
    //   290: aload 5
    //   292: astore_0
    //   293: aload 6
    //   295: ldc -82
    //   297: invokevirtual 178	java/lang/String:equals	(Ljava/lang/Object;)Z
    //   300: istore 4
    //   302: iload 4
    //   304: ifeq +10 -> 314
    //   307: iconst_0
    //   308: istore_2
    //   309: aconst_null
    //   310: astore_0
    //   311: goto +338 -> 649
    //   314: iconst_1
    //   315: istore_2
    //   316: aload 6
    //   318: astore_0
    //   319: goto +330 -> 649
    //   322: ldc -76
    //   324: astore_0
    //   325: goto +328 -> 653
    //   328: aload 5
    //   330: astore_0
    //   331: aload 6
    //   333: ldc -74
    //   335: invokevirtual 164	java/lang/String:contains	(Ljava/lang/CharSequence;)Z
    //   338: ifeq +304 -> 642
    //   341: aload 5
    //   343: astore_0
    //   344: invokestatic 167	com/aps/l:b	()Ljava/lang/String;
    //   347: astore 6
    //   349: aload 5
    //   351: astore_0
    //   352: aload 6
    //   354: invokestatic 172	android/text/TextUtils:isEmpty	(Ljava/lang/CharSequence;)Z
    //   357: ifeq +10 -> 367
    //   360: iconst_0
    //   361: istore_2
    //   362: aconst_null
    //   363: astore_0
    //   364: goto +295 -> 659
    //   367: aload 5
    //   369: astore_0
    //   370: aload 6
    //   372: ldc -82
    //   374: invokevirtual 178	java/lang/String:equals	(Ljava/lang/Object;)Z
    //   377: istore 4
    //   379: iload 4
    //   381: ifeq +10 -> 391
    //   384: iconst_0
    //   385: istore_2
    //   386: aconst_null
    //   387: astore_0
    //   388: goto +271 -> 659
    //   391: iconst_1
    //   392: istore_2
    //   393: aload 6
    //   395: astore_0
    //   396: goto +263 -> 659
    //   399: ldc -72
    //   401: astore_0
    //   402: goto +261 -> 663
    //   405: aload_1
    //   406: invokevirtual 158	android/net/NetworkInfo:getExtraInfo	()Ljava/lang/String;
    //   409: getstatic 145	java/util/Locale:US	Ljava/util/Locale;
    //   412: invokevirtual 149	java/lang/String:toLowerCase	(Ljava/util/Locale;)Ljava/lang/String;
    //   415: astore 9
    //   417: invokestatic 167	com/aps/l:b	()Ljava/lang/String;
    //   420: astore_1
    //   421: aload 9
    //   423: ldc -96
    //   425: invokevirtual 187	java/lang/String:indexOf	(Ljava/lang/String;)I
    //   428: iconst_m1
    //   429: if_icmpne +31 -> 460
    //   432: iload_3
    //   433: istore_2
    //   434: aload 9
    //   436: ldc -74
    //   438: invokevirtual 187	java/lang/String:indexOf	(Ljava/lang/String;)I
    //   441: iconst_m1
    //   442: if_icmpeq -199 -> 243
    //   445: aload_1
    //   446: invokestatic 172	android/text/TextUtils:isEmpty	(Ljava/lang/CharSequence;)Z
    //   449: ifeq +43 -> 492
    //   452: iconst_0
    //   453: istore_2
    //   454: aload 6
    //   456: astore_0
    //   457: goto +212 -> 669
    //   460: aload_1
    //   461: invokestatic 172	android/text/TextUtils:isEmpty	(Ljava/lang/CharSequence;)Z
    //   464: ifeq +11 -> 475
    //   467: iconst_0
    //   468: istore_2
    //   469: aload 7
    //   471: astore_0
    //   472: goto +207 -> 679
    //   475: aload_1
    //   476: ldc -82
    //   478: invokevirtual 178	java/lang/String:equals	(Ljava/lang/Object;)Z
    //   481: ifeq +208 -> 689
    //   484: iconst_0
    //   485: istore_2
    //   486: aload 7
    //   488: astore_0
    //   489: goto +190 -> 679
    //   492: aload_1
    //   493: ldc -82
    //   495: invokevirtual 178	java/lang/String:equals	(Ljava/lang/Object;)Z
    //   498: ifeq +202 -> 700
    //   501: iconst_0
    //   502: istore_2
    //   503: aload 6
    //   505: astore_0
    //   506: goto +163 -> 669
    //   509: ldc -76
    //   511: astore_0
    //   512: goto +161 -> 673
    //   515: astore_1
    //   516: aconst_null
    //   517: astore 5
    //   519: aload 5
    //   521: astore_0
    //   522: aload_1
    //   523: invokestatic 190	com/aps/t:a	(Ljava/lang/Throwable;)V
    //   526: iload_3
    //   527: istore_2
    //   528: aload 7
    //   530: astore_0
    //   531: aload 5
    //   533: ifnull -502 -> 31
    //   536: aload 5
    //   538: invokeinterface 193 1 0
    //   543: iload_3
    //   544: istore_2
    //   545: aload 7
    //   547: astore_0
    //   548: goto -517 -> 31
    //   551: astore_1
    //   552: aconst_null
    //   553: astore_0
    //   554: aload_0
    //   555: ifnonnull +49 -> 604
    //   558: aload_1
    //   559: athrow
    //   560: aload 8
    //   562: ldc -61
    //   564: new 197	org/apache/http/HttpHost
    //   567: dup
    //   568: aload_0
    //   569: iload_2
    //   570: ldc 81
    //   572: invokespecial 200	org/apache/http/HttpHost:<init>	(Ljava/lang/String;ILjava/lang/String;)V
    //   575: invokeinterface 206 3 0
    //   580: pop
    //   581: goto -542 -> 39
    //   584: aload 5
    //   586: invokeinterface 193 1 0
    //   591: goto -451 -> 140
    //   594: aload 5
    //   596: invokeinterface 193 1 0
    //   601: goto -353 -> 248
    //   604: aload_0
    //   605: invokeinterface 193 1 0
    //   610: goto -52 -> 558
    //   613: astore_1
    //   614: goto -60 -> 554
    //   617: astore_1
    //   618: aload 5
    //   620: astore_0
    //   621: goto -67 -> 554
    //   624: astore_1
    //   625: goto -106 -> 519
    //   628: astore_0
    //   629: goto -407 -> 222
    //   632: aload 6
    //   634: ifnonnull -383 -> 251
    //   637: aload 6
    //   639: ifnonnull -311 -> 328
    //   642: iconst_m1
    //   643: istore_2
    //   644: aconst_null
    //   645: astore_0
    //   646: goto -511 -> 135
    //   649: iload_2
    //   650: ifeq -328 -> 322
    //   653: bipush 80
    //   655: istore_2
    //   656: goto -521 -> 135
    //   659: iload_2
    //   660: ifeq -261 -> 399
    //   663: bipush 80
    //   665: istore_2
    //   666: goto -531 -> 135
    //   669: iload_2
    //   670: ifeq -161 -> 509
    //   673: bipush 80
    //   675: istore_2
    //   676: goto -433 -> 243
    //   679: iload_2
    //   680: ifeq +14 -> 694
    //   683: bipush 80
    //   685: istore_2
    //   686: goto -443 -> 243
    //   689: aload_1
    //   690: astore_0
    //   691: goto -12 -> 679
    //   694: ldc -76
    //   696: astore_0
    //   697: goto -14 -> 683
    //   700: aload_1
    //   701: astore_0
    //   702: iconst_1
    //   703: istore_2
    //   704: goto -35 -> 669
    // Local variable table:
    //   start	length	slot	name	signature
    //   0	707	0	paramContext	android.content.Context
    //   0	707	1	paramNetworkInfo	NetworkInfo
    //   3	701	2	i	int
    //   1	543	3	j	int
    //   300	80	4	bool	boolean
    //   5	614	5	localContext	android.content.Context
    //   105	533	6	localObject1	Object
    //   8	538	7	localObject2	Object
    //   17	544	8	localBasicHttpParams	org.apache.http.params.BasicHttpParams
    //   234	201	9	str	String
    // Exception table:
    //   from	to	target	type
    //   146	156	221	java/lang/SecurityException
    //   159	177	221	java/lang/SecurityException
    //   188	198	221	java/lang/SecurityException
    //   201	218	221	java/lang/SecurityException
    //   254	264	221	java/lang/SecurityException
    //   267	272	221	java/lang/SecurityException
    //   275	283	221	java/lang/SecurityException
    //   293	302	221	java/lang/SecurityException
    //   331	341	221	java/lang/SecurityException
    //   344	349	221	java/lang/SecurityException
    //   352	360	221	java/lang/SecurityException
    //   370	379	221	java/lang/SecurityException
    //   112	123	515	java/lang/Exception
    //   112	123	551	finally
    //   146	156	613	finally
    //   159	177	613	finally
    //   188	198	613	finally
    //   201	218	613	finally
    //   254	264	613	finally
    //   267	272	613	finally
    //   275	283	613	finally
    //   293	302	613	finally
    //   331	341	613	finally
    //   344	349	613	finally
    //   352	360	613	finally
    //   370	379	613	finally
    //   522	526	613	finally
    //   230	236	617	finally
    //   405	432	617	finally
    //   434	452	617	finally
    //   460	467	617	finally
    //   475	484	617	finally
    //   492	501	617	finally
    //   146	156	624	java/lang/Exception
    //   159	177	624	java/lang/Exception
    //   188	198	624	java/lang/Exception
    //   201	218	624	java/lang/Exception
    //   254	264	624	java/lang/Exception
    //   267	272	624	java/lang/Exception
    //   275	283	624	java/lang/Exception
    //   293	302	624	java/lang/Exception
    //   331	341	624	java/lang/Exception
    //   344	349	624	java/lang/Exception
    //   352	360	624	java/lang/Exception
    //   370	379	624	java/lang/Exception
    //   112	123	628	java/lang/SecurityException
  }
  
  private static boolean a(String paramString, int paramInt)
  {
    if (paramString == null) {}
    while ((paramString.length() <= 0) || (paramInt == -1)) {
      return false;
    }
    return true;
  }
  
  private static boolean a(HttpResponse paramHttpResponse)
  {
    paramHttpResponse = paramHttpResponse.getFirstHeader("Content-Encoding");
    if (paramHttpResponse == null) {}
    while (!paramHttpResponse.getValue().equalsIgnoreCase("gzip")) {
      return false;
    }
    return true;
  }
  
  public static String[] a(JSONObject paramJSONObject)
  {
    String[] arrayOfString = new String[5];
    arrayOfString[0] = null;
    arrayOfString[1] = null;
    arrayOfString[2] = null;
    arrayOfString[3] = null;
    arrayOfString[4] = null;
    if (paramJSONObject == null) {}
    while (c.j().length() == 0)
    {
      arrayOfString[0] = "false";
      return arrayOfString;
    }
    for (;;)
    {
      try
      {
        str1 = paramJSONObject.getString("key");
        str2 = paramJSONObject.getString("X-INFO");
        str3 = paramJSONObject.getString("X-BIZ");
        paramJSONObject = paramJSONObject.getString("User-Agent");
        boolean bool = TextUtils.isEmpty(str1);
        if (!bool) {
          continue;
        }
      }
      catch (JSONException paramJSONObject)
      {
        String str1;
        String str2;
        String str3;
        continue;
        if (!arrayOfString[0].equals("true")) {
          continue;
        }
      }
      if (arrayOfString[0] != null) {
        continue;
      }
      arrayOfString[0] = "true";
      return arrayOfString;
      if (!TextUtils.isEmpty(paramJSONObject))
      {
        arrayOfString[0] = "true";
        arrayOfString[1] = str1;
        arrayOfString[2] = str2;
        arrayOfString[3] = str3;
        arrayOfString[4] = paramJSONObject;
      }
    }
    return arrayOfString;
  }
  
  private static String b()
  {
    Object localObject = null;
    try
    {
      String str = Proxy.getDefaultHost();
      localObject = str;
    }
    catch (Throwable localThrowable)
    {
      for (;;)
      {
        localThrowable.printStackTrace();
      }
    }
    if (localObject != null) {
      return (String)localObject;
    }
    return "null";
  }
  
  /* Error */
  public String a(android.content.Context paramContext, String paramString1, byte[] paramArrayOfByte, String paramString2)
    throws com.amap.api.location.core.AMapLocException
  {
    // Byte code:
    //   0: aload_2
    //   1: invokestatic 172	android/text/TextUtils:isEmpty	(Ljava/lang/CharSequence;)Z
    //   4: ifeq +5 -> 9
    //   7: aconst_null
    //   8: areturn
    //   9: aload_3
    //   10: ifnull -3 -> 7
    //   13: aload_1
    //   14: invokestatic 279	com/aps/t:b	(Landroid/content/Context;)Landroid/net/NetworkInfo;
    //   17: astore 7
    //   19: aload 7
    //   21: invokestatic 281	com/aps/l:a	(Landroid/net/NetworkInfo;)I
    //   24: iconst_m1
    //   25: if_icmpeq +608 -> 633
    //   28: aconst_null
    //   29: astore 32
    //   31: aconst_null
    //   32: astore 11
    //   34: aconst_null
    //   35: astore 33
    //   37: aconst_null
    //   38: astore 35
    //   40: aconst_null
    //   41: astore 36
    //   43: aconst_null
    //   44: astore 34
    //   46: aconst_null
    //   47: astore 42
    //   49: aconst_null
    //   50: astore 41
    //   52: aconst_null
    //   53: astore 22
    //   55: aconst_null
    //   56: astore 29
    //   58: aconst_null
    //   59: astore 27
    //   61: aconst_null
    //   62: astore 30
    //   64: aconst_null
    //   65: astore 31
    //   67: aconst_null
    //   68: astore 28
    //   70: aconst_null
    //   71: astore 43
    //   73: aconst_null
    //   74: astore 40
    //   76: aconst_null
    //   77: astore 15
    //   79: aconst_null
    //   80: astore 24
    //   82: aconst_null
    //   83: astore 21
    //   85: aconst_null
    //   86: astore 25
    //   88: aconst_null
    //   89: astore 26
    //   91: aconst_null
    //   92: astore 23
    //   94: aconst_null
    //   95: astore 44
    //   97: aconst_null
    //   98: astore 39
    //   100: aconst_null
    //   101: astore 14
    //   103: aconst_null
    //   104: astore 18
    //   106: aconst_null
    //   107: astore 16
    //   109: aconst_null
    //   110: astore 19
    //   112: aconst_null
    //   113: astore 20
    //   115: aconst_null
    //   116: astore 17
    //   118: aconst_null
    //   119: astore 45
    //   121: aconst_null
    //   122: astore 38
    //   124: new 283	java/lang/StringBuffer
    //   127: dup
    //   128: invokespecial 284	java/lang/StringBuffer:<init>	()V
    //   131: astore 46
    //   133: ldc_w 286
    //   136: astore 37
    //   138: aload_1
    //   139: aload 7
    //   141: invokestatic 288	com/aps/l:a	(Landroid/content/Context;Landroid/net/NetworkInfo;)Lorg/apache/http/client/HttpClient;
    //   144: astore 7
    //   146: new 290	org/apache/http/client/methods/HttpPost
    //   149: dup
    //   150: aload_2
    //   151: invokespecial 293	org/apache/http/client/methods/HttpPost:<init>	(Ljava/lang/String;)V
    //   154: astore 8
    //   156: aload 45
    //   158: astore_2
    //   159: aload 44
    //   161: astore 9
    //   163: aload 43
    //   165: astore 10
    //   167: aload 42
    //   169: astore 11
    //   171: aload 8
    //   173: astore 12
    //   175: aload 7
    //   177: astore 13
    //   179: new 295	org/apache/http/entity/ByteArrayEntity
    //   182: dup
    //   183: aload_3
    //   184: invokespecial 298	org/apache/http/entity/ByteArrayEntity:<init>	([B)V
    //   187: astore_1
    //   188: aload 45
    //   190: astore_2
    //   191: aload 44
    //   193: astore 9
    //   195: aload 43
    //   197: astore 10
    //   199: aload 42
    //   201: astore 11
    //   203: aload 8
    //   205: astore 12
    //   207: aload 7
    //   209: astore 13
    //   211: aload 8
    //   213: ldc_w 300
    //   216: ldc_w 302
    //   219: invokevirtual 306	org/apache/http/client/methods/HttpPost:addHeader	(Ljava/lang/String;Ljava/lang/String;)V
    //   222: aload 45
    //   224: astore_2
    //   225: aload 44
    //   227: astore 9
    //   229: aload 43
    //   231: astore 10
    //   233: aload 42
    //   235: astore 11
    //   237: aload 8
    //   239: astore 12
    //   241: aload 7
    //   243: astore 13
    //   245: aload 8
    //   247: ldc -3
    //   249: ldc_w 308
    //   252: invokevirtual 306	org/apache/http/client/methods/HttpPost:addHeader	(Ljava/lang/String;Ljava/lang/String;)V
    //   255: aload 45
    //   257: astore_2
    //   258: aload 44
    //   260: astore 9
    //   262: aload 43
    //   264: astore 10
    //   266: aload 42
    //   268: astore 11
    //   270: aload 8
    //   272: astore 12
    //   274: aload 7
    //   276: astore 13
    //   278: aload 8
    //   280: ldc_w 310
    //   283: ldc -30
    //   285: invokevirtual 306	org/apache/http/client/methods/HttpPost:addHeader	(Ljava/lang/String;Ljava/lang/String;)V
    //   288: aload 45
    //   290: astore_2
    //   291: aload 44
    //   293: astore 9
    //   295: aload 43
    //   297: astore 10
    //   299: aload 42
    //   301: astore 11
    //   303: aload 8
    //   305: astore 12
    //   307: aload 7
    //   309: astore 13
    //   311: aload 8
    //   313: ldc_w 312
    //   316: ldc_w 314
    //   319: invokevirtual 306	org/apache/http/client/methods/HttpPost:addHeader	(Ljava/lang/String;Ljava/lang/String;)V
    //   322: aload 45
    //   324: astore_2
    //   325: aload 44
    //   327: astore 9
    //   329: aload 43
    //   331: astore 10
    //   333: aload 42
    //   335: astore 11
    //   337: aload 8
    //   339: astore 12
    //   341: aload 7
    //   343: astore 13
    //   345: aload 8
    //   347: ldc -7
    //   349: aconst_null
    //   350: invokestatic 317	com/amap/api/location/core/c:a	(Landroid/content/Context;)Lcom/amap/api/location/core/c;
    //   353: aload 4
    //   355: invokevirtual 319	com/amap/api/location/core/c:a	(Ljava/lang/String;)Ljava/lang/String;
    //   358: invokevirtual 306	org/apache/http/client/methods/HttpPost:addHeader	(Ljava/lang/String;Ljava/lang/String;)V
    //   361: aload 45
    //   363: astore_2
    //   364: aload 44
    //   366: astore 9
    //   368: aload 43
    //   370: astore 10
    //   372: aload 42
    //   374: astore 11
    //   376: aload 8
    //   378: astore 12
    //   380: aload 7
    //   382: astore 13
    //   384: aload 8
    //   386: ldc_w 321
    //   389: ldc_w 323
    //   392: invokevirtual 306	org/apache/http/client/methods/HttpPost:addHeader	(Ljava/lang/String;Ljava/lang/String;)V
    //   395: aload 45
    //   397: astore_2
    //   398: aload 44
    //   400: astore 9
    //   402: aload 43
    //   404: astore 10
    //   406: aload 42
    //   408: astore 11
    //   410: aload 8
    //   412: astore 12
    //   414: aload 7
    //   416: astore 13
    //   418: aload 8
    //   420: ldc -14
    //   422: invokestatic 325	com/amap/api/location/core/c:a	()Ljava/lang/String;
    //   425: invokevirtual 306	org/apache/http/client/methods/HttpPost:addHeader	(Ljava/lang/String;Ljava/lang/String;)V
    //   428: aload 45
    //   430: astore_2
    //   431: aload 44
    //   433: astore 9
    //   435: aload 43
    //   437: astore 10
    //   439: aload 42
    //   441: astore 11
    //   443: aload 8
    //   445: astore 12
    //   447: aload 7
    //   449: astore 13
    //   451: aload 46
    //   453: iconst_0
    //   454: aload 46
    //   456: invokevirtual 326	java/lang/StringBuffer:length	()I
    //   459: invokevirtual 330	java/lang/StringBuffer:delete	(II)Ljava/lang/StringBuffer;
    //   462: pop
    //   463: aload 45
    //   465: astore_2
    //   466: aload 44
    //   468: astore 9
    //   470: aload 43
    //   472: astore 10
    //   474: aload 42
    //   476: astore 11
    //   478: aload 8
    //   480: astore 12
    //   482: aload 7
    //   484: astore 13
    //   486: aload 8
    //   488: aload_1
    //   489: invokevirtual 334	org/apache/http/client/methods/HttpPost:setEntity	(Lorg/apache/http/HttpEntity;)V
    //   492: aload 45
    //   494: astore_2
    //   495: aload 44
    //   497: astore 9
    //   499: aload 43
    //   501: astore 10
    //   503: aload 42
    //   505: astore 11
    //   507: aload 8
    //   509: astore 12
    //   511: aload 7
    //   513: astore 13
    //   515: aload 7
    //   517: aload 8
    //   519: invokeinterface 340 2 0
    //   524: astore 4
    //   526: aload 45
    //   528: astore_2
    //   529: aload 44
    //   531: astore 9
    //   533: aload 43
    //   535: astore 10
    //   537: aload 42
    //   539: astore 11
    //   541: aload 8
    //   543: astore 12
    //   545: aload 7
    //   547: astore 13
    //   549: aload 4
    //   551: invokeinterface 344 1 0
    //   556: invokeinterface 349 1 0
    //   561: istore 5
    //   563: iload 5
    //   565: sipush 200
    //   568: if_icmpeq +67 -> 635
    //   571: iload 5
    //   573: sipush 404
    //   576: if_icmpeq +409 -> 985
    //   579: aload 41
    //   581: astore 4
    //   583: aload 40
    //   585: astore 9
    //   587: aload 39
    //   589: astore_3
    //   590: aload 38
    //   592: astore_2
    //   593: aload 37
    //   595: astore_1
    //   596: aload 8
    //   598: ifnonnull +586 -> 1184
    //   601: aload 7
    //   603: ifnonnull +589 -> 1192
    //   606: aload 9
    //   608: ifnonnull +599 -> 1207
    //   611: aload 4
    //   613: ifnonnull +607 -> 1220
    //   616: aload_3
    //   617: ifnonnull +621 -> 1238
    //   620: aload_2
    //   621: ifnonnull +632 -> 1253
    //   624: aload_1
    //   625: invokestatic 172	android/text/TextUtils:isEmpty	(Ljava/lang/CharSequence;)Z
    //   628: ifne +554 -> 1182
    //   631: aload_1
    //   632: areturn
    //   633: aconst_null
    //   634: areturn
    //   635: aload 45
    //   637: astore_2
    //   638: aload 44
    //   640: astore 9
    //   642: aload 43
    //   644: astore 10
    //   646: aload 42
    //   648: astore 11
    //   650: aload 8
    //   652: astore 12
    //   654: aload 7
    //   656: astore 13
    //   658: aload 4
    //   660: invokeinterface 353 1 0
    //   665: invokeinterface 359 1 0
    //   670: astore_1
    //   671: aload 4
    //   673: invokeinterface 353 1 0
    //   678: invokeinterface 363 1 0
    //   683: invokeinterface 224 1 0
    //   688: astore_3
    //   689: ldc_w 286
    //   692: astore_2
    //   693: aload_3
    //   694: ldc_w 365
    //   697: invokevirtual 187	java/lang/String:indexOf	(Ljava/lang/String;)I
    //   700: istore 5
    //   702: iload 5
    //   704: iconst_m1
    //   705: if_icmpne +103 -> 808
    //   708: aload_2
    //   709: invokestatic 172	android/text/TextUtils:isEmpty	(Ljava/lang/CharSequence;)Z
    //   712: ifne +1308 -> 2020
    //   715: aload_2
    //   716: astore_3
    //   717: aload 4
    //   719: invokestatic 367	com/aps/l:a	(Lorg/apache/http/HttpResponse;)Z
    //   722: istore 6
    //   724: iload 6
    //   726: ifne +95 -> 821
    //   729: aconst_null
    //   730: astore_2
    //   731: aload_2
    //   732: ifnonnull +179 -> 911
    //   735: new 369	java/io/InputStreamReader
    //   738: dup
    //   739: aload_1
    //   740: aload_3
    //   741: invokespecial 372	java/io/InputStreamReader:<init>	(Ljava/io/InputStream;Ljava/lang/String;)V
    //   744: astore_3
    //   745: new 374	java/io/BufferedReader
    //   748: dup
    //   749: aload_3
    //   750: sipush 2048
    //   753: invokespecial 377	java/io/BufferedReader:<init>	(Ljava/io/Reader;I)V
    //   756: astore 4
    //   758: aload 4
    //   760: invokevirtual 380	java/io/BufferedReader:readLine	()Ljava/lang/String;
    //   763: astore 9
    //   765: aload 9
    //   767: ifnonnull +180 -> 947
    //   770: aload 46
    //   772: invokevirtual 383	java/lang/StringBuffer:toString	()Ljava/lang/String;
    //   775: astore 11
    //   777: aload 46
    //   779: iconst_0
    //   780: aload 46
    //   782: invokevirtual 326	java/lang/StringBuffer:length	()I
    //   785: invokevirtual 330	java/lang/StringBuffer:delete	(II)Ljava/lang/StringBuffer;
    //   788: pop
    //   789: aload_2
    //   790: astore 9
    //   792: aload_1
    //   793: astore 10
    //   795: aload 11
    //   797: astore_1
    //   798: aload 4
    //   800: astore_2
    //   801: aload 10
    //   803: astore 4
    //   805: goto -209 -> 596
    //   808: aload_3
    //   809: iload 5
    //   811: bipush 8
    //   813: iadd
    //   814: invokevirtual 386	java/lang/String:substring	(I)Ljava/lang/String;
    //   817: astore_2
    //   818: goto -110 -> 708
    //   821: new 388	java/util/zip/GZIPInputStream
    //   824: dup
    //   825: aload_1
    //   826: invokespecial 391	java/util/zip/GZIPInputStream:<init>	(Ljava/io/InputStream;)V
    //   829: astore_2
    //   830: goto -99 -> 731
    //   833: astore_2
    //   834: aload_1
    //   835: astore_3
    //   836: aload 8
    //   838: astore_1
    //   839: aload 7
    //   841: astore_2
    //   842: aload 22
    //   844: astore 10
    //   846: aload 15
    //   848: astore 9
    //   850: aload 14
    //   852: astore 4
    //   854: new 268	com/amap/api/location/core/AMapLocException
    //   857: dup
    //   858: ldc_w 393
    //   861: invokespecial 394	com/amap/api/location/core/AMapLocException:<init>	(Ljava/lang/String;)V
    //   864: athrow
    //   865: astore 11
    //   867: aload_2
    //   868: astore 7
    //   870: aload_1
    //   871: astore 8
    //   873: aload_3
    //   874: astore_2
    //   875: aload 4
    //   877: astore_3
    //   878: aload 11
    //   880: astore_1
    //   881: aload 8
    //   883: ifnonnull +385 -> 1268
    //   886: aload 7
    //   888: ifnonnull +388 -> 1276
    //   891: aload 10
    //   893: ifnonnull +398 -> 1291
    //   896: aload_2
    //   897: ifnonnull +407 -> 1304
    //   900: aload 9
    //   902: ifnonnull +417 -> 1319
    //   905: aload_3
    //   906: ifnonnull +429 -> 1335
    //   909: aload_1
    //   910: athrow
    //   911: new 369	java/io/InputStreamReader
    //   914: dup
    //   915: aload_2
    //   916: aload_3
    //   917: invokespecial 372	java/io/InputStreamReader:<init>	(Ljava/io/InputStream;Ljava/lang/String;)V
    //   920: astore_3
    //   921: goto -176 -> 745
    //   924: astore_3
    //   925: aload_1
    //   926: astore_3
    //   927: aload 8
    //   929: astore_1
    //   930: aload 14
    //   932: astore 4
    //   934: aload 15
    //   936: astore 9
    //   938: aload_2
    //   939: astore 10
    //   941: aload 7
    //   943: astore_2
    //   944: goto -90 -> 854
    //   947: aload 46
    //   949: aload 9
    //   951: invokevirtual 398	java/lang/StringBuffer:append	(Ljava/lang/String;)Ljava/lang/StringBuffer;
    //   954: pop
    //   955: goto -197 -> 758
    //   958: astore 9
    //   960: aload 8
    //   962: astore 9
    //   964: aload_1
    //   965: astore 8
    //   967: aload 9
    //   969: astore_1
    //   970: aload_3
    //   971: astore 9
    //   973: aload_2
    //   974: astore 10
    //   976: aload 8
    //   978: astore_3
    //   979: aload 7
    //   981: astore_2
    //   982: goto -128 -> 854
    //   985: aload 45
    //   987: astore_2
    //   988: aload 44
    //   990: astore 9
    //   992: aload 43
    //   994: astore 10
    //   996: aload 42
    //   998: astore 11
    //   1000: aload 8
    //   1002: astore 12
    //   1004: aload 7
    //   1006: astore 13
    //   1008: new 268	com/amap/api/location/core/AMapLocException
    //   1011: dup
    //   1012: ldc_w 400
    //   1015: invokespecial 394	com/amap/api/location/core/AMapLocException:<init>	(Ljava/lang/String;)V
    //   1018: athrow
    //   1019: astore_1
    //   1020: aload 8
    //   1022: astore_1
    //   1023: aload 7
    //   1025: astore_2
    //   1026: aload 14
    //   1028: astore 4
    //   1030: aload 15
    //   1032: astore 9
    //   1034: aload 22
    //   1036: astore 10
    //   1038: aload 32
    //   1040: astore_3
    //   1041: goto -187 -> 854
    //   1044: astore_1
    //   1045: aconst_null
    //   1046: astore 7
    //   1048: aconst_null
    //   1049: astore 8
    //   1051: aload 33
    //   1053: astore 11
    //   1055: aload 27
    //   1057: astore 10
    //   1059: aload 21
    //   1061: astore 9
    //   1063: aload 16
    //   1065: astore_2
    //   1066: aload 8
    //   1068: astore 12
    //   1070: aload 7
    //   1072: astore 13
    //   1074: new 268	com/amap/api/location/core/AMapLocException
    //   1077: dup
    //   1078: ldc_w 402
    //   1081: invokespecial 394	com/amap/api/location/core/AMapLocException:<init>	(Ljava/lang/String;)V
    //   1084: athrow
    //   1085: aload 8
    //   1087: astore 12
    //   1089: aload 7
    //   1091: astore 13
    //   1093: new 268	com/amap/api/location/core/AMapLocException
    //   1096: dup
    //   1097: ldc_w 404
    //   1100: invokespecial 394	com/amap/api/location/core/AMapLocException:<init>	(Ljava/lang/String;)V
    //   1103: athrow
    //   1104: aload 8
    //   1106: astore 12
    //   1108: aload 7
    //   1110: astore 13
    //   1112: new 268	com/amap/api/location/core/AMapLocException
    //   1115: dup
    //   1116: ldc_w 406
    //   1119: invokespecial 394	com/amap/api/location/core/AMapLocException:<init>	(Ljava/lang/String;)V
    //   1122: athrow
    //   1123: aload 15
    //   1125: astore_2
    //   1126: aload 14
    //   1128: astore 9
    //   1130: aload 4
    //   1132: astore 10
    //   1134: aload_3
    //   1135: astore 11
    //   1137: aload 8
    //   1139: astore 12
    //   1141: aload 7
    //   1143: astore 13
    //   1145: aload_1
    //   1146: invokevirtual 265	java/lang/Throwable:printStackTrace	()V
    //   1149: aload 15
    //   1151: astore_2
    //   1152: aload 14
    //   1154: astore 9
    //   1156: aload 4
    //   1158: astore 10
    //   1160: aload_3
    //   1161: astore 11
    //   1163: aload 8
    //   1165: astore 12
    //   1167: aload 7
    //   1169: astore 13
    //   1171: new 268	com/amap/api/location/core/AMapLocException
    //   1174: dup
    //   1175: ldc_w 408
    //   1178: invokespecial 394	com/amap/api/location/core/AMapLocException:<init>	(Ljava/lang/String;)V
    //   1181: athrow
    //   1182: aconst_null
    //   1183: areturn
    //   1184: aload 8
    //   1186: invokevirtual 411	org/apache/http/client/methods/HttpPost:abort	()V
    //   1189: goto -588 -> 601
    //   1192: aload 7
    //   1194: invokeinterface 415 1 0
    //   1199: invokeinterface 420 1 0
    //   1204: goto -598 -> 606
    //   1207: aload 9
    //   1209: invokevirtual 421	java/util/zip/GZIPInputStream:close	()V
    //   1212: goto -601 -> 611
    //   1215: astore 7
    //   1217: goto -606 -> 611
    //   1220: aload 4
    //   1222: invokevirtual 424	java/io/InputStream:close	()V
    //   1225: goto -609 -> 616
    //   1228: astore 4
    //   1230: aload 4
    //   1232: invokevirtual 265	java/lang/Throwable:printStackTrace	()V
    //   1235: goto -619 -> 616
    //   1238: aload_3
    //   1239: invokevirtual 425	java/io/InputStreamReader:close	()V
    //   1242: goto -622 -> 620
    //   1245: astore_3
    //   1246: aload_3
    //   1247: invokevirtual 265	java/lang/Throwable:printStackTrace	()V
    //   1250: goto -630 -> 620
    //   1253: aload_2
    //   1254: invokevirtual 426	java/io/BufferedReader:close	()V
    //   1257: goto -633 -> 624
    //   1260: astore_2
    //   1261: aload_2
    //   1262: invokevirtual 265	java/lang/Throwable:printStackTrace	()V
    //   1265: goto -641 -> 624
    //   1268: aload 8
    //   1270: invokevirtual 411	org/apache/http/client/methods/HttpPost:abort	()V
    //   1273: goto -387 -> 886
    //   1276: aload 7
    //   1278: invokeinterface 415 1 0
    //   1283: invokeinterface 420 1 0
    //   1288: goto -397 -> 891
    //   1291: aload 10
    //   1293: invokevirtual 421	java/util/zip/GZIPInputStream:close	()V
    //   1296: goto -400 -> 896
    //   1299: astore 4
    //   1301: goto -405 -> 896
    //   1304: aload_2
    //   1305: invokevirtual 424	java/io/InputStream:close	()V
    //   1308: goto -408 -> 900
    //   1311: astore_2
    //   1312: aload_2
    //   1313: invokevirtual 265	java/lang/Throwable:printStackTrace	()V
    //   1316: goto -416 -> 900
    //   1319: aload 9
    //   1321: invokevirtual 425	java/io/InputStreamReader:close	()V
    //   1324: goto -419 -> 905
    //   1327: astore_2
    //   1328: aload_2
    //   1329: invokevirtual 265	java/lang/Throwable:printStackTrace	()V
    //   1332: goto -427 -> 905
    //   1335: aload_3
    //   1336: invokevirtual 426	java/io/BufferedReader:close	()V
    //   1339: goto -430 -> 909
    //   1342: astore_2
    //   1343: aload_2
    //   1344: invokevirtual 265	java/lang/Throwable:printStackTrace	()V
    //   1347: goto -438 -> 909
    //   1350: astore_1
    //   1351: aconst_null
    //   1352: astore 7
    //   1354: aconst_null
    //   1355: astore 8
    //   1357: aload 18
    //   1359: astore_3
    //   1360: aload 24
    //   1362: astore 9
    //   1364: aload 29
    //   1366: astore 10
    //   1368: aload 11
    //   1370: astore_2
    //   1371: goto -490 -> 881
    //   1374: astore_1
    //   1375: aconst_null
    //   1376: astore 8
    //   1378: aload 18
    //   1380: astore_3
    //   1381: aload 24
    //   1383: astore 9
    //   1385: aload 29
    //   1387: astore 10
    //   1389: aload 11
    //   1391: astore_2
    //   1392: goto -511 -> 881
    //   1395: astore_3
    //   1396: aload_1
    //   1397: astore_2
    //   1398: aload_3
    //   1399: astore_1
    //   1400: aload 18
    //   1402: astore_3
    //   1403: aload 24
    //   1405: astore 9
    //   1407: aload 29
    //   1409: astore 10
    //   1411: goto -530 -> 881
    //   1414: astore_3
    //   1415: aload_1
    //   1416: astore 4
    //   1418: aload_3
    //   1419: astore_1
    //   1420: aload 18
    //   1422: astore_3
    //   1423: aload 24
    //   1425: astore 9
    //   1427: aload_2
    //   1428: astore 10
    //   1430: aload 4
    //   1432: astore_2
    //   1433: goto -552 -> 881
    //   1436: astore 10
    //   1438: aload_3
    //   1439: astore 9
    //   1441: aload_1
    //   1442: astore 4
    //   1444: aload 10
    //   1446: astore_1
    //   1447: aload 18
    //   1449: astore_3
    //   1450: aload_2
    //   1451: astore 10
    //   1453: aload 4
    //   1455: astore_2
    //   1456: goto -575 -> 881
    //   1459: astore 10
    //   1461: aload_3
    //   1462: astore 9
    //   1464: aload_1
    //   1465: astore 11
    //   1467: aload 10
    //   1469: astore_1
    //   1470: aload 4
    //   1472: astore_3
    //   1473: aload_2
    //   1474: astore 10
    //   1476: aload 11
    //   1478: astore_2
    //   1479: goto -598 -> 881
    //   1482: astore_1
    //   1483: aconst_null
    //   1484: astore 8
    //   1486: aload 17
    //   1488: astore 15
    //   1490: aload 23
    //   1492: astore 14
    //   1494: aload 28
    //   1496: astore 4
    //   1498: aload 34
    //   1500: astore_3
    //   1501: goto -378 -> 1123
    //   1504: astore_1
    //   1505: aload 17
    //   1507: astore 15
    //   1509: aload 23
    //   1511: astore 14
    //   1513: aload 28
    //   1515: astore 4
    //   1517: aload 34
    //   1519: astore_3
    //   1520: goto -397 -> 1123
    //   1523: astore_2
    //   1524: aload_1
    //   1525: astore_3
    //   1526: aload_2
    //   1527: astore_1
    //   1528: aload 17
    //   1530: astore 15
    //   1532: aload 23
    //   1534: astore 14
    //   1536: aload 28
    //   1538: astore 4
    //   1540: goto -417 -> 1123
    //   1543: astore 4
    //   1545: aload_1
    //   1546: astore_3
    //   1547: aload 4
    //   1549: astore_1
    //   1550: aload 17
    //   1552: astore 15
    //   1554: aload 23
    //   1556: astore 14
    //   1558: aload_2
    //   1559: astore 4
    //   1561: goto -438 -> 1123
    //   1564: astore 4
    //   1566: aload_1
    //   1567: astore 9
    //   1569: aload 4
    //   1571: astore_1
    //   1572: aload 17
    //   1574: astore 15
    //   1576: aload_3
    //   1577: astore 14
    //   1579: aload_2
    //   1580: astore 4
    //   1582: aload 9
    //   1584: astore_3
    //   1585: goto -462 -> 1123
    //   1588: astore 10
    //   1590: aload_1
    //   1591: astore 9
    //   1593: aload 10
    //   1595: astore_1
    //   1596: aload 4
    //   1598: astore 15
    //   1600: aload_3
    //   1601: astore 14
    //   1603: aload_2
    //   1604: astore 4
    //   1606: aload 9
    //   1608: astore_3
    //   1609: goto -486 -> 1123
    //   1612: astore_1
    //   1613: aconst_null
    //   1614: astore 8
    //   1616: aload 20
    //   1618: astore_2
    //   1619: aload 26
    //   1621: astore 9
    //   1623: aload 31
    //   1625: astore 10
    //   1627: aload 36
    //   1629: astore 11
    //   1631: goto -527 -> 1104
    //   1634: astore_1
    //   1635: aload 20
    //   1637: astore_2
    //   1638: aload 26
    //   1640: astore 9
    //   1642: aload 31
    //   1644: astore 10
    //   1646: aload 36
    //   1648: astore 11
    //   1650: goto -546 -> 1104
    //   1653: astore_2
    //   1654: aload 20
    //   1656: astore_2
    //   1657: aload 26
    //   1659: astore 9
    //   1661: aload 31
    //   1663: astore 10
    //   1665: aload_1
    //   1666: astore 11
    //   1668: goto -564 -> 1104
    //   1671: astore_3
    //   1672: aload_2
    //   1673: astore 10
    //   1675: aload 20
    //   1677: astore_2
    //   1678: aload 26
    //   1680: astore 9
    //   1682: aload_1
    //   1683: astore 11
    //   1685: goto -581 -> 1104
    //   1688: astore 4
    //   1690: aload_2
    //   1691: astore 10
    //   1693: aload 20
    //   1695: astore_2
    //   1696: aload_3
    //   1697: astore 9
    //   1699: aload_1
    //   1700: astore 11
    //   1702: goto -598 -> 1104
    //   1705: astore 9
    //   1707: aload_2
    //   1708: astore 10
    //   1710: aload 4
    //   1712: astore_2
    //   1713: aload_3
    //   1714: astore 9
    //   1716: aload_1
    //   1717: astore 11
    //   1719: goto -615 -> 1104
    //   1722: astore_1
    //   1723: aconst_null
    //   1724: astore 8
    //   1726: aload 19
    //   1728: astore_2
    //   1729: aload 25
    //   1731: astore 9
    //   1733: aload 30
    //   1735: astore 10
    //   1737: aload 35
    //   1739: astore 11
    //   1741: goto -656 -> 1085
    //   1744: astore_1
    //   1745: aload 19
    //   1747: astore_2
    //   1748: aload 25
    //   1750: astore 9
    //   1752: aload 30
    //   1754: astore 10
    //   1756: aload 35
    //   1758: astore 11
    //   1760: goto -675 -> 1085
    //   1763: astore_2
    //   1764: aload 19
    //   1766: astore_2
    //   1767: aload 25
    //   1769: astore 9
    //   1771: aload 30
    //   1773: astore 10
    //   1775: aload_1
    //   1776: astore 11
    //   1778: goto -693 -> 1085
    //   1781: astore_3
    //   1782: aload_2
    //   1783: astore 10
    //   1785: aload 19
    //   1787: astore_2
    //   1788: aload 25
    //   1790: astore 9
    //   1792: aload_1
    //   1793: astore 11
    //   1795: goto -710 -> 1085
    //   1798: astore 4
    //   1800: aload_2
    //   1801: astore 10
    //   1803: aload 19
    //   1805: astore_2
    //   1806: aload_3
    //   1807: astore 9
    //   1809: aload_1
    //   1810: astore 11
    //   1812: goto -727 -> 1085
    //   1815: astore 9
    //   1817: aload_2
    //   1818: astore 10
    //   1820: aload 4
    //   1822: astore_2
    //   1823: aload_3
    //   1824: astore 9
    //   1826: aload_1
    //   1827: astore 11
    //   1829: goto -744 -> 1085
    //   1832: astore_1
    //   1833: aconst_null
    //   1834: astore 8
    //   1836: aload 16
    //   1838: astore_2
    //   1839: aload 21
    //   1841: astore 9
    //   1843: aload 27
    //   1845: astore 10
    //   1847: aload 33
    //   1849: astore 11
    //   1851: goto -785 -> 1066
    //   1854: astore_1
    //   1855: aload 16
    //   1857: astore_2
    //   1858: aload 21
    //   1860: astore 9
    //   1862: aload 27
    //   1864: astore 10
    //   1866: aload 33
    //   1868: astore 11
    //   1870: goto -804 -> 1066
    //   1873: astore_2
    //   1874: aload 16
    //   1876: astore_2
    //   1877: aload 21
    //   1879: astore 9
    //   1881: aload 27
    //   1883: astore 10
    //   1885: aload_1
    //   1886: astore 11
    //   1888: goto -822 -> 1066
    //   1891: astore_3
    //   1892: aload_2
    //   1893: astore 10
    //   1895: aload 16
    //   1897: astore_2
    //   1898: aload 21
    //   1900: astore 9
    //   1902: aload_1
    //   1903: astore 11
    //   1905: goto -839 -> 1066
    //   1908: astore 4
    //   1910: aload_2
    //   1911: astore 10
    //   1913: aload 16
    //   1915: astore_2
    //   1916: aload_3
    //   1917: astore 9
    //   1919: aload_1
    //   1920: astore 11
    //   1922: goto -856 -> 1066
    //   1925: astore 9
    //   1927: aload_2
    //   1928: astore 10
    //   1930: aload 4
    //   1932: astore_2
    //   1933: aload_3
    //   1934: astore 9
    //   1936: aload_1
    //   1937: astore 11
    //   1939: goto -873 -> 1066
    //   1942: astore_1
    //   1943: aconst_null
    //   1944: astore_1
    //   1945: aconst_null
    //   1946: astore_2
    //   1947: aload 14
    //   1949: astore 4
    //   1951: aload 15
    //   1953: astore 9
    //   1955: aload 22
    //   1957: astore 10
    //   1959: aload 32
    //   1961: astore_3
    //   1962: goto -1108 -> 854
    //   1965: astore_1
    //   1966: aconst_null
    //   1967: astore_1
    //   1968: aload 7
    //   1970: astore_2
    //   1971: aload 14
    //   1973: astore 4
    //   1975: aload 15
    //   1977: astore 9
    //   1979: aload 22
    //   1981: astore 10
    //   1983: aload 32
    //   1985: astore_3
    //   1986: goto -1132 -> 854
    //   1989: astore 4
    //   1991: aload 8
    //   1993: astore 4
    //   1995: aload_1
    //   1996: astore 8
    //   1998: aload 4
    //   2000: astore_1
    //   2001: aload 14
    //   2003: astore 4
    //   2005: aload_3
    //   2006: astore 9
    //   2008: aload_2
    //   2009: astore 10
    //   2011: aload 8
    //   2013: astore_3
    //   2014: aload 7
    //   2016: astore_2
    //   2017: goto -1163 -> 854
    //   2020: ldc_w 428
    //   2023: astore_3
    //   2024: goto -1307 -> 717
    //   2027: astore_1
    //   2028: aload_2
    //   2029: astore_3
    //   2030: aload 11
    //   2032: astore_2
    //   2033: aload 12
    //   2035: astore 8
    //   2037: aload 13
    //   2039: astore 7
    //   2041: goto -1160 -> 881
    //   2044: astore_1
    //   2045: aconst_null
    //   2046: astore 7
    //   2048: aconst_null
    //   2049: astore 8
    //   2051: aload 19
    //   2053: astore_2
    //   2054: aload 25
    //   2056: astore 9
    //   2058: aload 30
    //   2060: astore 10
    //   2062: aload 35
    //   2064: astore 11
    //   2066: goto -981 -> 1085
    //   2069: astore_1
    //   2070: aconst_null
    //   2071: astore 7
    //   2073: aconst_null
    //   2074: astore 8
    //   2076: aload 20
    //   2078: astore_2
    //   2079: aload 26
    //   2081: astore 9
    //   2083: aload 31
    //   2085: astore 10
    //   2087: aload 36
    //   2089: astore 11
    //   2091: goto -987 -> 1104
    //   2094: astore_1
    //   2095: aconst_null
    //   2096: astore 7
    //   2098: aconst_null
    //   2099: astore 8
    //   2101: aload 17
    //   2103: astore 15
    //   2105: aload 23
    //   2107: astore 14
    //   2109: aload 28
    //   2111: astore 4
    //   2113: aload 34
    //   2115: astore_3
    //   2116: goto -993 -> 1123
    // Local variable table:
    //   start	length	slot	name	signature
    //   0	2119	0	this	l
    //   0	2119	1	paramContext	android.content.Context
    //   0	2119	2	paramString1	String
    //   0	2119	3	paramArrayOfByte	byte[]
    //   0	2119	4	paramString2	String
    //   561	253	5	i	int
    //   722	3	6	bool	boolean
    //   17	1176	7	localObject1	Object
    //   1215	62	7	localThrowable1	Throwable
    //   1352	745	7	localObject2	Object
    //   154	1946	8	localObject3	Object
    //   161	789	9	localObject4	Object
    //   958	1	9	localUnknownHostException	java.net.UnknownHostException
    //   962	736	9	localObject5	Object
    //   1705	1	9	localConnectTimeoutException	org.apache.http.conn.ConnectTimeoutException
    //   1714	94	9	localObject6	Object
    //   1815	1	9	localSocketTimeoutException	java.net.SocketTimeoutException
    //   1824	94	9	localObject7	Object
    //   1925	1	9	localSocketException	java.net.SocketException
    //   1934	148	9	localObject8	Object
    //   165	1264	10	localObject9	Object
    //   1436	9	10	localObject10	Object
    //   1451	1	10	str1	String
    //   1459	9	10	localObject11	Object
    //   1474	1	10	str2	String
    //   1588	6	10	localThrowable2	Throwable
    //   1625	461	10	localObject12	Object
    //   32	764	11	localObject13	Object
    //   865	14	11	localObject14	Object
    //   998	1092	11	localObject15	Object
    //   173	1861	12	localObject16	Object
    //   177	1861	13	localObject17	Object
    //   101	2007	14	localObject18	Object
    //   77	2027	15	localObject19	Object
    //   107	1807	16	localObject20	Object
    //   116	1986	17	localObject21	Object
    //   104	1344	18	localObject22	Object
    //   110	1942	19	localObject23	Object
    //   113	1964	20	localObject24	Object
    //   83	1816	21	localObject25	Object
    //   53	1927	22	localObject26	Object
    //   92	2014	23	localObject27	Object
    //   80	1344	24	localObject28	Object
    //   86	1969	25	localObject29	Object
    //   89	1991	26	localObject30	Object
    //   59	1823	27	localObject31	Object
    //   68	2042	28	localObject32	Object
    //   56	1352	29	localObject33	Object
    //   62	1997	30	localObject34	Object
    //   65	2019	31	localObject35	Object
    //   29	1955	32	localObject36	Object
    //   35	1832	33	localObject37	Object
    //   44	2070	34	localObject38	Object
    //   38	2025	35	localObject39	Object
    //   41	2047	36	localObject40	Object
    //   136	458	37	str3	String
    //   122	469	38	localObject41	Object
    //   98	490	39	localObject42	Object
    //   74	510	40	localObject43	Object
    //   50	530	41	localObject44	Object
    //   47	950	42	localObject45	Object
    //   71	922	43	localObject46	Object
    //   95	894	44	localObject47	Object
    //   119	867	45	localObject48	Object
    //   131	817	46	localStringBuffer	StringBuffer
    // Exception table:
    //   from	to	target	type
    //   671	689	833	java/net/UnknownHostException
    //   693	702	833	java/net/UnknownHostException
    //   708	715	833	java/net/UnknownHostException
    //   717	724	833	java/net/UnknownHostException
    //   808	818	833	java/net/UnknownHostException
    //   821	830	833	java/net/UnknownHostException
    //   854	865	865	finally
    //   735	745	924	java/net/UnknownHostException
    //   911	921	924	java/net/UnknownHostException
    //   758	765	958	java/net/UnknownHostException
    //   770	789	958	java/net/UnknownHostException
    //   947	955	958	java/net/UnknownHostException
    //   179	188	1019	java/net/UnknownHostException
    //   211	222	1019	java/net/UnknownHostException
    //   245	255	1019	java/net/UnknownHostException
    //   278	288	1019	java/net/UnknownHostException
    //   311	322	1019	java/net/UnknownHostException
    //   345	361	1019	java/net/UnknownHostException
    //   384	395	1019	java/net/UnknownHostException
    //   418	428	1019	java/net/UnknownHostException
    //   451	463	1019	java/net/UnknownHostException
    //   486	492	1019	java/net/UnknownHostException
    //   515	526	1019	java/net/UnknownHostException
    //   549	563	1019	java/net/UnknownHostException
    //   658	671	1019	java/net/UnknownHostException
    //   1008	1019	1019	java/net/UnknownHostException
    //   138	146	1044	java/net/SocketException
    //   1207	1212	1215	java/lang/Throwable
    //   1220	1225	1228	java/lang/Throwable
    //   1238	1242	1245	java/lang/Throwable
    //   1253	1257	1260	java/lang/Throwable
    //   1291	1296	1299	java/lang/Throwable
    //   1304	1308	1311	java/lang/Throwable
    //   1319	1324	1327	java/lang/Throwable
    //   1335	1339	1342	java/lang/Throwable
    //   138	146	1350	finally
    //   146	156	1374	finally
    //   671	689	1395	finally
    //   693	702	1395	finally
    //   708	715	1395	finally
    //   717	724	1395	finally
    //   808	818	1395	finally
    //   821	830	1395	finally
    //   735	745	1414	finally
    //   911	921	1414	finally
    //   745	758	1436	finally
    //   758	765	1459	finally
    //   770	789	1459	finally
    //   947	955	1459	finally
    //   146	156	1482	java/lang/Throwable
    //   179	188	1504	java/lang/Throwable
    //   211	222	1504	java/lang/Throwable
    //   245	255	1504	java/lang/Throwable
    //   278	288	1504	java/lang/Throwable
    //   311	322	1504	java/lang/Throwable
    //   345	361	1504	java/lang/Throwable
    //   384	395	1504	java/lang/Throwable
    //   418	428	1504	java/lang/Throwable
    //   451	463	1504	java/lang/Throwable
    //   486	492	1504	java/lang/Throwable
    //   515	526	1504	java/lang/Throwable
    //   549	563	1504	java/lang/Throwable
    //   658	671	1504	java/lang/Throwable
    //   1008	1019	1504	java/lang/Throwable
    //   671	689	1523	java/lang/Throwable
    //   693	702	1523	java/lang/Throwable
    //   708	715	1523	java/lang/Throwable
    //   717	724	1523	java/lang/Throwable
    //   808	818	1523	java/lang/Throwable
    //   821	830	1523	java/lang/Throwable
    //   735	745	1543	java/lang/Throwable
    //   911	921	1543	java/lang/Throwable
    //   745	758	1564	java/lang/Throwable
    //   758	765	1588	java/lang/Throwable
    //   770	789	1588	java/lang/Throwable
    //   947	955	1588	java/lang/Throwable
    //   146	156	1612	org/apache/http/conn/ConnectTimeoutException
    //   179	188	1634	org/apache/http/conn/ConnectTimeoutException
    //   211	222	1634	org/apache/http/conn/ConnectTimeoutException
    //   245	255	1634	org/apache/http/conn/ConnectTimeoutException
    //   278	288	1634	org/apache/http/conn/ConnectTimeoutException
    //   311	322	1634	org/apache/http/conn/ConnectTimeoutException
    //   345	361	1634	org/apache/http/conn/ConnectTimeoutException
    //   384	395	1634	org/apache/http/conn/ConnectTimeoutException
    //   418	428	1634	org/apache/http/conn/ConnectTimeoutException
    //   451	463	1634	org/apache/http/conn/ConnectTimeoutException
    //   486	492	1634	org/apache/http/conn/ConnectTimeoutException
    //   515	526	1634	org/apache/http/conn/ConnectTimeoutException
    //   549	563	1634	org/apache/http/conn/ConnectTimeoutException
    //   658	671	1634	org/apache/http/conn/ConnectTimeoutException
    //   1008	1019	1634	org/apache/http/conn/ConnectTimeoutException
    //   671	689	1653	org/apache/http/conn/ConnectTimeoutException
    //   693	702	1653	org/apache/http/conn/ConnectTimeoutException
    //   708	715	1653	org/apache/http/conn/ConnectTimeoutException
    //   717	724	1653	org/apache/http/conn/ConnectTimeoutException
    //   808	818	1653	org/apache/http/conn/ConnectTimeoutException
    //   821	830	1653	org/apache/http/conn/ConnectTimeoutException
    //   735	745	1671	org/apache/http/conn/ConnectTimeoutException
    //   911	921	1671	org/apache/http/conn/ConnectTimeoutException
    //   745	758	1688	org/apache/http/conn/ConnectTimeoutException
    //   758	765	1705	org/apache/http/conn/ConnectTimeoutException
    //   770	789	1705	org/apache/http/conn/ConnectTimeoutException
    //   947	955	1705	org/apache/http/conn/ConnectTimeoutException
    //   146	156	1722	java/net/SocketTimeoutException
    //   179	188	1744	java/net/SocketTimeoutException
    //   211	222	1744	java/net/SocketTimeoutException
    //   245	255	1744	java/net/SocketTimeoutException
    //   278	288	1744	java/net/SocketTimeoutException
    //   311	322	1744	java/net/SocketTimeoutException
    //   345	361	1744	java/net/SocketTimeoutException
    //   384	395	1744	java/net/SocketTimeoutException
    //   418	428	1744	java/net/SocketTimeoutException
    //   451	463	1744	java/net/SocketTimeoutException
    //   486	492	1744	java/net/SocketTimeoutException
    //   515	526	1744	java/net/SocketTimeoutException
    //   549	563	1744	java/net/SocketTimeoutException
    //   658	671	1744	java/net/SocketTimeoutException
    //   1008	1019	1744	java/net/SocketTimeoutException
    //   671	689	1763	java/net/SocketTimeoutException
    //   693	702	1763	java/net/SocketTimeoutException
    //   708	715	1763	java/net/SocketTimeoutException
    //   717	724	1763	java/net/SocketTimeoutException
    //   808	818	1763	java/net/SocketTimeoutException
    //   821	830	1763	java/net/SocketTimeoutException
    //   735	745	1781	java/net/SocketTimeoutException
    //   911	921	1781	java/net/SocketTimeoutException
    //   745	758	1798	java/net/SocketTimeoutException
    //   758	765	1815	java/net/SocketTimeoutException
    //   770	789	1815	java/net/SocketTimeoutException
    //   947	955	1815	java/net/SocketTimeoutException
    //   146	156	1832	java/net/SocketException
    //   179	188	1854	java/net/SocketException
    //   211	222	1854	java/net/SocketException
    //   245	255	1854	java/net/SocketException
    //   278	288	1854	java/net/SocketException
    //   311	322	1854	java/net/SocketException
    //   345	361	1854	java/net/SocketException
    //   384	395	1854	java/net/SocketException
    //   418	428	1854	java/net/SocketException
    //   451	463	1854	java/net/SocketException
    //   486	492	1854	java/net/SocketException
    //   515	526	1854	java/net/SocketException
    //   549	563	1854	java/net/SocketException
    //   658	671	1854	java/net/SocketException
    //   1008	1019	1854	java/net/SocketException
    //   671	689	1873	java/net/SocketException
    //   693	702	1873	java/net/SocketException
    //   708	715	1873	java/net/SocketException
    //   717	724	1873	java/net/SocketException
    //   808	818	1873	java/net/SocketException
    //   821	830	1873	java/net/SocketException
    //   735	745	1891	java/net/SocketException
    //   911	921	1891	java/net/SocketException
    //   745	758	1908	java/net/SocketException
    //   758	765	1925	java/net/SocketException
    //   770	789	1925	java/net/SocketException
    //   947	955	1925	java/net/SocketException
    //   138	146	1942	java/net/UnknownHostException
    //   146	156	1965	java/net/UnknownHostException
    //   745	758	1989	java/net/UnknownHostException
    //   179	188	2027	finally
    //   211	222	2027	finally
    //   245	255	2027	finally
    //   278	288	2027	finally
    //   311	322	2027	finally
    //   345	361	2027	finally
    //   384	395	2027	finally
    //   418	428	2027	finally
    //   451	463	2027	finally
    //   486	492	2027	finally
    //   515	526	2027	finally
    //   549	563	2027	finally
    //   658	671	2027	finally
    //   1008	1019	2027	finally
    //   1074	1085	2027	finally
    //   1093	1104	2027	finally
    //   1112	1123	2027	finally
    //   1145	1149	2027	finally
    //   1171	1182	2027	finally
    //   138	146	2044	java/net/SocketTimeoutException
    //   138	146	2069	org/apache/http/conn/ConnectTimeoutException
    //   138	146	2094	java/lang/Throwable
  }
  
  /* Error */
  public String a(byte[] paramArrayOfByte, android.content.Context paramContext)
    throws java.lang.Exception
  {
    // Byte code:
    //   0: aload_2
    //   1: invokestatic 279	com/aps/t:b	(Landroid/content/Context;)Landroid/net/NetworkInfo;
    //   4: astore 20
    //   6: aload 20
    //   8: invokestatic 281	com/aps/l:a	(Landroid/net/NetworkInfo;)I
    //   11: iconst_m1
    //   12: if_icmpeq +117 -> 129
    //   15: aconst_null
    //   16: astore 8
    //   18: new 283	java/lang/StringBuffer
    //   21: dup
    //   22: invokespecial 284	java/lang/StringBuffer:<init>	()V
    //   25: astore 14
    //   27: new 283	java/lang/StringBuffer
    //   30: dup
    //   31: invokespecial 284	java/lang/StringBuffer:<init>	()V
    //   34: astore 21
    //   36: aload 21
    //   38: ldc_w 431
    //   41: invokevirtual 398	java/lang/StringBuffer:append	(Ljava/lang/String;)Ljava/lang/StringBuffer;
    //   44: pop
    //   45: aload 21
    //   47: ldc_w 433
    //   50: invokevirtual 398	java/lang/StringBuffer:append	(Ljava/lang/String;)Ljava/lang/StringBuffer;
    //   53: getstatic 436	com/aps/f:a	Ljava/lang/String;
    //   56: invokevirtual 398	java/lang/StringBuffer:append	(Ljava/lang/String;)Ljava/lang/StringBuffer;
    //   59: pop
    //   60: aload 21
    //   62: ldc_w 438
    //   65: invokevirtual 398	java/lang/StringBuffer:append	(Ljava/lang/String;)Ljava/lang/StringBuffer;
    //   68: getstatic 440	com/aps/f:b	Ljava/lang/String;
    //   71: invokevirtual 398	java/lang/StringBuffer:append	(Ljava/lang/String;)Ljava/lang/StringBuffer;
    //   74: pop
    //   75: iconst_0
    //   76: istore 4
    //   78: iconst_0
    //   79: istore_3
    //   80: aconst_null
    //   81: astore 12
    //   83: aconst_null
    //   84: astore 11
    //   86: aconst_null
    //   87: astore 7
    //   89: aconst_null
    //   90: astore 6
    //   92: ldc_w 286
    //   95: astore 9
    //   97: iload 4
    //   99: iconst_1
    //   100: if_icmplt +31 -> 131
    //   103: aload 21
    //   105: iconst_0
    //   106: aload 21
    //   108: invokevirtual 326	java/lang/StringBuffer:length	()I
    //   111: invokevirtual 330	java/lang/StringBuffer:delete	(II)Ljava/lang/StringBuffer;
    //   114: pop
    //   115: aload 9
    //   117: ldc_w 286
    //   120: invokevirtual 178	java/lang/String:equals	(Ljava/lang/Object;)Z
    //   123: ifne +544 -> 667
    //   126: aload 9
    //   128: areturn
    //   129: aconst_null
    //   130: areturn
    //   131: iload_3
    //   132: ifne -29 -> 103
    //   135: aload_2
    //   136: aload 20
    //   138: invokestatic 288	com/aps/l:a	(Landroid/content/Context;Landroid/net/NetworkInfo;)Lorg/apache/http/client/HttpClient;
    //   141: astore 10
    //   143: aload 10
    //   145: astore 8
    //   147: new 290	org/apache/http/client/methods/HttpPost
    //   150: dup
    //   151: aload 21
    //   153: invokevirtual 383	java/lang/StringBuffer:toString	()Ljava/lang/String;
    //   156: invokespecial 293	org/apache/http/client/methods/HttpPost:<init>	(Ljava/lang/String;)V
    //   159: astore 10
    //   161: aload 14
    //   163: iconst_0
    //   164: aload 14
    //   166: invokevirtual 326	java/lang/StringBuffer:length	()I
    //   169: invokevirtual 330	java/lang/StringBuffer:delete	(II)Ljava/lang/StringBuffer;
    //   172: pop
    //   173: aload 14
    //   175: ldc_w 442
    //   178: invokevirtual 398	java/lang/StringBuffer:append	(Ljava/lang/String;)Ljava/lang/StringBuffer;
    //   181: pop
    //   182: aload 14
    //   184: ldc_w 428
    //   187: invokevirtual 398	java/lang/StringBuffer:append	(Ljava/lang/String;)Ljava/lang/StringBuffer;
    //   190: pop
    //   191: aload 14
    //   193: iconst_0
    //   194: aload 14
    //   196: invokevirtual 326	java/lang/StringBuffer:length	()I
    //   199: invokevirtual 330	java/lang/StringBuffer:delete	(II)Ljava/lang/StringBuffer;
    //   202: pop
    //   203: aload 10
    //   205: ldc_w 444
    //   208: ldc_w 323
    //   211: invokevirtual 306	org/apache/http/client/methods/HttpPost:addHeader	(Ljava/lang/String;Ljava/lang/String;)V
    //   214: new 295	org/apache/http/entity/ByteArrayEntity
    //   217: dup
    //   218: aload_1
    //   219: invokestatic 447	com/aps/t:a	([B)[B
    //   222: invokespecial 298	org/apache/http/entity/ByteArrayEntity:<init>	([B)V
    //   225: astore 6
    //   227: aload 6
    //   229: ldc_w 449
    //   232: invokevirtual 452	org/apache/http/entity/ByteArrayEntity:setContentType	(Ljava/lang/String;)V
    //   235: aload 10
    //   237: aload 6
    //   239: invokevirtual 334	org/apache/http/client/methods/HttpPost:setEntity	(Lorg/apache/http/HttpEntity;)V
    //   242: aload 8
    //   244: aload 10
    //   246: invokeinterface 340 2 0
    //   251: astore 6
    //   253: aload 6
    //   255: invokeinterface 344 1 0
    //   260: invokeinterface 349 1 0
    //   265: sipush 200
    //   268: if_icmpeq +14 -> 282
    //   271: aload 9
    //   273: astore 6
    //   275: aload 7
    //   277: astore 9
    //   279: goto +1502 -> 1781
    //   282: aload 6
    //   284: invokeinterface 353 1 0
    //   289: invokeinterface 359 1 0
    //   294: astore 6
    //   296: new 369	java/io/InputStreamReader
    //   299: dup
    //   300: aload 6
    //   302: ldc_w 428
    //   305: invokespecial 372	java/io/InputStreamReader:<init>	(Ljava/io/InputStream;Ljava/lang/String;)V
    //   308: astore 7
    //   310: new 374	java/io/BufferedReader
    //   313: dup
    //   314: aload 7
    //   316: sipush 2048
    //   319: invokespecial 377	java/io/BufferedReader:<init>	(Ljava/io/Reader;I)V
    //   322: astore 11
    //   324: aload 11
    //   326: invokevirtual 380	java/io/BufferedReader:readLine	()Ljava/lang/String;
    //   329: astore 12
    //   331: aload 12
    //   333: ifnonnull +50 -> 383
    //   336: aload 14
    //   338: invokevirtual 383	java/lang/StringBuffer:toString	()Ljava/lang/String;
    //   341: astore 12
    //   343: aload 14
    //   345: iconst_0
    //   346: aload 14
    //   348: invokevirtual 326	java/lang/StringBuffer:length	()I
    //   351: invokevirtual 330	java/lang/StringBuffer:delete	(II)Ljava/lang/StringBuffer;
    //   354: pop
    //   355: aconst_null
    //   356: astore 14
    //   358: iconst_1
    //   359: istore_3
    //   360: aload 12
    //   362: astore 13
    //   364: aload 11
    //   366: astore 12
    //   368: aload 7
    //   370: astore 11
    //   372: aload 6
    //   374: astore 9
    //   376: aload 13
    //   378: astore 6
    //   380: goto +1401 -> 1781
    //   383: aload 14
    //   385: aload 12
    //   387: invokevirtual 398	java/lang/StringBuffer:append	(Ljava/lang/String;)Ljava/lang/StringBuffer;
    //   390: pop
    //   391: goto -67 -> 324
    //   394: astore 12
    //   396: aload 11
    //   398: astore 12
    //   400: aload 7
    //   402: astore 11
    //   404: aload 6
    //   406: astore 13
    //   408: aload 9
    //   410: astore 6
    //   412: aload 8
    //   414: astore 7
    //   416: aload 10
    //   418: astore 8
    //   420: aload 13
    //   422: astore 9
    //   424: aload 12
    //   426: astore 10
    //   428: aload 8
    //   430: ifnonnull +301 -> 731
    //   433: aload 8
    //   435: astore 15
    //   437: aload 7
    //   439: ifnonnull +303 -> 742
    //   442: aload 7
    //   444: astore 16
    //   446: aload 9
    //   448: ifnonnull +312 -> 760
    //   451: aload 9
    //   453: astore 17
    //   455: aload 11
    //   457: ifnonnull +314 -> 771
    //   460: aload 11
    //   462: astore 18
    //   464: iload_3
    //   465: istore 5
    //   467: aload 14
    //   469: astore 19
    //   471: aload 10
    //   473: astore 12
    //   475: aload 18
    //   477: astore 11
    //   479: aload 17
    //   481: astore 9
    //   483: aload 15
    //   485: astore 8
    //   487: aload 16
    //   489: astore 7
    //   491: aload 6
    //   493: astore 13
    //   495: aload 10
    //   497: ifnull +1336 -> 1833
    //   500: aload 10
    //   502: invokevirtual 426	java/io/BufferedReader:close	()V
    //   505: aconst_null
    //   506: astore 12
    //   508: iload_3
    //   509: istore 5
    //   511: aload 14
    //   513: astore 19
    //   515: aload 18
    //   517: astore 11
    //   519: aload 17
    //   521: astore 9
    //   523: aload 15
    //   525: astore 8
    //   527: aload 16
    //   529: astore 7
    //   531: aload 6
    //   533: astore 13
    //   535: goto +1298 -> 1833
    //   538: astore 10
    //   540: aload 6
    //   542: astore 10
    //   544: aload 9
    //   546: astore 13
    //   548: aload 12
    //   550: astore 6
    //   552: aload 10
    //   554: ifnonnull +228 -> 782
    //   557: aload 10
    //   559: astore 12
    //   561: aload 8
    //   563: ifnonnull +230 -> 793
    //   566: aload 8
    //   568: astore 10
    //   570: aload 7
    //   572: ifnonnull +239 -> 811
    //   575: aload 7
    //   577: astore 8
    //   579: aload 11
    //   581: ifnonnull +241 -> 822
    //   584: aload 11
    //   586: astore 9
    //   588: aload 6
    //   590: ifnonnull +243 -> 833
    //   593: aload 13
    //   595: astore 11
    //   597: aload 12
    //   599: astore 7
    //   601: aload 11
    //   603: astore 13
    //   605: iload_3
    //   606: istore 5
    //   608: aload 14
    //   610: astore 19
    //   612: aload 6
    //   614: astore 12
    //   616: aload 9
    //   618: astore 11
    //   620: aload 8
    //   622: astore 9
    //   624: aload 7
    //   626: astore 8
    //   628: aload 10
    //   630: astore 7
    //   632: goto +1201 -> 1833
    //   635: astore_1
    //   636: aload 6
    //   638: astore 10
    //   640: aload 10
    //   642: ifnonnull +524 -> 1166
    //   645: aload 8
    //   647: ifnonnull +527 -> 1174
    //   650: aload 7
    //   652: ifnonnull +537 -> 1189
    //   655: aload 11
    //   657: ifnonnull +540 -> 1197
    //   660: aload 12
    //   662: ifnonnull +543 -> 1205
    //   665: aload_1
    //   666: athrow
    //   667: aconst_null
    //   668: areturn
    //   669: aload 10
    //   671: invokevirtual 411	org/apache/http/client/methods/HttpPost:abort	()V
    //   674: aconst_null
    //   675: astore 7
    //   677: goto +1113 -> 1790
    //   680: aload 8
    //   682: invokeinterface 415 1 0
    //   687: invokeinterface 420 1 0
    //   692: aconst_null
    //   693: astore 8
    //   695: goto +1100 -> 1795
    //   698: aload 9
    //   700: invokevirtual 424	java/io/InputStream:close	()V
    //   703: aconst_null
    //   704: astore 9
    //   706: goto +1094 -> 1800
    //   709: aload 11
    //   711: invokevirtual 425	java/io/InputStreamReader:close	()V
    //   714: aconst_null
    //   715: astore 11
    //   717: goto +1088 -> 1805
    //   720: aload 12
    //   722: invokevirtual 426	java/io/BufferedReader:close	()V
    //   725: aconst_null
    //   726: astore 12
    //   728: goto +1082 -> 1810
    //   731: aload 8
    //   733: invokevirtual 411	org/apache/http/client/methods/HttpPost:abort	()V
    //   736: aconst_null
    //   737: astore 15
    //   739: goto -302 -> 437
    //   742: aload 7
    //   744: invokeinterface 415 1 0
    //   749: invokeinterface 420 1 0
    //   754: aconst_null
    //   755: astore 16
    //   757: goto -311 -> 446
    //   760: aload 9
    //   762: invokevirtual 424	java/io/InputStream:close	()V
    //   765: aconst_null
    //   766: astore 17
    //   768: goto -313 -> 455
    //   771: aload 11
    //   773: invokevirtual 425	java/io/InputStreamReader:close	()V
    //   776: aconst_null
    //   777: astore 18
    //   779: goto -315 -> 464
    //   782: aload 10
    //   784: invokevirtual 411	org/apache/http/client/methods/HttpPost:abort	()V
    //   787: aconst_null
    //   788: astore 12
    //   790: goto -229 -> 561
    //   793: aload 8
    //   795: invokeinterface 415 1 0
    //   800: invokeinterface 420 1 0
    //   805: aconst_null
    //   806: astore 10
    //   808: goto -238 -> 570
    //   811: aload 7
    //   813: invokevirtual 424	java/io/InputStream:close	()V
    //   816: aconst_null
    //   817: astore 8
    //   819: goto -240 -> 579
    //   822: aload 11
    //   824: invokevirtual 425	java/io/InputStreamReader:close	()V
    //   827: aconst_null
    //   828: astore 9
    //   830: goto -242 -> 588
    //   833: aload 6
    //   835: invokevirtual 426	java/io/BufferedReader:close	()V
    //   838: aconst_null
    //   839: astore 6
    //   841: aload 12
    //   843: astore 7
    //   845: aload 13
    //   847: astore 11
    //   849: goto -248 -> 601
    //   852: astore 10
    //   854: aload 6
    //   856: astore 10
    //   858: aload 9
    //   860: astore 13
    //   862: aload 10
    //   864: ifnonnull +94 -> 958
    //   867: aload 10
    //   869: astore 15
    //   871: aload 8
    //   873: ifnonnull +96 -> 969
    //   876: aload 8
    //   878: astore 16
    //   880: aload 7
    //   882: ifnonnull +105 -> 987
    //   885: aload 7
    //   887: astore 17
    //   889: aload 11
    //   891: ifnonnull +107 -> 998
    //   894: aload 11
    //   896: astore 18
    //   898: aload 12
    //   900: astore 6
    //   902: aload 18
    //   904: astore 9
    //   906: aload 17
    //   908: astore 8
    //   910: aload 15
    //   912: astore 7
    //   914: aload 13
    //   916: astore 11
    //   918: aload 16
    //   920: astore 10
    //   922: aload 12
    //   924: ifnull -323 -> 601
    //   927: aload 12
    //   929: invokevirtual 426	java/io/BufferedReader:close	()V
    //   932: aconst_null
    //   933: astore 6
    //   935: aload 18
    //   937: astore 9
    //   939: aload 17
    //   941: astore 8
    //   943: aload 15
    //   945: astore 7
    //   947: aload 13
    //   949: astore 11
    //   951: aload 16
    //   953: astore 10
    //   955: goto -354 -> 601
    //   958: aload 10
    //   960: invokevirtual 411	org/apache/http/client/methods/HttpPost:abort	()V
    //   963: aconst_null
    //   964: astore 15
    //   966: goto -95 -> 871
    //   969: aload 8
    //   971: invokeinterface 415 1 0
    //   976: invokeinterface 420 1 0
    //   981: aconst_null
    //   982: astore 16
    //   984: goto -104 -> 880
    //   987: aload 7
    //   989: invokevirtual 424	java/io/InputStream:close	()V
    //   992: aconst_null
    //   993: astore 17
    //   995: goto -106 -> 889
    //   998: aload 11
    //   1000: invokevirtual 425	java/io/InputStreamReader:close	()V
    //   1003: aconst_null
    //   1004: astore 18
    //   1006: goto -108 -> 898
    //   1009: astore 10
    //   1011: aload 6
    //   1013: astore 10
    //   1015: aload 9
    //   1017: astore 13
    //   1019: aload 10
    //   1021: ifnonnull +94 -> 1115
    //   1024: aload 10
    //   1026: astore 15
    //   1028: aload 8
    //   1030: ifnonnull +96 -> 1126
    //   1033: aload 8
    //   1035: astore 16
    //   1037: aload 7
    //   1039: ifnonnull +105 -> 1144
    //   1042: aload 7
    //   1044: astore 17
    //   1046: aload 11
    //   1048: ifnonnull +107 -> 1155
    //   1051: aload 11
    //   1053: astore 18
    //   1055: aload 12
    //   1057: astore 6
    //   1059: aload 18
    //   1061: astore 9
    //   1063: aload 17
    //   1065: astore 8
    //   1067: aload 15
    //   1069: astore 7
    //   1071: aload 13
    //   1073: astore 11
    //   1075: aload 16
    //   1077: astore 10
    //   1079: aload 12
    //   1081: ifnull -480 -> 601
    //   1084: aload 12
    //   1086: invokevirtual 426	java/io/BufferedReader:close	()V
    //   1089: aconst_null
    //   1090: astore 6
    //   1092: aload 18
    //   1094: astore 9
    //   1096: aload 17
    //   1098: astore 8
    //   1100: aload 15
    //   1102: astore 7
    //   1104: aload 13
    //   1106: astore 11
    //   1108: aload 16
    //   1110: astore 10
    //   1112: goto -511 -> 601
    //   1115: aload 10
    //   1117: invokevirtual 411	org/apache/http/client/methods/HttpPost:abort	()V
    //   1120: aconst_null
    //   1121: astore 15
    //   1123: goto -95 -> 1028
    //   1126: aload 8
    //   1128: invokeinterface 415 1 0
    //   1133: invokeinterface 420 1 0
    //   1138: aconst_null
    //   1139: astore 16
    //   1141: goto -104 -> 1037
    //   1144: aload 7
    //   1146: invokevirtual 424	java/io/InputStream:close	()V
    //   1149: aconst_null
    //   1150: astore 17
    //   1152: goto -106 -> 1046
    //   1155: aload 11
    //   1157: invokevirtual 425	java/io/InputStreamReader:close	()V
    //   1160: aconst_null
    //   1161: astore 18
    //   1163: goto -108 -> 1055
    //   1166: aload 10
    //   1168: invokevirtual 411	org/apache/http/client/methods/HttpPost:abort	()V
    //   1171: goto -526 -> 645
    //   1174: aload 8
    //   1176: invokeinterface 415 1 0
    //   1181: invokeinterface 420 1 0
    //   1186: goto -536 -> 650
    //   1189: aload 7
    //   1191: invokevirtual 424	java/io/InputStream:close	()V
    //   1194: goto -539 -> 655
    //   1197: aload 11
    //   1199: invokevirtual 425	java/io/InputStreamReader:close	()V
    //   1202: goto -542 -> 660
    //   1205: aload 12
    //   1207: invokevirtual 426	java/io/BufferedReader:close	()V
    //   1210: goto -545 -> 665
    //   1213: astore_1
    //   1214: aload 6
    //   1216: astore 10
    //   1218: goto -578 -> 640
    //   1221: astore_1
    //   1222: goto -582 -> 640
    //   1225: astore_1
    //   1226: aload 6
    //   1228: astore 7
    //   1230: goto -590 -> 640
    //   1233: astore_1
    //   1234: aload 7
    //   1236: astore 11
    //   1238: aload 6
    //   1240: astore 7
    //   1242: goto -602 -> 640
    //   1245: astore_1
    //   1246: aload 11
    //   1248: astore 12
    //   1250: aload 7
    //   1252: astore 11
    //   1254: aload 6
    //   1256: astore 7
    //   1258: goto -618 -> 640
    //   1261: astore 10
    //   1263: aload 9
    //   1265: astore 13
    //   1267: aload 6
    //   1269: astore 10
    //   1271: goto -252 -> 1019
    //   1274: astore 6
    //   1276: aload 9
    //   1278: astore 13
    //   1280: goto -261 -> 1019
    //   1283: astore 7
    //   1285: aload 6
    //   1287: astore 7
    //   1289: aload 9
    //   1291: astore 13
    //   1293: goto -274 -> 1019
    //   1296: astore 11
    //   1298: aload 7
    //   1300: astore 11
    //   1302: aload 6
    //   1304: astore 7
    //   1306: aload 9
    //   1308: astore 13
    //   1310: goto -291 -> 1019
    //   1313: astore 12
    //   1315: aload 11
    //   1317: astore 12
    //   1319: aload 7
    //   1321: astore 11
    //   1323: aload 6
    //   1325: astore 7
    //   1327: aload 9
    //   1329: astore 13
    //   1331: goto -312 -> 1019
    //   1334: astore 9
    //   1336: aload 12
    //   1338: astore 13
    //   1340: aload 11
    //   1342: astore 12
    //   1344: aload 7
    //   1346: astore 11
    //   1348: aload 6
    //   1350: astore 7
    //   1352: goto -333 -> 1019
    //   1355: astore 10
    //   1357: aload 9
    //   1359: astore 13
    //   1361: aload 6
    //   1363: astore 10
    //   1365: goto -503 -> 862
    //   1368: astore 6
    //   1370: aload 9
    //   1372: astore 13
    //   1374: goto -512 -> 862
    //   1377: astore 7
    //   1379: aload 6
    //   1381: astore 7
    //   1383: aload 9
    //   1385: astore 13
    //   1387: goto -525 -> 862
    //   1390: astore 11
    //   1392: aload 7
    //   1394: astore 11
    //   1396: aload 6
    //   1398: astore 7
    //   1400: aload 9
    //   1402: astore 13
    //   1404: goto -542 -> 862
    //   1407: astore 12
    //   1409: aload 11
    //   1411: astore 12
    //   1413: aload 7
    //   1415: astore 11
    //   1417: aload 6
    //   1419: astore 7
    //   1421: aload 9
    //   1423: astore 13
    //   1425: goto -563 -> 862
    //   1428: astore 9
    //   1430: aload 12
    //   1432: astore 13
    //   1434: aload 11
    //   1436: astore 12
    //   1438: aload 7
    //   1440: astore 11
    //   1442: aload 6
    //   1444: astore 7
    //   1446: goto -584 -> 862
    //   1449: astore 10
    //   1451: aload 6
    //   1453: astore 10
    //   1455: aload 12
    //   1457: astore 6
    //   1459: aload 9
    //   1461: astore 13
    //   1463: goto -911 -> 552
    //   1466: astore 6
    //   1468: aload 12
    //   1470: astore 6
    //   1472: aload 9
    //   1474: astore 13
    //   1476: goto -924 -> 552
    //   1479: astore 7
    //   1481: aload 6
    //   1483: astore 7
    //   1485: aload 12
    //   1487: astore 6
    //   1489: aload 9
    //   1491: astore 13
    //   1493: goto -941 -> 552
    //   1496: astore 11
    //   1498: aload 6
    //   1500: astore 13
    //   1502: aload 12
    //   1504: astore 6
    //   1506: aload 7
    //   1508: astore 11
    //   1510: aload 13
    //   1512: astore 7
    //   1514: aload 9
    //   1516: astore 13
    //   1518: goto -966 -> 552
    //   1521: astore 12
    //   1523: aload 6
    //   1525: astore 12
    //   1527: aload 11
    //   1529: astore 6
    //   1531: aload 7
    //   1533: astore 11
    //   1535: aload 12
    //   1537: astore 7
    //   1539: aload 9
    //   1541: astore 13
    //   1543: goto -991 -> 552
    //   1546: astore 9
    //   1548: aload 6
    //   1550: astore 9
    //   1552: aload 11
    //   1554: astore 6
    //   1556: aload 7
    //   1558: astore 11
    //   1560: aload 9
    //   1562: astore 7
    //   1564: aload 12
    //   1566: astore 13
    //   1568: goto -1016 -> 552
    //   1571: astore 10
    //   1573: aload 9
    //   1575: astore 13
    //   1577: aload 8
    //   1579: astore 15
    //   1581: aload 12
    //   1583: astore 10
    //   1585: aload 7
    //   1587: astore 9
    //   1589: aload 6
    //   1591: astore 8
    //   1593: aload 15
    //   1595: astore 7
    //   1597: aload 13
    //   1599: astore 6
    //   1601: goto -1173 -> 428
    //   1604: astore 10
    //   1606: aload 9
    //   1608: astore 13
    //   1610: aload 8
    //   1612: astore 15
    //   1614: aload 12
    //   1616: astore 10
    //   1618: aload 7
    //   1620: astore 9
    //   1622: aload 6
    //   1624: astore 8
    //   1626: aload 15
    //   1628: astore 7
    //   1630: aload 13
    //   1632: astore 6
    //   1634: goto -1206 -> 428
    //   1637: astore 6
    //   1639: aload 10
    //   1641: astore 13
    //   1643: aload 9
    //   1645: astore 6
    //   1647: aload 8
    //   1649: astore 15
    //   1651: aload 12
    //   1653: astore 10
    //   1655: aload 7
    //   1657: astore 9
    //   1659: aload 13
    //   1661: astore 8
    //   1663: aload 15
    //   1665: astore 7
    //   1667: goto -1239 -> 428
    //   1670: astore 7
    //   1672: aload 6
    //   1674: astore 7
    //   1676: aload 10
    //   1678: astore 13
    //   1680: aload 9
    //   1682: astore 6
    //   1684: aload 8
    //   1686: astore 15
    //   1688: aload 12
    //   1690: astore 10
    //   1692: aload 7
    //   1694: astore 9
    //   1696: aload 13
    //   1698: astore 8
    //   1700: aload 15
    //   1702: astore 7
    //   1704: goto -1276 -> 428
    //   1707: astore 11
    //   1709: aload 6
    //   1711: astore 13
    //   1713: aload 10
    //   1715: astore 15
    //   1717: aload 9
    //   1719: astore 6
    //   1721: aload 8
    //   1723: astore 16
    //   1725: aload 12
    //   1727: astore 10
    //   1729: aload 7
    //   1731: astore 11
    //   1733: aload 13
    //   1735: astore 9
    //   1737: aload 15
    //   1739: astore 8
    //   1741: aload 16
    //   1743: astore 7
    //   1745: goto -1317 -> 428
    //   1748: astore 9
    //   1750: aload 8
    //   1752: astore 13
    //   1754: aload 6
    //   1756: astore 9
    //   1758: aload 10
    //   1760: astore 8
    //   1762: aload 12
    //   1764: astore 6
    //   1766: aload 11
    //   1768: astore 10
    //   1770: aload 7
    //   1772: astore 11
    //   1774: aload 13
    //   1776: astore 7
    //   1778: goto -1350 -> 428
    //   1781: aload 10
    //   1783: ifnonnull -1114 -> 669
    //   1786: aload 10
    //   1788: astore 7
    //   1790: aload 8
    //   1792: ifnonnull -1112 -> 680
    //   1795: aload 9
    //   1797: ifnonnull -1099 -> 698
    //   1800: aload 11
    //   1802: ifnonnull -1093 -> 709
    //   1805: aload 12
    //   1807: ifnonnull -1087 -> 720
    //   1810: aload 6
    //   1812: astore 13
    //   1814: aload 7
    //   1816: astore 6
    //   1818: aload 8
    //   1820: astore 7
    //   1822: aload 6
    //   1824: astore 8
    //   1826: aload 14
    //   1828: astore 19
    //   1830: iload_3
    //   1831: istore 5
    //   1833: iload 4
    //   1835: iconst_1
    //   1836: iadd
    //   1837: istore 4
    //   1839: aload 7
    //   1841: astore 10
    //   1843: iload 5
    //   1845: istore_3
    //   1846: aload 19
    //   1848: astore 14
    //   1850: aload 9
    //   1852: astore 7
    //   1854: aload 8
    //   1856: astore 6
    //   1858: aload 13
    //   1860: astore 9
    //   1862: aload 10
    //   1864: astore 8
    //   1866: goto -1769 -> 97
    // Local variable table:
    //   start	length	slot	name	signature
    //   0	1869	0	this	l
    //   0	1869	1	paramArrayOfByte	byte[]
    //   0	1869	2	paramContext	android.content.Context
    //   79	1767	3	i	int
    //   76	1762	4	j	int
    //   465	1379	5	k	int
    //   90	1178	6	localObject1	Object
    //   1274	88	6	localConnectTimeoutException1	org.apache.http.conn.ConnectTimeoutException
    //   1368	84	6	localSocketTimeoutException1	java.net.SocketTimeoutException
    //   1457	1	6	localObject2	Object
    //   1466	1	6	localSocketException1	java.net.SocketException
    //   1470	163	6	localObject3	Object
    //   1637	1	6	localUnknownHostException1	java.net.UnknownHostException
    //   1645	212	6	localObject4	Object
    //   87	1170	7	localObject5	Object
    //   1283	1	7	localConnectTimeoutException2	org.apache.http.conn.ConnectTimeoutException
    //   1287	64	7	localObject6	Object
    //   1377	1	7	localSocketTimeoutException2	java.net.SocketTimeoutException
    //   1381	64	7	localObject7	Object
    //   1479	1	7	localSocketException2	java.net.SocketException
    //   1483	183	7	localObject8	Object
    //   1670	1	7	localUnknownHostException2	java.net.UnknownHostException
    //   1674	179	7	localObject9	Object
    //   16	1849	8	localObject10	Object
    //   95	1233	9	localObject11	Object
    //   1334	88	9	localConnectTimeoutException3	org.apache.http.conn.ConnectTimeoutException
    //   1428	112	9	localSocketTimeoutException3	java.net.SocketTimeoutException
    //   1546	1	9	localSocketException3	java.net.SocketException
    //   1550	186	9	localObject12	Object
    //   1748	1	9	localUnknownHostException3	java.net.UnknownHostException
    //   1756	105	9	localObject13	Object
    //   141	360	10	localObject14	Object
    //   538	1	10	localSocketException4	java.net.SocketException
    //   542	265	10	localObject15	Object
    //   852	1	10	localSocketTimeoutException4	java.net.SocketTimeoutException
    //   856	103	10	localObject16	Object
    //   1009	1	10	localConnectTimeoutException4	org.apache.http.conn.ConnectTimeoutException
    //   1013	204	10	localObject17	Object
    //   1261	1	10	localConnectTimeoutException5	org.apache.http.conn.ConnectTimeoutException
    //   1269	1	10	localObject18	Object
    //   1355	1	10	localSocketTimeoutException5	java.net.SocketTimeoutException
    //   1363	1	10	localConnectTimeoutException6	org.apache.http.conn.ConnectTimeoutException
    //   1449	1	10	localSocketException5	java.net.SocketException
    //   1453	1	10	localSocketTimeoutException6	java.net.SocketTimeoutException
    //   1571	1	10	localUnknownHostException4	java.net.UnknownHostException
    //   1583	1	10	localObject19	Object
    //   1604	1	10	localUnknownHostException5	java.net.UnknownHostException
    //   1616	247	10	localObject20	Object
    //   84	1169	11	localObject21	Object
    //   1296	1	11	localConnectTimeoutException7	org.apache.http.conn.ConnectTimeoutException
    //   1300	47	11	localObject22	Object
    //   1390	1	11	localSocketTimeoutException7	java.net.SocketTimeoutException
    //   1394	47	11	localObject23	Object
    //   1496	1	11	localSocketException6	java.net.SocketException
    //   1508	51	11	localObject24	Object
    //   1707	1	11	localUnknownHostException6	java.net.UnknownHostException
    //   1731	70	11	localObject25	Object
    //   81	305	12	localObject26	Object
    //   394	1	12	localUnknownHostException7	java.net.UnknownHostException
    //   398	851	12	localObject27	Object
    //   1313	1	12	localConnectTimeoutException8	org.apache.http.conn.ConnectTimeoutException
    //   1317	26	12	localObject28	Object
    //   1407	1	12	localSocketTimeoutException8	java.net.SocketTimeoutException
    //   1411	92	12	localObject29	Object
    //   1521	1	12	localSocketException7	java.net.SocketException
    //   1525	281	12	localObject30	Object
    //   362	1497	13	localObject31	Object
    //   25	1824	14	localObject32	Object
    //   435	1303	15	localObject33	Object
    //   444	1298	16	localObject34	Object
    //   453	698	17	localObject35	Object
    //   462	700	18	localObject36	Object
    //   469	1378	19	localObject37	Object
    //   4	133	20	localNetworkInfo	NetworkInfo
    //   34	118	21	localStringBuffer	StringBuffer
    // Exception table:
    //   from	to	target	type
    //   324	331	394	java/net/UnknownHostException
    //   336	343	394	java/net/UnknownHostException
    //   383	391	394	java/net/UnknownHostException
    //   135	143	538	java/net/SocketException
    //   135	143	635	finally
    //   135	143	852	java/net/SocketTimeoutException
    //   135	143	1009	org/apache/http/conn/ConnectTimeoutException
    //   147	161	1213	finally
    //   161	271	1221	finally
    //   282	296	1221	finally
    //   296	310	1225	finally
    //   310	324	1233	finally
    //   324	331	1245	finally
    //   336	343	1245	finally
    //   343	355	1245	finally
    //   383	391	1245	finally
    //   147	161	1261	org/apache/http/conn/ConnectTimeoutException
    //   161	271	1274	org/apache/http/conn/ConnectTimeoutException
    //   282	296	1274	org/apache/http/conn/ConnectTimeoutException
    //   296	310	1283	org/apache/http/conn/ConnectTimeoutException
    //   310	324	1296	org/apache/http/conn/ConnectTimeoutException
    //   324	331	1313	org/apache/http/conn/ConnectTimeoutException
    //   336	343	1313	org/apache/http/conn/ConnectTimeoutException
    //   383	391	1313	org/apache/http/conn/ConnectTimeoutException
    //   343	355	1334	org/apache/http/conn/ConnectTimeoutException
    //   147	161	1355	java/net/SocketTimeoutException
    //   161	271	1368	java/net/SocketTimeoutException
    //   282	296	1368	java/net/SocketTimeoutException
    //   296	310	1377	java/net/SocketTimeoutException
    //   310	324	1390	java/net/SocketTimeoutException
    //   324	331	1407	java/net/SocketTimeoutException
    //   336	343	1407	java/net/SocketTimeoutException
    //   383	391	1407	java/net/SocketTimeoutException
    //   343	355	1428	java/net/SocketTimeoutException
    //   147	161	1449	java/net/SocketException
    //   161	271	1466	java/net/SocketException
    //   282	296	1466	java/net/SocketException
    //   296	310	1479	java/net/SocketException
    //   310	324	1496	java/net/SocketException
    //   324	331	1521	java/net/SocketException
    //   336	343	1521	java/net/SocketException
    //   383	391	1521	java/net/SocketException
    //   343	355	1546	java/net/SocketException
    //   135	143	1571	java/net/UnknownHostException
    //   147	161	1604	java/net/UnknownHostException
    //   161	271	1637	java/net/UnknownHostException
    //   282	296	1637	java/net/UnknownHostException
    //   296	310	1670	java/net/UnknownHostException
    //   310	324	1707	java/net/UnknownHostException
    //   343	355	1748	java/net/UnknownHostException
  }
  
  /* Error */
  public String a(byte[] paramArrayOfByte, android.content.Context paramContext, JSONObject paramJSONObject)
    throws java.lang.Exception
  {
    // Byte code:
    //   0: aload_2
    //   1: invokestatic 279	com/aps/t:b	(Landroid/content/Context;)Landroid/net/NetworkInfo;
    //   4: astore 23
    //   6: aload 23
    //   8: invokestatic 281	com/aps/l:a	(Landroid/net/NetworkInfo;)I
    //   11: iconst_m1
    //   12: if_icmpeq +58 -> 70
    //   15: new 283	java/lang/StringBuffer
    //   18: dup
    //   19: invokespecial 284	java/lang/StringBuffer:<init>	()V
    //   22: astore 21
    //   24: iconst_0
    //   25: istore 4
    //   27: iconst_0
    //   28: istore 5
    //   30: ldc_w 286
    //   33: astore 22
    //   35: aconst_null
    //   36: astore 13
    //   38: aconst_null
    //   39: astore 10
    //   41: aconst_null
    //   42: astore 9
    //   44: aconst_null
    //   45: astore 14
    //   47: aconst_null
    //   48: astore 8
    //   50: aconst_null
    //   51: astore 11
    //   53: iload 4
    //   55: iconst_1
    //   56: if_icmplt +25 -> 81
    //   59: aload 22
    //   61: invokestatic 172	android/text/TextUtils:isEmpty	(Ljava/lang/CharSequence;)Z
    //   64: ifne +1290 -> 1354
    //   67: aload 22
    //   69: areturn
    //   70: new 268	com/amap/api/location/core/AMapLocException
    //   73: dup
    //   74: ldc_w 406
    //   77: invokespecial 394	com/amap/api/location/core/AMapLocException:<init>	(Ljava/lang/String;)V
    //   80: athrow
    //   81: iload 5
    //   83: ifne -24 -> 59
    //   86: aload_2
    //   87: aload 23
    //   89: invokestatic 288	com/aps/l:a	(Landroid/content/Context;Landroid/net/NetworkInfo;)Lorg/apache/http/client/HttpClient;
    //   92: astore 12
    //   94: aload 12
    //   96: astore 11
    //   98: aload_3
    //   99: invokestatic 455	com/aps/l:a	(Lorg/json/JSONObject;)[Ljava/lang/String;
    //   102: astore 24
    //   104: new 290	org/apache/http/client/methods/HttpPost
    //   107: dup
    //   108: invokestatic 240	com/amap/api/location/core/c:j	()Ljava/lang/String;
    //   111: invokespecial 293	org/apache/http/client/methods/HttpPost:<init>	(Ljava/lang/String;)V
    //   114: astore 12
    //   116: aload 13
    //   118: astore 15
    //   120: aload 10
    //   122: astore 16
    //   124: aload 9
    //   126: astore 17
    //   128: aload 14
    //   130: astore 18
    //   132: aload 12
    //   134: astore 19
    //   136: aload 11
    //   138: astore 20
    //   140: new 295	org/apache/http/entity/ByteArrayEntity
    //   143: dup
    //   144: aload_1
    //   145: invokestatic 447	com/aps/t:a	([B)[B
    //   148: invokespecial 298	org/apache/http/entity/ByteArrayEntity:<init>	([B)V
    //   151: astore 8
    //   153: aload 13
    //   155: astore 15
    //   157: aload 10
    //   159: astore 16
    //   161: aload 9
    //   163: astore 17
    //   165: aload 14
    //   167: astore 18
    //   169: aload 12
    //   171: astore 19
    //   173: aload 11
    //   175: astore 20
    //   177: aload 8
    //   179: ldc_w 449
    //   182: invokevirtual 452	org/apache/http/entity/ByteArrayEntity:setContentType	(Ljava/lang/String;)V
    //   185: aload 13
    //   187: astore 15
    //   189: aload 10
    //   191: astore 16
    //   193: aload 9
    //   195: astore 17
    //   197: aload 14
    //   199: astore 18
    //   201: aload 12
    //   203: astore 19
    //   205: aload 11
    //   207: astore 20
    //   209: aload 12
    //   211: ldc_w 310
    //   214: ldc -30
    //   216: invokevirtual 306	org/apache/http/client/methods/HttpPost:addHeader	(Ljava/lang/String;Ljava/lang/String;)V
    //   219: aload 13
    //   221: astore 15
    //   223: aload 10
    //   225: astore 16
    //   227: aload 9
    //   229: astore 17
    //   231: aload 14
    //   233: astore 18
    //   235: aload 12
    //   237: astore 19
    //   239: aload 11
    //   241: astore 20
    //   243: aload 12
    //   245: ldc_w 444
    //   248: ldc_w 323
    //   251: invokevirtual 306	org/apache/http/client/methods/HttpPost:addHeader	(Ljava/lang/String;Ljava/lang/String;)V
    //   254: aload 13
    //   256: astore 15
    //   258: aload 10
    //   260: astore 16
    //   262: aload 9
    //   264: astore 17
    //   266: aload 14
    //   268: astore 18
    //   270: aload 12
    //   272: astore 19
    //   274: aload 11
    //   276: astore 20
    //   278: aload 12
    //   280: ldc -7
    //   282: aload 24
    //   284: iconst_2
    //   285: aaload
    //   286: invokevirtual 306	org/apache/http/client/methods/HttpPost:addHeader	(Ljava/lang/String;Ljava/lang/String;)V
    //   289: aload 13
    //   291: astore 15
    //   293: aload 10
    //   295: astore 16
    //   297: aload 9
    //   299: astore 17
    //   301: aload 14
    //   303: astore 18
    //   305: aload 12
    //   307: astore 19
    //   309: aload 11
    //   311: astore 20
    //   313: aload 12
    //   315: ldc -5
    //   317: aload 24
    //   319: iconst_3
    //   320: aaload
    //   321: invokevirtual 306	org/apache/http/client/methods/HttpPost:addHeader	(Ljava/lang/String;Ljava/lang/String;)V
    //   324: aload 13
    //   326: astore 15
    //   328: aload 10
    //   330: astore 16
    //   332: aload 9
    //   334: astore 17
    //   336: aload 14
    //   338: astore 18
    //   340: aload 12
    //   342: astore 19
    //   344: aload 11
    //   346: astore 20
    //   348: aload 12
    //   350: ldc_w 457
    //   353: aload 24
    //   355: iconst_1
    //   356: aaload
    //   357: invokevirtual 306	org/apache/http/client/methods/HttpPost:addHeader	(Ljava/lang/String;Ljava/lang/String;)V
    //   360: aload 13
    //   362: astore 15
    //   364: aload 10
    //   366: astore 16
    //   368: aload 9
    //   370: astore 17
    //   372: aload 14
    //   374: astore 18
    //   376: aload 12
    //   378: astore 19
    //   380: aload 11
    //   382: astore 20
    //   384: aload 12
    //   386: ldc_w 459
    //   389: ldc_w 323
    //   392: invokevirtual 306	org/apache/http/client/methods/HttpPost:addHeader	(Ljava/lang/String;Ljava/lang/String;)V
    //   395: aload 13
    //   397: astore 15
    //   399: aload 10
    //   401: astore 16
    //   403: aload 9
    //   405: astore 17
    //   407: aload 14
    //   409: astore 18
    //   411: aload 12
    //   413: astore 19
    //   415: aload 11
    //   417: astore 20
    //   419: aload 12
    //   421: ldc_w 461
    //   424: ldc_w 463
    //   427: invokevirtual 306	org/apache/http/client/methods/HttpPost:addHeader	(Ljava/lang/String;Ljava/lang/String;)V
    //   430: aload 24
    //   432: iconst_4
    //   433: aaload
    //   434: ifnonnull +317 -> 751
    //   437: aload 13
    //   439: astore 15
    //   441: aload 10
    //   443: astore 16
    //   445: aload 9
    //   447: astore 17
    //   449: aload 14
    //   451: astore 18
    //   453: aload 12
    //   455: astore 19
    //   457: aload 11
    //   459: astore 20
    //   461: invokestatic 466	com/amap/api/location/core/d:a	()Ljava/lang/String;
    //   464: astore 25
    //   466: aload 13
    //   468: astore 15
    //   470: aload 10
    //   472: astore 16
    //   474: aload 9
    //   476: astore 17
    //   478: aload 14
    //   480: astore 18
    //   482: aload 12
    //   484: astore 19
    //   486: aload 11
    //   488: astore 20
    //   490: aload 25
    //   492: new 468	java/lang/StringBuilder
    //   495: dup
    //   496: invokespecial 469	java/lang/StringBuilder:<init>	()V
    //   499: ldc_w 471
    //   502: invokevirtual 474	java/lang/StringBuilder:append	(Ljava/lang/String;)Ljava/lang/StringBuilder;
    //   505: aload 24
    //   507: iconst_1
    //   508: aaload
    //   509: invokevirtual 474	java/lang/StringBuilder:append	(Ljava/lang/String;)Ljava/lang/StringBuilder;
    //   512: invokevirtual 475	java/lang/StringBuilder:toString	()Ljava/lang/String;
    //   515: invokestatic 478	com/amap/api/location/core/d:a	(Ljava/lang/String;Ljava/lang/String;)Ljava/lang/String;
    //   518: astore 24
    //   520: aload 13
    //   522: astore 15
    //   524: aload 10
    //   526: astore 16
    //   528: aload 9
    //   530: astore 17
    //   532: aload 14
    //   534: astore 18
    //   536: aload 12
    //   538: astore 19
    //   540: aload 11
    //   542: astore 20
    //   544: aload 12
    //   546: ldc_w 480
    //   549: aload 25
    //   551: invokevirtual 306	org/apache/http/client/methods/HttpPost:addHeader	(Ljava/lang/String;Ljava/lang/String;)V
    //   554: aload 13
    //   556: astore 15
    //   558: aload 10
    //   560: astore 16
    //   562: aload 9
    //   564: astore 17
    //   566: aload 14
    //   568: astore 18
    //   570: aload 12
    //   572: astore 19
    //   574: aload 11
    //   576: astore 20
    //   578: aload 12
    //   580: ldc_w 482
    //   583: aload 24
    //   585: invokevirtual 306	org/apache/http/client/methods/HttpPost:addHeader	(Ljava/lang/String;Ljava/lang/String;)V
    //   588: aload 13
    //   590: astore 15
    //   592: aload 10
    //   594: astore 16
    //   596: aload 9
    //   598: astore 17
    //   600: aload 14
    //   602: astore 18
    //   604: aload 12
    //   606: astore 19
    //   608: aload 11
    //   610: astore 20
    //   612: aload 21
    //   614: iconst_0
    //   615: aload 21
    //   617: invokevirtual 326	java/lang/StringBuffer:length	()I
    //   620: invokevirtual 330	java/lang/StringBuffer:delete	(II)Ljava/lang/StringBuffer;
    //   623: pop
    //   624: aload 13
    //   626: astore 15
    //   628: aload 10
    //   630: astore 16
    //   632: aload 9
    //   634: astore 17
    //   636: aload 14
    //   638: astore 18
    //   640: aload 12
    //   642: astore 19
    //   644: aload 11
    //   646: astore 20
    //   648: aload 12
    //   650: aload 8
    //   652: invokevirtual 334	org/apache/http/client/methods/HttpPost:setEntity	(Lorg/apache/http/HttpEntity;)V
    //   655: aload 13
    //   657: astore 15
    //   659: aload 10
    //   661: astore 16
    //   663: aload 9
    //   665: astore 17
    //   667: aload 14
    //   669: astore 18
    //   671: aload 12
    //   673: astore 19
    //   675: aload 11
    //   677: astore 20
    //   679: aload 11
    //   681: aload 12
    //   683: invokeinterface 340 2 0
    //   688: astore 24
    //   690: aload 13
    //   692: astore 15
    //   694: aload 10
    //   696: astore 16
    //   698: aload 9
    //   700: astore 17
    //   702: aload 14
    //   704: astore 18
    //   706: aload 12
    //   708: astore 19
    //   710: aload 11
    //   712: astore 20
    //   714: aload 24
    //   716: invokeinterface 344 1 0
    //   721: invokeinterface 349 1 0
    //   726: istore 6
    //   728: iload 6
    //   730: sipush 200
    //   733: if_icmpeq +149 -> 882
    //   736: iload 6
    //   738: sipush 404
    //   741: if_icmpeq +437 -> 1178
    //   744: aload 22
    //   746: astore 8
    //   748: goto +1054 -> 1802
    //   751: aload 13
    //   753: astore 15
    //   755: aload 10
    //   757: astore 16
    //   759: aload 9
    //   761: astore 17
    //   763: aload 14
    //   765: astore 18
    //   767: aload 12
    //   769: astore 19
    //   771: aload 11
    //   773: astore 20
    //   775: aload 24
    //   777: iconst_4
    //   778: aaload
    //   779: invokevirtual 210	java/lang/String:length	()I
    //   782: ifle -345 -> 437
    //   785: aload 13
    //   787: astore 15
    //   789: aload 10
    //   791: astore 16
    //   793: aload 9
    //   795: astore 17
    //   797: aload 14
    //   799: astore 18
    //   801: aload 12
    //   803: astore 19
    //   805: aload 11
    //   807: astore 20
    //   809: aload 12
    //   811: ldc -3
    //   813: aload 24
    //   815: iconst_4
    //   816: aaload
    //   817: invokevirtual 306	org/apache/http/client/methods/HttpPost:addHeader	(Ljava/lang/String;Ljava/lang/String;)V
    //   820: goto -383 -> 437
    //   823: astore_1
    //   824: aload 12
    //   826: astore_1
    //   827: aload 11
    //   829: astore_2
    //   830: new 268	com/amap/api/location/core/AMapLocException
    //   833: dup
    //   834: ldc_w 393
    //   837: invokespecial 394	com/amap/api/location/core/AMapLocException:<init>	(Ljava/lang/String;)V
    //   840: athrow
    //   841: astore_3
    //   842: aload_1
    //   843: astore 12
    //   845: aload_3
    //   846: astore_1
    //   847: aload_2
    //   848: astore 11
    //   850: aload 12
    //   852: ifnonnull +597 -> 1449
    //   855: aload 11
    //   857: ifnonnull +600 -> 1457
    //   860: aload 9
    //   862: ifnonnull +610 -> 1472
    //   865: aload 14
    //   867: ifnonnull +621 -> 1488
    //   870: aload 10
    //   872: ifnonnull +632 -> 1504
    //   875: aload 13
    //   877: ifnonnull +635 -> 1512
    //   880: aload_1
    //   881: athrow
    //   882: aload 13
    //   884: astore 15
    //   886: aload 10
    //   888: astore 16
    //   890: aload 9
    //   892: astore 17
    //   894: aload 14
    //   896: astore 18
    //   898: aload 12
    //   900: astore 19
    //   902: aload 11
    //   904: astore 20
    //   906: aload 24
    //   908: invokeinterface 353 1 0
    //   913: invokeinterface 359 1 0
    //   918: astore 8
    //   920: aload 24
    //   922: invokeinterface 353 1 0
    //   927: invokeinterface 363 1 0
    //   932: invokeinterface 224 1 0
    //   937: astore 15
    //   939: ldc_w 286
    //   942: astore 14
    //   944: aload 15
    //   946: ldc_w 365
    //   949: invokevirtual 187	java/lang/String:indexOf	(Ljava/lang/String;)I
    //   952: istore 5
    //   954: iload 5
    //   956: iconst_m1
    //   957: if_icmpne +111 -> 1068
    //   960: aload 14
    //   962: invokestatic 172	android/text/TextUtils:isEmpty	(Ljava/lang/CharSequence;)Z
    //   965: ifne +884 -> 1849
    //   968: aload 24
    //   970: invokestatic 367	com/aps/l:a	(Lorg/apache/http/HttpResponse;)Z
    //   973: istore 7
    //   975: iload 7
    //   977: ifne +106 -> 1083
    //   980: aload 9
    //   982: ifnonnull +133 -> 1115
    //   985: new 369	java/io/InputStreamReader
    //   988: dup
    //   989: aload 8
    //   991: aload 14
    //   993: invokespecial 372	java/io/InputStreamReader:<init>	(Ljava/io/InputStream;Ljava/lang/String;)V
    //   996: astore 14
    //   998: aload 14
    //   1000: astore 10
    //   1002: new 374	java/io/BufferedReader
    //   1005: dup
    //   1006: aload 10
    //   1008: sipush 2048
    //   1011: invokespecial 377	java/io/BufferedReader:<init>	(Ljava/io/Reader;I)V
    //   1014: astore 14
    //   1016: aload 14
    //   1018: invokevirtual 380	java/io/BufferedReader:readLine	()Ljava/lang/String;
    //   1021: astore 13
    //   1023: aload 13
    //   1025: ifnonnull +124 -> 1149
    //   1028: aload 21
    //   1030: invokevirtual 383	java/lang/StringBuffer:toString	()Ljava/lang/String;
    //   1033: astore 15
    //   1035: aload 21
    //   1037: iconst_0
    //   1038: aload 21
    //   1040: invokevirtual 326	java/lang/StringBuffer:length	()I
    //   1043: invokevirtual 330	java/lang/StringBuffer:delete	(II)Ljava/lang/StringBuffer;
    //   1046: pop
    //   1047: aconst_null
    //   1048: astore 21
    //   1050: iconst_1
    //   1051: istore 5
    //   1053: aload 14
    //   1055: astore 13
    //   1057: aload 8
    //   1059: astore 14
    //   1061: aload 15
    //   1063: astore 8
    //   1065: goto +737 -> 1802
    //   1068: aload 15
    //   1070: iload 5
    //   1072: bipush 8
    //   1074: iadd
    //   1075: invokevirtual 386	java/lang/String:substring	(I)Ljava/lang/String;
    //   1078: astore 14
    //   1080: goto -120 -> 960
    //   1083: new 388	java/util/zip/GZIPInputStream
    //   1086: dup
    //   1087: aload 8
    //   1089: invokespecial 391	java/util/zip/GZIPInputStream:<init>	(Ljava/io/InputStream;)V
    //   1092: astore 15
    //   1094: aload 15
    //   1096: astore 9
    //   1098: goto -118 -> 980
    //   1101: astore_1
    //   1102: aload 12
    //   1104: astore_1
    //   1105: aload 11
    //   1107: astore_2
    //   1108: aload 8
    //   1110: astore 14
    //   1112: goto -282 -> 830
    //   1115: new 369	java/io/InputStreamReader
    //   1118: dup
    //   1119: aload 9
    //   1121: aload 14
    //   1123: invokespecial 372	java/io/InputStreamReader:<init>	(Ljava/io/InputStream;Ljava/lang/String;)V
    //   1126: astore 14
    //   1128: aload 14
    //   1130: astore 10
    //   1132: goto -130 -> 1002
    //   1135: astore_1
    //   1136: aload 12
    //   1138: astore_1
    //   1139: aload 11
    //   1141: astore_2
    //   1142: aload 8
    //   1144: astore 14
    //   1146: goto -316 -> 830
    //   1149: aload 21
    //   1151: aload 13
    //   1153: invokevirtual 398	java/lang/StringBuffer:append	(Ljava/lang/String;)Ljava/lang/StringBuffer;
    //   1156: pop
    //   1157: goto -141 -> 1016
    //   1160: astore_1
    //   1161: aload 14
    //   1163: astore 13
    //   1165: aload 12
    //   1167: astore_1
    //   1168: aload 11
    //   1170: astore_2
    //   1171: aload 8
    //   1173: astore 14
    //   1175: goto -345 -> 830
    //   1178: aload 13
    //   1180: astore 15
    //   1182: aload 10
    //   1184: astore 16
    //   1186: aload 9
    //   1188: astore 17
    //   1190: aload 14
    //   1192: astore 18
    //   1194: aload 12
    //   1196: astore 19
    //   1198: aload 11
    //   1200: astore 20
    //   1202: new 268	com/amap/api/location/core/AMapLocException
    //   1205: dup
    //   1206: ldc_w 400
    //   1209: invokespecial 394	com/amap/api/location/core/AMapLocException:<init>	(Ljava/lang/String;)V
    //   1212: athrow
    //   1213: astore_1
    //   1214: aload 13
    //   1216: astore 15
    //   1218: aload 10
    //   1220: astore 16
    //   1222: aload 9
    //   1224: astore 17
    //   1226: aload 14
    //   1228: astore 18
    //   1230: aload 12
    //   1232: astore 19
    //   1234: aload 11
    //   1236: astore 20
    //   1238: new 268	com/amap/api/location/core/AMapLocException
    //   1241: dup
    //   1242: ldc_w 402
    //   1245: invokespecial 394	com/amap/api/location/core/AMapLocException:<init>	(Ljava/lang/String;)V
    //   1248: athrow
    //   1249: aload 13
    //   1251: astore 15
    //   1253: aload 10
    //   1255: astore 16
    //   1257: aload 9
    //   1259: astore 17
    //   1261: aload 14
    //   1263: astore 18
    //   1265: aload 12
    //   1267: astore 19
    //   1269: aload 11
    //   1271: astore 20
    //   1273: new 268	com/amap/api/location/core/AMapLocException
    //   1276: dup
    //   1277: ldc_w 404
    //   1280: invokespecial 394	com/amap/api/location/core/AMapLocException:<init>	(Ljava/lang/String;)V
    //   1283: athrow
    //   1284: aload 13
    //   1286: astore 15
    //   1288: aload 10
    //   1290: astore 16
    //   1292: aload 9
    //   1294: astore 17
    //   1296: aload 14
    //   1298: astore 18
    //   1300: aload 12
    //   1302: astore 19
    //   1304: aload 11
    //   1306: astore 20
    //   1308: new 268	com/amap/api/location/core/AMapLocException
    //   1311: dup
    //   1312: ldc_w 406
    //   1315: invokespecial 394	com/amap/api/location/core/AMapLocException:<init>	(Ljava/lang/String;)V
    //   1318: athrow
    //   1319: aload 13
    //   1321: astore 15
    //   1323: aload 10
    //   1325: astore 16
    //   1327: aload 9
    //   1329: astore 17
    //   1331: aload 14
    //   1333: astore 18
    //   1335: aload 12
    //   1337: astore 19
    //   1339: aload 11
    //   1341: astore 20
    //   1343: new 268	com/amap/api/location/core/AMapLocException
    //   1346: dup
    //   1347: ldc_w 406
    //   1350: invokespecial 394	com/amap/api/location/core/AMapLocException:<init>	(Ljava/lang/String;)V
    //   1353: athrow
    //   1354: aconst_null
    //   1355: areturn
    //   1356: aload 12
    //   1358: invokevirtual 411	org/apache/http/client/methods/HttpPost:abort	()V
    //   1361: aconst_null
    //   1362: astore 12
    //   1364: goto +443 -> 1807
    //   1367: aload 11
    //   1369: invokeinterface 415 1 0
    //   1374: invokeinterface 420 1 0
    //   1379: aconst_null
    //   1380: astore 11
    //   1382: goto +430 -> 1812
    //   1385: aload 9
    //   1387: invokevirtual 421	java/util/zip/GZIPInputStream:close	()V
    //   1390: aconst_null
    //   1391: astore 9
    //   1393: goto +424 -> 1817
    //   1396: astore 9
    //   1398: aload 9
    //   1400: invokevirtual 265	java/lang/Throwable:printStackTrace	()V
    //   1403: goto -13 -> 1390
    //   1406: aload 14
    //   1408: invokevirtual 424	java/io/InputStream:close	()V
    //   1411: aconst_null
    //   1412: astore 14
    //   1414: goto +408 -> 1822
    //   1417: astore 14
    //   1419: aload 14
    //   1421: invokevirtual 265	java/lang/Throwable:printStackTrace	()V
    //   1424: goto -13 -> 1411
    //   1427: aload 10
    //   1429: invokevirtual 425	java/io/InputStreamReader:close	()V
    //   1432: aconst_null
    //   1433: astore 10
    //   1435: goto +392 -> 1827
    //   1438: aload 13
    //   1440: invokevirtual 426	java/io/BufferedReader:close	()V
    //   1443: aconst_null
    //   1444: astore 13
    //   1446: goto +386 -> 1832
    //   1449: aload 12
    //   1451: invokevirtual 411	org/apache/http/client/methods/HttpPost:abort	()V
    //   1454: goto -599 -> 855
    //   1457: aload 11
    //   1459: invokeinterface 415 1 0
    //   1464: invokeinterface 420 1 0
    //   1469: goto -609 -> 860
    //   1472: aload 9
    //   1474: invokevirtual 421	java/util/zip/GZIPInputStream:close	()V
    //   1477: goto -612 -> 865
    //   1480: astore_2
    //   1481: aload_2
    //   1482: invokevirtual 265	java/lang/Throwable:printStackTrace	()V
    //   1485: goto -620 -> 865
    //   1488: aload 14
    //   1490: invokevirtual 424	java/io/InputStream:close	()V
    //   1493: goto -623 -> 870
    //   1496: astore_2
    //   1497: aload_2
    //   1498: invokevirtual 265	java/lang/Throwable:printStackTrace	()V
    //   1501: goto -631 -> 870
    //   1504: aload 10
    //   1506: invokevirtual 425	java/io/InputStreamReader:close	()V
    //   1509: goto -634 -> 875
    //   1512: aload 13
    //   1514: invokevirtual 426	java/io/BufferedReader:close	()V
    //   1517: goto -637 -> 880
    //   1520: astore_1
    //   1521: aload 8
    //   1523: astore 12
    //   1525: goto -675 -> 850
    //   1528: astore_1
    //   1529: aload 8
    //   1531: astore 12
    //   1533: goto -683 -> 850
    //   1536: astore_1
    //   1537: aload 8
    //   1539: astore 14
    //   1541: goto -691 -> 850
    //   1544: astore_1
    //   1545: aload 8
    //   1547: astore 14
    //   1549: goto -699 -> 850
    //   1552: astore_1
    //   1553: aload 8
    //   1555: astore 14
    //   1557: goto -707 -> 850
    //   1560: astore_1
    //   1561: aload 14
    //   1563: astore 13
    //   1565: aload 8
    //   1567: astore 14
    //   1569: goto -719 -> 850
    //   1572: astore_1
    //   1573: aload 8
    //   1575: astore 12
    //   1577: goto -258 -> 1319
    //   1580: astore_1
    //   1581: goto -262 -> 1319
    //   1584: astore_1
    //   1585: aload 8
    //   1587: astore 14
    //   1589: goto -270 -> 1319
    //   1592: astore_1
    //   1593: aload 8
    //   1595: astore 14
    //   1597: goto -278 -> 1319
    //   1600: astore_1
    //   1601: aload 8
    //   1603: astore 14
    //   1605: goto -286 -> 1319
    //   1608: astore_1
    //   1609: aload 14
    //   1611: astore 13
    //   1613: aload 8
    //   1615: astore 14
    //   1617: goto -298 -> 1319
    //   1620: astore_1
    //   1621: aload 8
    //   1623: astore 12
    //   1625: goto -341 -> 1284
    //   1628: astore_1
    //   1629: goto -345 -> 1284
    //   1632: astore_1
    //   1633: aload 8
    //   1635: astore 14
    //   1637: goto -353 -> 1284
    //   1640: astore_1
    //   1641: aload 8
    //   1643: astore 14
    //   1645: goto -361 -> 1284
    //   1648: astore_1
    //   1649: aload 8
    //   1651: astore 14
    //   1653: goto -369 -> 1284
    //   1656: astore_1
    //   1657: aload 14
    //   1659: astore 13
    //   1661: aload 8
    //   1663: astore 14
    //   1665: goto -381 -> 1284
    //   1668: astore_1
    //   1669: aload 8
    //   1671: astore 12
    //   1673: goto -424 -> 1249
    //   1676: astore_1
    //   1677: goto -428 -> 1249
    //   1680: astore_1
    //   1681: aload 8
    //   1683: astore 14
    //   1685: goto -436 -> 1249
    //   1688: astore_1
    //   1689: aload 8
    //   1691: astore 14
    //   1693: goto -444 -> 1249
    //   1696: astore_1
    //   1697: aload 8
    //   1699: astore 14
    //   1701: goto -452 -> 1249
    //   1704: astore_1
    //   1705: aload 14
    //   1707: astore 13
    //   1709: aload 8
    //   1711: astore 14
    //   1713: goto -464 -> 1249
    //   1716: astore_1
    //   1717: aload 8
    //   1719: astore 12
    //   1721: goto -507 -> 1214
    //   1724: astore_1
    //   1725: aload 8
    //   1727: astore 12
    //   1729: goto -515 -> 1214
    //   1732: astore_1
    //   1733: aload 8
    //   1735: astore 14
    //   1737: goto -523 -> 1214
    //   1740: astore_1
    //   1741: aload 8
    //   1743: astore 14
    //   1745: goto -531 -> 1214
    //   1748: astore_1
    //   1749: aload 8
    //   1751: astore 14
    //   1753: goto -539 -> 1214
    //   1756: astore_1
    //   1757: aload 14
    //   1759: astore 13
    //   1761: aload 8
    //   1763: astore 14
    //   1765: goto -551 -> 1214
    //   1768: astore_1
    //   1769: aload 8
    //   1771: astore_1
    //   1772: aload 11
    //   1774: astore_2
    //   1775: goto -945 -> 830
    //   1778: astore_1
    //   1779: aload 8
    //   1781: astore_1
    //   1782: aload 11
    //   1784: astore_2
    //   1785: goto -955 -> 830
    //   1788: astore_1
    //   1789: aload 12
    //   1791: astore_1
    //   1792: aload 11
    //   1794: astore_2
    //   1795: aload 8
    //   1797: astore 14
    //   1799: goto -969 -> 830
    //   1802: aload 12
    //   1804: ifnonnull -448 -> 1356
    //   1807: aload 11
    //   1809: ifnonnull -442 -> 1367
    //   1812: aload 9
    //   1814: ifnonnull -429 -> 1385
    //   1817: aload 14
    //   1819: ifnonnull -413 -> 1406
    //   1822: aload 10
    //   1824: ifnonnull -397 -> 1427
    //   1827: aload 13
    //   1829: ifnonnull -391 -> 1438
    //   1832: iload 4
    //   1834: iconst_1
    //   1835: iadd
    //   1836: istore 4
    //   1838: aload 8
    //   1840: astore 22
    //   1842: aload 12
    //   1844: astore 8
    //   1846: goto -1793 -> 53
    //   1849: ldc_w 428
    //   1852: astore 14
    //   1854: goto -886 -> 968
    //   1857: astore_1
    //   1858: aload 15
    //   1860: astore 13
    //   1862: aload 16
    //   1864: astore 10
    //   1866: aload 17
    //   1868: astore 9
    //   1870: aload 18
    //   1872: astore 14
    //   1874: aload 19
    //   1876: astore 12
    //   1878: aload 20
    //   1880: astore 11
    //   1882: goto -1032 -> 850
    //   1885: astore_1
    //   1886: aload 8
    //   1888: astore 12
    //   1890: goto -641 -> 1249
    //   1893: astore_1
    //   1894: aload 8
    //   1896: astore 12
    //   1898: goto -614 -> 1284
    //   1901: astore_1
    //   1902: aload 8
    //   1904: astore 12
    //   1906: goto -587 -> 1319
    // Local variable table:
    //   start	length	slot	name	signature
    //   0	1909	0	this	l
    //   0	1909	1	paramArrayOfByte	byte[]
    //   0	1909	2	paramContext	android.content.Context
    //   0	1909	3	paramJSONObject	JSONObject
    //   25	1812	4	i	int
    //   28	1047	5	j	int
    //   726	16	6	k	int
    //   973	3	7	bool	boolean
    //   48	1855	8	localObject1	Object
    //   42	1350	9	localObject2	Object
    //   1396	417	9	localThrowable1	Throwable
    //   1868	1	9	localObject3	Object
    //   39	1826	10	localObject4	Object
    //   51	1830	11	localObject5	Object
    //   92	1813	12	localObject6	Object
    //   36	1825	13	localObject7	Object
    //   45	1368	14	localObject8	Object
    //   1417	72	14	localThrowable2	Throwable
    //   1539	334	14	localObject9	Object
    //   118	1741	15	localObject10	Object
    //   122	1741	16	localObject11	Object
    //   126	1741	17	localObject12	Object
    //   130	1741	18	localObject13	Object
    //   134	1741	19	localObject14	Object
    //   138	1741	20	localObject15	Object
    //   22	1128	21	localStringBuffer	StringBuffer
    //   33	1808	22	localObject16	Object
    //   4	84	23	localNetworkInfo	NetworkInfo
    //   102	867	24	localObject17	Object
    //   464	86	25	str	String
    // Exception table:
    //   from	to	target	type
    //   140	153	823	java/net/UnknownHostException
    //   177	185	823	java/net/UnknownHostException
    //   209	219	823	java/net/UnknownHostException
    //   243	254	823	java/net/UnknownHostException
    //   278	289	823	java/net/UnknownHostException
    //   313	324	823	java/net/UnknownHostException
    //   348	360	823	java/net/UnknownHostException
    //   384	395	823	java/net/UnknownHostException
    //   419	430	823	java/net/UnknownHostException
    //   461	466	823	java/net/UnknownHostException
    //   490	520	823	java/net/UnknownHostException
    //   544	554	823	java/net/UnknownHostException
    //   578	588	823	java/net/UnknownHostException
    //   612	624	823	java/net/UnknownHostException
    //   648	655	823	java/net/UnknownHostException
    //   679	690	823	java/net/UnknownHostException
    //   714	728	823	java/net/UnknownHostException
    //   775	785	823	java/net/UnknownHostException
    //   809	820	823	java/net/UnknownHostException
    //   906	920	823	java/net/UnknownHostException
    //   1202	1213	823	java/net/UnknownHostException
    //   830	841	841	finally
    //   920	939	1101	java/net/UnknownHostException
    //   944	954	1101	java/net/UnknownHostException
    //   960	968	1101	java/net/UnknownHostException
    //   968	975	1101	java/net/UnknownHostException
    //   1068	1080	1101	java/net/UnknownHostException
    //   1083	1094	1101	java/net/UnknownHostException
    //   985	998	1135	java/net/UnknownHostException
    //   1115	1128	1135	java/net/UnknownHostException
    //   1016	1023	1160	java/net/UnknownHostException
    //   1028	1047	1160	java/net/UnknownHostException
    //   1149	1157	1160	java/net/UnknownHostException
    //   140	153	1213	java/net/SocketException
    //   177	185	1213	java/net/SocketException
    //   209	219	1213	java/net/SocketException
    //   243	254	1213	java/net/SocketException
    //   278	289	1213	java/net/SocketException
    //   313	324	1213	java/net/SocketException
    //   348	360	1213	java/net/SocketException
    //   384	395	1213	java/net/SocketException
    //   419	430	1213	java/net/SocketException
    //   461	466	1213	java/net/SocketException
    //   490	520	1213	java/net/SocketException
    //   544	554	1213	java/net/SocketException
    //   578	588	1213	java/net/SocketException
    //   612	624	1213	java/net/SocketException
    //   648	655	1213	java/net/SocketException
    //   679	690	1213	java/net/SocketException
    //   714	728	1213	java/net/SocketException
    //   775	785	1213	java/net/SocketException
    //   809	820	1213	java/net/SocketException
    //   906	920	1213	java/net/SocketException
    //   1202	1213	1213	java/net/SocketException
    //   1385	1390	1396	java/lang/Throwable
    //   1406	1411	1417	java/lang/Throwable
    //   1472	1477	1480	java/lang/Throwable
    //   1488	1493	1496	java/lang/Throwable
    //   86	94	1520	finally
    //   98	116	1528	finally
    //   920	939	1536	finally
    //   944	954	1536	finally
    //   960	968	1536	finally
    //   968	975	1536	finally
    //   1068	1080	1536	finally
    //   1083	1094	1536	finally
    //   985	998	1544	finally
    //   1115	1128	1544	finally
    //   1002	1016	1552	finally
    //   1016	1023	1560	finally
    //   1028	1047	1560	finally
    //   1149	1157	1560	finally
    //   98	116	1572	java/lang/Throwable
    //   140	153	1580	java/lang/Throwable
    //   177	185	1580	java/lang/Throwable
    //   209	219	1580	java/lang/Throwable
    //   243	254	1580	java/lang/Throwable
    //   278	289	1580	java/lang/Throwable
    //   313	324	1580	java/lang/Throwable
    //   348	360	1580	java/lang/Throwable
    //   384	395	1580	java/lang/Throwable
    //   419	430	1580	java/lang/Throwable
    //   461	466	1580	java/lang/Throwable
    //   490	520	1580	java/lang/Throwable
    //   544	554	1580	java/lang/Throwable
    //   578	588	1580	java/lang/Throwable
    //   612	624	1580	java/lang/Throwable
    //   648	655	1580	java/lang/Throwable
    //   679	690	1580	java/lang/Throwable
    //   714	728	1580	java/lang/Throwable
    //   775	785	1580	java/lang/Throwable
    //   809	820	1580	java/lang/Throwable
    //   906	920	1580	java/lang/Throwable
    //   1202	1213	1580	java/lang/Throwable
    //   920	939	1584	java/lang/Throwable
    //   944	954	1584	java/lang/Throwable
    //   960	968	1584	java/lang/Throwable
    //   968	975	1584	java/lang/Throwable
    //   1068	1080	1584	java/lang/Throwable
    //   1083	1094	1584	java/lang/Throwable
    //   985	998	1592	java/lang/Throwable
    //   1115	1128	1592	java/lang/Throwable
    //   1002	1016	1600	java/lang/Throwable
    //   1016	1023	1608	java/lang/Throwable
    //   1028	1047	1608	java/lang/Throwable
    //   1149	1157	1608	java/lang/Throwable
    //   98	116	1620	org/apache/http/conn/ConnectTimeoutException
    //   140	153	1628	org/apache/http/conn/ConnectTimeoutException
    //   177	185	1628	org/apache/http/conn/ConnectTimeoutException
    //   209	219	1628	org/apache/http/conn/ConnectTimeoutException
    //   243	254	1628	org/apache/http/conn/ConnectTimeoutException
    //   278	289	1628	org/apache/http/conn/ConnectTimeoutException
    //   313	324	1628	org/apache/http/conn/ConnectTimeoutException
    //   348	360	1628	org/apache/http/conn/ConnectTimeoutException
    //   384	395	1628	org/apache/http/conn/ConnectTimeoutException
    //   419	430	1628	org/apache/http/conn/ConnectTimeoutException
    //   461	466	1628	org/apache/http/conn/ConnectTimeoutException
    //   490	520	1628	org/apache/http/conn/ConnectTimeoutException
    //   544	554	1628	org/apache/http/conn/ConnectTimeoutException
    //   578	588	1628	org/apache/http/conn/ConnectTimeoutException
    //   612	624	1628	org/apache/http/conn/ConnectTimeoutException
    //   648	655	1628	org/apache/http/conn/ConnectTimeoutException
    //   679	690	1628	org/apache/http/conn/ConnectTimeoutException
    //   714	728	1628	org/apache/http/conn/ConnectTimeoutException
    //   775	785	1628	org/apache/http/conn/ConnectTimeoutException
    //   809	820	1628	org/apache/http/conn/ConnectTimeoutException
    //   906	920	1628	org/apache/http/conn/ConnectTimeoutException
    //   1202	1213	1628	org/apache/http/conn/ConnectTimeoutException
    //   920	939	1632	org/apache/http/conn/ConnectTimeoutException
    //   944	954	1632	org/apache/http/conn/ConnectTimeoutException
    //   960	968	1632	org/apache/http/conn/ConnectTimeoutException
    //   968	975	1632	org/apache/http/conn/ConnectTimeoutException
    //   1068	1080	1632	org/apache/http/conn/ConnectTimeoutException
    //   1083	1094	1632	org/apache/http/conn/ConnectTimeoutException
    //   985	998	1640	org/apache/http/conn/ConnectTimeoutException
    //   1115	1128	1640	org/apache/http/conn/ConnectTimeoutException
    //   1002	1016	1648	org/apache/http/conn/ConnectTimeoutException
    //   1016	1023	1656	org/apache/http/conn/ConnectTimeoutException
    //   1028	1047	1656	org/apache/http/conn/ConnectTimeoutException
    //   1149	1157	1656	org/apache/http/conn/ConnectTimeoutException
    //   98	116	1668	java/net/SocketTimeoutException
    //   140	153	1676	java/net/SocketTimeoutException
    //   177	185	1676	java/net/SocketTimeoutException
    //   209	219	1676	java/net/SocketTimeoutException
    //   243	254	1676	java/net/SocketTimeoutException
    //   278	289	1676	java/net/SocketTimeoutException
    //   313	324	1676	java/net/SocketTimeoutException
    //   348	360	1676	java/net/SocketTimeoutException
    //   384	395	1676	java/net/SocketTimeoutException
    //   419	430	1676	java/net/SocketTimeoutException
    //   461	466	1676	java/net/SocketTimeoutException
    //   490	520	1676	java/net/SocketTimeoutException
    //   544	554	1676	java/net/SocketTimeoutException
    //   578	588	1676	java/net/SocketTimeoutException
    //   612	624	1676	java/net/SocketTimeoutException
    //   648	655	1676	java/net/SocketTimeoutException
    //   679	690	1676	java/net/SocketTimeoutException
    //   714	728	1676	java/net/SocketTimeoutException
    //   775	785	1676	java/net/SocketTimeoutException
    //   809	820	1676	java/net/SocketTimeoutException
    //   906	920	1676	java/net/SocketTimeoutException
    //   1202	1213	1676	java/net/SocketTimeoutException
    //   920	939	1680	java/net/SocketTimeoutException
    //   944	954	1680	java/net/SocketTimeoutException
    //   960	968	1680	java/net/SocketTimeoutException
    //   968	975	1680	java/net/SocketTimeoutException
    //   1068	1080	1680	java/net/SocketTimeoutException
    //   1083	1094	1680	java/net/SocketTimeoutException
    //   985	998	1688	java/net/SocketTimeoutException
    //   1115	1128	1688	java/net/SocketTimeoutException
    //   1002	1016	1696	java/net/SocketTimeoutException
    //   1016	1023	1704	java/net/SocketTimeoutException
    //   1028	1047	1704	java/net/SocketTimeoutException
    //   1149	1157	1704	java/net/SocketTimeoutException
    //   86	94	1716	java/net/SocketException
    //   98	116	1724	java/net/SocketException
    //   920	939	1732	java/net/SocketException
    //   944	954	1732	java/net/SocketException
    //   960	968	1732	java/net/SocketException
    //   968	975	1732	java/net/SocketException
    //   1068	1080	1732	java/net/SocketException
    //   1083	1094	1732	java/net/SocketException
    //   985	998	1740	java/net/SocketException
    //   1115	1128	1740	java/net/SocketException
    //   1002	1016	1748	java/net/SocketException
    //   1016	1023	1756	java/net/SocketException
    //   1028	1047	1756	java/net/SocketException
    //   1149	1157	1756	java/net/SocketException
    //   86	94	1768	java/net/UnknownHostException
    //   98	116	1778	java/net/UnknownHostException
    //   1002	1016	1788	java/net/UnknownHostException
    //   140	153	1857	finally
    //   177	185	1857	finally
    //   209	219	1857	finally
    //   243	254	1857	finally
    //   278	289	1857	finally
    //   313	324	1857	finally
    //   348	360	1857	finally
    //   384	395	1857	finally
    //   419	430	1857	finally
    //   461	466	1857	finally
    //   490	520	1857	finally
    //   544	554	1857	finally
    //   578	588	1857	finally
    //   612	624	1857	finally
    //   648	655	1857	finally
    //   679	690	1857	finally
    //   714	728	1857	finally
    //   775	785	1857	finally
    //   809	820	1857	finally
    //   906	920	1857	finally
    //   1202	1213	1857	finally
    //   1238	1249	1857	finally
    //   1273	1284	1857	finally
    //   1308	1319	1857	finally
    //   1343	1354	1857	finally
    //   86	94	1885	java/net/SocketTimeoutException
    //   86	94	1893	org/apache/http/conn/ConnectTimeoutException
    //   86	94	1901	java/lang/Throwable
  }
}


/* Location:              /Users/joshua/Desktop/system_framework/classes-dex2jar.jar!/com/aps/l.class
 * Java compiler version: 6 (50.0)
 * JD-Core Version:       0.7.1
 */